Workbook

Sheet README
A1: L3 Agent (Controller) — Reusable Solution Benchmark KPIs
A2: Zion Quality Platform · Sol PE grp1 / grp2 / grp3 · companion to wf2c_l3_agent_kpi_benchmark_light.html (sections A–E)
A4: Purpose | B4: One benchmark for every L3 AI agent, ML model, heuristic and business-logic component across STLC phases 1–10, so each capability is built once, certified, and reused by all three Sol PE groups.
A6: Sheet | B6: What it holds
A7: A_Scoring_Model | B7: Section A — six weighted dimensions, generic KPIs, scoring parameters, six mandatory gates, five eligibility tiers. Weights and thresholds here drive every formula.
A8: B_Evaluation_Flow | B8: Section B — the eight steps from registering an idea to quarterly re-benchmarking, with owner, inputs, outputs and exit criterion.
A9: C_Components | B9: Section C — the 30 L3 components: phase, type, technique, reusable I/O contract, golden benchmark set, shared services, KPI counts.
A10: C_KPI_Benchmark | B10: Section C — detailed KPI catalogue: one row per KPI per component with dimension, unit, direction, Target (Tier 1), Min floor and measurement method.
A11: D_Shared_Services | B11: Section D — ten shared platform services and a component × service usage matrix.
A12: E_Measurements | B12: Section E — enter each group's measured value per KPI; KPI scores (0–100) calculate automatically.
A13: E_Scorecard | B13: Section E — per component and group: dimension scores, composite, gates, tier and rank.
A14: E_Summary | B14: Section E — per component: leading group, composite, tier and the action for all groups.
A16: Legend
A17: Yellow fill | B17: Input cell — enter values here (E_Measurements group values, E_Scorecard gates G1–G4 and G6).
A18: Blue text | B18: Hardcoded benchmark values (weights, thresholds, KPI targets and floors) — change only with review board approval.
A19: Black text | B19: Formulas — do not overwrite.
A20: Green text | B20: Links pulled from another sheet.
A22: How to score
A23: 1 | B23: In E_Measurements, enter the measured value on the golden set for each KPI and group. Percent KPIs as percentages (e.g. 94%), Yes/No KPIs as 1 = Yes, 0 = No.
A24: 2 | B24: KPI score = 100 at or beyond Target, 60 at the Min floor, linear between, 0 beyond the floor. KPIs without a defined Min use the default tolerance in A_Scoring_Model.
A25: 3 | B25: In E_Scorecard, set gates G1–G4 and G6 to Y or N. G5 (efficacy floors) is computed. Composite, tier and rank calculate once all six dimensions have at least one measured KPI.
A26: 4 | B26: E_Summary shows the leading eligible solution per component. Tier 1 becomes the Sol PE standard.
A28: Example data | B28: Component L3-1.a (NL Req Parsing & Classification Agent) is pre-filled with ILLUSTRATIVE values for grp1, grp2 and grp3 to show the mechanics. Replace them with real benchmark results.
A29: Source | B29: All targets and floors: proposed benchmark v1.0 (wf2c page, September 2026), to be confirmed by the cross-group review board.

Sheet A_Scoring_Model
A1: A · Scoring model
A2: Six dimensions every L3 solution is measured on; weights are fixed across all 30 components so rankings are comparable
A4: Dim | B4: Dimension | C4: Weight | D4: Generic KPIs applied to every component
A5: D1 | B5: Functional efficacy | C5: 0.3 | D5: Component KPIs in C_KPI_Benchmark on the shared golden set · must beat the current manual / tool baseline · every D1 KPI ≥ Min (gate G5)
A6: D2 | B6: Reuse & genericity | C6: 0.2 | D6: Portability: ≥3 product lines (NVMe SSD, UFS, eMMC/uSD, PSSD) with ≤10% efficacy drop · ≥90% of specifics in config · versioned OpenAPI / JSON Schema I/O · uses shared services · adopted by ≥2 of 3 groups within 2 quarters · onboarding ≤2 days
A7: D3 | B7: Scalability & performance | C7: 0.15 | D7: p95 latency / throughput at component target · 10× load with ≤20% latency degradation · stateless, horizontally scalable on Zion K8s · cost per 1k runs at or below benchmark · fits on-prem GPU budget
A8: D4 | B8: Reliability & trust | C8: 0.1 | D8: Run-to-run consistency ≥95% · hallucination / fabricated output at or below target · evidence or citation on every output · availability ≥99.5% · graceful fallback to rules or a human
A9: D5 | B9: Business value | C9: 0.15 | D9: Effort saved vs manual baseline · SME accept-without-edit rate · cycle-time reduction of the STLC activity · monthly active users across groups
A10: D6 | B10: Governance & maintainability | C10: 0.1 | D10: Solution code test coverage ≥80% · Review Shield 0 critical · SAST 0 high, 0 secrets, data on-prem · model card, data sheet, README, runbook · MLOps drift monitor + registry · named owner and support SLA
B11: Total (must be 100%) | C11: =SUM(C5:C10) -> 1 | D11: =IF(ROUND(C11,4)=1,"OK — weights sum to 100%","CHECK — weights must sum to 100%") -> OK — weights sum to 100%
A13: Scoring parameters
B14: Score at or beyond Target | C14: 100 | D14: KPI score formula: 100 at/beyond Target · 60 at Min · linear between · 0 beyond Min
B15: Score at the Min floor | C15: 60
B16: Default tolerance for KPIs without a defined Min | C16: 0.2 | D16: Assumption: a KPI with no Min floor is interpolated between Target and Target relaxed by this tolerance (Yes/No and zero-target KPIs become pass / fail).
B17: Challenger margin to replace a champion (points) | C17: 5 | D17: Challenger replaces champion only if composite ≥ champion + margin and no gate regresses
A19: Mandatory gates — any failure makes a solution ineligible
A20: Gate | B20: Name | C20: Check | D20: Rule
A21: G1 | B21: Registered first | C21: Input | D21: Registered in the Zion Capability Registry before development starts; duplicate check done against existing Tier-1/Tier-2 components.
A22: G2 | B22: Reproducible benchmark | C22: Input | D22: Benchmarked on the shared golden dataset with a reproducible harness (versioned data, fixed seeds, scripted run).
A23: G3 | B23: Data stays on-prem | C23: Input | D23: Customer specs, logs and telemetry processed only through the approved on-prem LLM / Zion LLM gateway.
A24: G4 | B24: Human in the loop | C24: Input | D24: Human approval for irreversible actions: closing defects, granting access, release Go, committing healed scripts.
A25: G5 | B25: Efficacy floors met | C25: Auto | D25: Every D1 efficacy KPI at or above its Min floor (computed from E_Measurements).
A26: G6 | B26: Documentation complete | C26: Input | D26: README, I/O contract, model card, runbook, benchmark report.
A28: Eligibility tiers by composite score
A29: Tier | B29: Tier name | C29: Min composite | D29: What it means for the groups
A30: T1 | B30: Tier 1 · Certified | C30: 85 | D30: Platform standard. Mandatory reuse across grp1/2/3; new builds of this capability are blocked.
A31: T2 | B31: Tier 2 · Conditional | C31: 75 | D31: Reusable with a named improvement plan; re-benchmark in one quarter.
A32: T3 | B32: Tier 3 · Group-local | C32: 60 | D32: Usable within the owning group only; not listed in the shared catalog.
A33: T4 | B33: Tier 4 · Rework | C33: 45 | D33: Not for production use; merge effort into the leading solution.
A34: — | B34: Not eligible | C34: < T4 or gate fail | D34: Composite below the Tier 4 minimum, or any gate failed. Retire, or fix the failed gate and resubmit.
A36: Composite = Σ weight × dimension score = 0.30·D1 + 0.20·D2 + 0.15·D3 + 0.10·D4 + 0.15·D5 + 0.10·D6 · Dimension score = mean of its KPI scores · Tie-break: higher D1 → lower cost per 1k runs → more groups already adopting

Sheet B_Evaluation_Flow
A1: B · Evaluation flow
A2: From idea to certified reusable component
A4: Step | B4: Name | C4: What happens | D4: Owner | E4: Input | F4: Output | G4: Exit criterion
A5: 1 | B5: Register intent | C5: Group files the capability in the Zion Capability Registry with its L3 ID (e.g. L3-1.a). | D5: Proposing group lead | E5: Capability idea, target phase | F5: Registry entry | G5: Entry exists before any development (G1)
A6: 2 | B6: Duplicate check | C6: Registry searched for Tier-1/2 solutions of the same capability; if one exists the group extends it instead of building new. | D6: Review board + Zion platform team | E6: Registry entry | F6: Build / extend decision | G6: Decision recorded in registry
A7: 3 | B7: Build to contract | C7: Implement the reusable I/O contract and use the shared services (D_Shared_Services). | D7: Component owner | E7: L3 contract, shared services | F7: Solution + docs pack | G7: Contract tests pass; docs pack complete (G6)
A8: 4 | B8: Benchmark run | C8: Automated harness on the shared golden set produces the KPI report. | D8: Golden-set owner + component owner | E8: Solution, golden set | F8: KPI report (E_Measurements values) | G8: Reproducible run, versioned data and seeds (G2)
A9: 5 | B9: Score & gate | C9: KPI scores roll up to six dimensions and a composite; six gates checked. | D9: Component owner | E9: KPI report | F9: E_Scorecard row | G9: All six dimensions scored
A10: 6 | B10: Cross-group review | C10: grp1/2/3 leads and AI champions validate the evidence and gate status. | D10: Cross-group review board | E10: Scorecard + evidence | F10: Validated scores | G10: Board sign-off
A11: 7 | B11: Rank & publish | C11: Tier assigned; Tier 1 is published to the shared catalog as the Sol PE standard. | D11: Cross-group review board | E11: Validated scores | F11: Tier + catalog entry | G11: E_Summary updated and communicated
A12: 8 | B12: Quarterly re-benchmark | C12: Champion vs challenger on the grown golden set; challenger wins only by ≥ margin with no gate regression. | D12: Review board + all groups | E12: New submissions, updated golden set | F12: Updated tiers | G12: Re-benchmark completed each quarter

Sheet C_Components
A1: C · L3 component register — 30 components, STLC phases 1–10
A2: Reusable I/O contract, technique, golden benchmark set and shared services per component
A4: Phase | B4: Phase name | C4: L3 ID | D4: L3 component | E4: Type | F4: Technique | G4: Input (contract) | H4: Output (contract) | I4: Golden benchmark set | J4: Shared services | K4: KPIs total | L4: D1 KPIs | M4: D1 KPIs with floor
A5: 1 | B5: Requirements Analysis & Review | C5: 1.a | D5: NL Req Parsing & Classification Agent | E5: AI + HX | F5: LLM extraction + taxonomy classifier; clause-level chunking | G5: Spec / PRD (PDF, DOCX, ReqIF) | H5: Atomic requirements JSON {id, text, type, priority, source clause} | I5: 5 annotated specs (NVMe 2.0 Base, ZNS, UFS 4.0, 2 internal PRDs), ~2,500 labelled requirements | J5: LLM gateway, Spec &, golden harness | K5: =COUNTIF(C_KPI_Benchmark!$D$5:$D$546,C5) -> 19 | L5: =COUNTIFS(C_KPI_Benchmark!$D$5:$D$546,C5,C_KPI_Benchmark!$F$5:$F$546,"D1") -> 3 | M5: =COUNTIFS(C_KPI_Benchmark!$D$5:$D$546,C5,C_KPI_Benchmark!$F$5:$F$546,"D1",C_KPI_Benchmark!$P$5:$P$546,"Defined") -> 3
A6: 1 | B6: Requirements Analysis & Review | C6: 1.b | D6: Feasibility & Quality Analyzer | E6: AI + HX | F6: LLM rubric on ISO/IEC/IEEE 29148 attributes + ambiguity lexicon | G6: Atomic requirements | H6: Flags {ambiguous, untestable, incomplete, conflicting} + rewrite suggestion | I6: 800 requirements with SME-labelled 29148 defects + 120 known conflict pairs | J6: LLM gateway, Embedding &, Rule &, golden harness | K6: =COUNTIF(C_KPI_Benchmark!$D$5:$D$546,C6) -> 18 | L6: =COUNTIFS(C_KPI_Benchmark!$D$5:$D$546,C6,C_KPI_Benchmark!$F$5:$F$546,"D1") -> 4 | M6: =COUNTIFS(C_KPI_Benchmark!$D$5:$D$546,C6,C_KPI_Benchmark!$F$5:$F$546,"D1",C_KPI_Benchmark!$P$5:$P$546,"Defined") -> 4
A7: 1 | B7: Requirements Analysis & Review | C7: 1.c | D7: RTM Auto-Generator + Risk Scoring | E7: AI + HX | F7: Semantic linking + traceability graph; likelihood × impact risk heuristic | G7: Requirements + test cases | H7: RTM links {req, tc, confidence} + risk score 1–25 | I7: Curated RTMs from 2 released products (~6k links) with SME risk rankings | J7: LLM gateway, Embedding &, Risk scoring, golden harness | K7: =COUNTIF(C_KPI_Benchmark!$D$5:$D$546,C7) -> 19 | L7: =COUNTIFS(C_KPI_Benchmark!$D$5:$D$546,C7,C_KPI_Benchmark!$F$5:$F$546,"D1") -> 4 | M7: =COUNTIFS(C_KPI_Benchmark!$D$5:$D$546,C7,C_KPI_Benchmark!$F$5:$F$546,"D1",C_KPI_Benchmark!$P$5:$P$546,"Defined") -> 4
A8: 2 | B8: Test Planning | C8: 2.a | D8: Test Strategy AI Advisor | E8: AI | F8: RAG over strategy templates and past strategies + LLM drafting | G8: Scope, risk register, product type | H8: Strategy draft {levels, types, techniques, entry/exit} | I8: 20 approved historical strategies + SME scoring rubric | J8: LLM gateway, Spec &, Report &, golden harness | K8: =COUNTIF(C_KPI_Benchmark!$D$5:$D$546,C8) -> 17 | L8: =COUNTIFS(C_KPI_Benchmark!$D$5:$D$546,C8,C_KPI_Benchmark!$F$5:$F$546,"D1") -> 3 | M8: =COUNTIFS(C_KPI_Benchmark!$D$5:$D$546,C8,C_KPI_Benchmark!$F$5:$F$546,"D1",C_KPI_Benchmark!$P$5:$P$546,"Defined") -> 3
A9: 2 | B9: Test Planning | C9: 2.b | D9: Effort Estimator ML Model | E9: ML | F9: Gradient boosting / quantile regression on historical effort | G9: Features {req count, complexity, TC count, reuse %, FW delta} | H9: Person-days P10 / P50 / P90 | I9: ≥150 closed projects, planned vs actual effort, time-split hold-out | J9: MLOps pipeline, golden harness | K9: =COUNTIF(C_KPI_Benchmark!$D$5:$D$546,C9) -> 18 | L9: =COUNTIFS(C_KPI_Benchmark!$D$5:$D$546,C9,C_KPI_Benchmark!$F$5:$F$546,"D1") -> 3 | M9: =COUNTIFS(C_KPI_Benchmark!$D$5:$D$546,C9,C_KPI_Benchmark!$F$5:$F$546,"D1",C_KPI_Benchmark!$P$5:$P$546,"Defined") -> 3
A10: 2 | B10: Test Planning | C10: 2.c | D10: Risk Scoring & Plan Generator | E10: HX + AI | F10: FMEA RPN heuristic + LLM plan writer | G10: Features, risk items, strategy | H10: RPN scores, mitigations, test plan (MD / DOCX / Confluence) | I10: 15 plans with SME risk rankings and review comments | J10: LLM gateway, Risk scoring, Rule &, Report &, golden harness | K10: =COUNTIF(C_KPI_Benchmark!$D$5:$D$546,C10) -> 17 | L10: =COUNTIFS(C_KPI_Benchmark!$D$5:$D$546,C10,C_KPI_Benchmark!$F$5:$F$546,"D1") -> 3 | M10: =COUNTIFS(C_KPI_Benchmark!$D$5:$D$546,C10,C_KPI_Benchmark!$F$5:$F$546,"D1",C_KPI_Benchmark!$P$5:$P$546,"Defined") -> 3
A11: 3 | B11: Test Design & Development | C11: 3.a | D11: Scenario + LLM Test Case Gen Agent | E11: AI + HX | F11: LLM + technique heuristics (EP, BVA, pairwise, state transition) | G11: Atomic requirement + domain pack | H11: TCs {pre, steps, expected, technique, req link} | I11: NVMe Format NVM, Sanitize, Get Log Page expert suites (~1,500 TCs) + seeded mutants | J11: LLM gateway, Embedding &, golden harness | K11: =COUNTIF(C_KPI_Benchmark!$D$5:$D$546,C11) -> 19 | L11: =COUNTIFS(C_KPI_Benchmark!$D$5:$D$546,C11,C_KPI_Benchmark!$F$5:$F$546,"D1") -> 4 | M11: =COUNTIFS(C_KPI_Benchmark!$D$5:$D$546,C11,C_KPI_Benchmark!$F$5:$F$546,"D1",C_KPI_Benchmark!$P$5:$P$546,"Defined") -> 4
A12: 3 | B12: Test Design & Development | C12: 3.b | D12: BDD Writer & Data Synth Agent | E12: AI + HX | F12: LLM Gherkin writer + constraint-based / generative data synthesis | G12: TC or requirement; data schema + constraints | H12: .feature files; synthetic datasets | I12: 300 reference scenarios + 20 data schemas with constraint oracles | J12: LLM gateway, golden harness | K12: =COUNTIF(C_KPI_Benchmark!$D$5:$D$546,C12) -> 17 | L12: =COUNTIFS(C_KPI_Benchmark!$D$5:$D$546,C12,C_KPI_Benchmark!$F$5:$F$546,"D1") -> 4 | M12: =COUNTIFS(C_KPI_Benchmark!$D$5:$D$546,C12,C_KPI_Benchmark!$F$5:$F$546,"D1",C_KPI_Benchmark!$P$5:$P$546,"Defined") -> 4
A13: 3 | B13: Test Design & Development | C13: 3.c | D13: Script Dev/Review & Coverage Agent | E13: AI + HX | F13: Code LLM + static analysis + coverage-gap heuristics | G13: TC; existing scripts; coverage data | H13: Automation script; review findings; coverage-gap list | I13: 200 TC→script reference pairs + seeded-defect review set | J13: LLM gateway, Log parser, golden harness | K13: =COUNTIF(C_KPI_Benchmark!$D$5:$D$546,C13) -> 18 | L13: =COUNTIFS(C_KPI_Benchmark!$D$5:$D$546,C13,C_KPI_Benchmark!$F$5:$F$546,"D1") -> 3 | M13: =COUNTIFS(C_KPI_Benchmark!$D$5:$D$546,C13,C_KPI_Benchmark!$F$5:$F$546,"D1",C_KPI_Benchmark!$P$5:$P$546,"Defined") -> 3
A14: 3 | B14: Test Design & Development | C14: 3.d | D14: AI Code Review Agent (Review Shield) | E14: AI + HX | F14: LLM reviewer over MR diff with Graph RAG branch context, layered on SAM static analysis and linters | G14: MR diff + changed-line summary; branch Graph RAG context; static-analysis output; per-repo feature config | H14: Risk summary + capped review comments {file, line, severity, type, issue, fix} | I14: ≥200 seeded, SME-labelled defects across C/C++ firmware, Python backend and TypeScript/Angular repos + clean diffs for false-positive measurement | J14: LLM gateway, Embedding &, Log parser, Rule &, Report &, MLOps pipeline, golden harness | K14: =COUNTIF(C_KPI_Benchmark!$D$5:$D$546,C14) -> 34 | L14: =COUNTIFS(C_KPI_Benchmark!$D$5:$D$546,C14,C_KPI_Benchmark!$F$5:$F$546,"D1") -> 7 | M14: =COUNTIFS(C_KPI_Benchmark!$D$5:$D$546,C14,C_KPI_Benchmark!$F$5:$F$546,"D1",C_KPI_Benchmark!$P$5:$P$546,"Defined") -> 7
A15: 4 | B15: Test Environment Setup | C15: 4.a | D15: IaC Provisioner Agent | E15: AI + BL | F15: LLM → Terraform / Ansible + policy-as-code checks | G15: Env spec {host OS, kernel, driver, FW, tools} | H15: IaC modules + provisioned rig / VM / pod | I15: 25 reference environment specs with expected end-state | J15: LLM gateway, Rule &, golden harness | K15: =COUNTIF(C_KPI_Benchmark!$D$5:$D$546,C15) -> 18 | L15: =COUNTIFS(C_KPI_Benchmark!$D$5:$D$546,C15,C_KPI_Benchmark!$F$5:$F$546,"D1") -> 3 | M15: =COUNTIFS(C_KPI_Benchmark!$D$5:$D$546,C15,C_KPI_Benchmark!$F$5:$F$546,"D1",C_KPI_Benchmark!$P$5:$P$546,"Defined") -> 3
A16: 4 | B16: Test Environment Setup | C16: 4.b | D16: Env Validator & Drift Detector | E16: ML + BL | F16: Golden-config diff rules + anomaly model on inventory snapshots | G16: Rig inventory snapshot | H16: Health status + drift items {expected, actual} | I16: 100 seeded-drift scenarios on reference rigs | J16: Time-series anomaly, MLOps pipeline, golden harness | K16: =COUNTIF(C_KPI_Benchmark!$D$5:$D$546,C16) -> 16 | L16: =COUNTIFS(C_KPI_Benchmark!$D$5:$D$546,C16,C_KPI_Benchmark!$F$5:$F$546,"D1") -> 3 | M16: =COUNTIFS(C_KPI_Benchmark!$D$5:$D$546,C16,C_KPI_Benchmark!$F$5:$F$546,"D1",C_KPI_Benchmark!$P$5:$P$546,"Defined") -> 3
... A35: 10 | B35: Post-Release & Prod. Monitoring | C35: 10.c | D35: Hotfix Triage & MLOps Pipeline | E35: HX + ML | F35: Hotfix priority heuristic + targeted regression + champion / challenger retraining | G35: Field issues; feedback data | H35: Hotfix priority + targeted suite; retrained model versions | I35: 60 historical hotfixes | J35: MLOps pipeline, Risk scoring, golden harness | K35: =COUNTIF(C_KPI_Benchmark!$D$5:$D$546,C35) -> 17 | L35: =COUNTIFS(C_KPI_Benchmark!$D$5:$D$546,C35,C_KPI_Benchmark!$F$5:$F$546,"D1") -> 3 | M35: =COUNTIFS(C_KPI_Benchmark!$D$5:$D$546,C35,C_KPI_Benchmark!$F$5:$F$546,"D1",C_KPI_Benchmark!$P$5:$P$546,"Defined") -> 3
J38: Total KPIs | K38: =SUM(K5:K35) -> 542

Sheet C_KPI_Benchmark
A1: C · Benchmark KPIs per L3 component — STLC phases 1–10
A2: One row per KPI · Target = full score and Tier-1 requirement · Min = floor (below it the KPI scores 0; below it on a D1 KPI fails gate G5)
A4: KPI ID | B4: Phase | C4: Phase name | D4: L3 ID | E4: L3 component | F4: Dim | G4: Dimension | H4: Dim weight | I4: Scope | J4: KPI | K4: Unit | L4: Direction | M4: Cond. | N4: Target (Tier 1) | O4: Min floor | P4: Min source | Q4: Measurement method | R4: Golden benchmark set
A5: 1.a-D1-01 | B5: 1 | C5: Requirements Analysis & Review | D5: 1.a | E5: NL Req Parsing & Classification Agent | F5: D1 | G5: Functional efficacy | H5: =INDEX(A_Scoring_Model!$C$5:$C$10,MATCH(F5,A_Scoring_Model!$A$5:$A$10,0)) -> 0.3 | I5: Component-specific | J5: Atomic requirement extraction recall | K5: % | L5: Higher is better | M5: ≥ | N5: 0.95 | O5: 0.88 | P5: Defined | Q5: Automated harness run on the shared golden set | R5: 5 annotated specs (NVMe 2.0 Base, ZNS, UFS 4.0, 2 internal PRDs), ~2,500 labelled requirements
A6: 1.a-D1-02 | B6: 1 | C6: Requirements Analysis & Review | D6: 1.a | E6: NL Req Parsing & Classification Agent | F6: D1 | G6: Functional efficacy | H6: =INDEX(A_Scoring_Model!$C$5:$C$10,MATCH(F6,A_Scoring_Model!$A$5:$A$10,0)) -> 0.3 | I6: Component-specific | J6: Classification macro-F1 (func / perf / security / compliance / interface) | K6: F1 | L6: Higher is better | M6: ≥ | N6: 0.9 | O6: 0.82 | P6: Defined | Q6: Automated harness run on the shared golden set | R6: 5 annotated specs (NVMe 2.0 Base, ZNS, UFS 4.0, 2 internal PRDs), ~2,500 labelled requirements
A7: 1.a-D1-03 | B7: 1 | C7: Requirements Analysis & Review | D7: 1.a | E7: NL Req Parsing & Classification Agent | F7: D1 | G7: Functional efficacy | H7: =INDEX(A_Scoring_Model!$C$5:$C$10,MATCH(F7,A_Scoring_Model!$A$5:$A$10,0)) -> 0.3 | I7: Component-specific | J7: Source-clause traceability | K7: % | L7: Higher is better | M7: ≥ | N7: 1 | O7: 0.98 | P7: Defined | Q7: Automated harness run on the shared golden set | R7: 5 annotated specs (NVMe 2.0 Base, ZNS, UFS 4.0, 2 internal PRDs), ~2,500 labelled requirements
A8: 1.a-D2-04 | B8: 1 | C8: Requirements Analysis & Review | D8: 1.a | E8: NL Req Parsing & Classification Agent | F8: D2 | G8: Reuse & genericity | H8: =INDEX(A_Scoring_Model!$C$5:$C$10,MATCH(F8,A_Scoring_Model!$A$5:$A$10,0)) -> 0.2 | I8: Component-specific | J8: Taxonomy and rules in YAML / prompt packs, no code change per group | K8: Yes/No | L8: Higher is better | M8: ≥ | N8: 1 | P8: Default tolerance | Q8: Architecture review against the L3 contract + cross-product run
A9: 1.a-D2-05 | B9: 1 | C9: Requirements Analysis & Review | D9: 1.a | E9: NL Req Parsing & Classification Agent | F9: D2 | G9: Reuse & genericity | H9: =INDEX(A_Scoring_Model!$C$5:$C$10,MATCH(F9,A_Scoring_Model!$A$5:$A$10,0)) -> 0.2 | I9: Generic | J9: Product lines supported with ≤10% efficacy drop (NVMe SSD, UFS, eMMC/uSD, PSSD) | K9: count | L9: Higher is better | M9: ≥ | N9: 3 | O9: 2 | P9: Defined | Q9: Architecture review against the L3 contract + cross-product run
A10: 1.a-D2-06 | B10: 1 | C10: Requirements Analysis & Review | D10: 1.a | E10: NL Req Parsing & Classification Agent | F10: D2 | G10: Reuse & genericity | H10: =INDEX(A_Scoring_Model!$C$5:$C$10,MATCH(F10,A_Scoring_Model!$A$5:$A$10,0)) -> 0.2 | I10: Generic | J10: Uses Zion shared services instead of re-implementing them | K10: Yes/No | L10: Higher is better | M10: ≥ | N10: 1 | P10: Default tolerance | Q10: Architecture review against the L3 contract + cross-product run
A11: 1.a-D3-07 | B11: 1 | C11: Requirements Analysis & Review | D11: 1.a | E11: NL Req Parsing & Classification Agent | F11: D3 | G11: Scalability & performance | H11: =INDEX(A_Scoring_Model!$C$5:$C$10,MATCH(F11,A_Scoring_Model!$A$5:$A$10,0)) -> 0.15 | I11: Component-specific | J11: Throughput | K11: pages/hr | L11: Higher is better | M11: ≥ | N11: 300 | P11: Default tolerance | Q11: Load / performance test on Zion reference cluster
A12: 1.a-D3-08 | B12: 1 | C12: Requirements Analysis & Review | D12: 1.a | E12: NL Req Parsing & Classification Agent | F12: D3 | G12: Scalability & performance | H12: =INDEX(A_Scoring_Model!$C$5:$C$10,MATCH(F12,A_Scoring_Model!$A$5:$A$10,0)) -> 0.15 | I12: Component-specific | J12: p95 latency per page | K12: s | L12: Lower is better | M12: ≤ | N12: 8 | P12: Default tolerance | Q12: Load / performance test on Zion reference cluster
A13: 1.a-D3-09 | B13: 1 | C13: Requirements Analysis & Review | D13: 1.a | E13: NL Req Parsing & Classification Agent | F13: D3 | G13: Scalability & performance | H13: =INDEX(A_Scoring_Model!$C$5:$C$10,MATCH(F13,A_Scoring_Model!$A$5:$A$10,0)) -> 0.15 | I13: Generic | J13: Latency degradation at 10× load | K13: % | L13: Lower is better | M13: ≤ | N13: 0.2 | O13: 0.4 | P13: Defined | Q13: Load / performance test on Zion reference cluster
A14: 1.a-D4-10 | B14: 1 | C14: Requirements Analysis & Review | D14: 1.a | E14: NL Req Parsing & Classification Agent | F14: D4 | G14: Reliability & trust | H14: =INDEX(A_Scoring_Model!$C$5:$C$10,MATCH(F14,A_Scoring_Model!$A$5:$A$10,0)) -> 0.1 | I14: Component-specific | J14: Hallucinated requirements | K14: % | L14: Lower is better | M14: ≤ | N14: 0.01 | P14: Default tolerance | Q14: Repeat harness runs, audit log and ops monitoring
A15: 1.a-D4-11 | B15: 1 | C15: Requirements Analysis & Review | D15: 1.a | E15: NL Req Parsing & Classification Agent | F15: D4 | G15: Reliability & trust | H15: =INDEX(A_Scoring_Model!$C$5:$C$10,MATCH(F15,A_Scoring_Model!$A$5:$A$10,0)) -> 0.1 | I15: Component-specific | J15: Run-to-run agreement (temperature 0) | K15: % | L15: Higher is better | M15: ≥ | N15: 0.97 | P15: Default tolerance | Q15: Repeat harness runs, audit log and ops monitoring
A16: 1.a-D4-12 | B16: 1 | C16: Requirements Analysis & Review | D16: 1.a | E16: NL Req Parsing & Classification Agent | F16: D4 | G16: Reliability & trust | H16: =INDEX(A_Scoring_Model!$C$5:$C$10,MATCH(F16,A_Scoring_Model!$A$5:$A$10,0)) -> 0.1 | I16: Generic | J16: Service availability | K16: % | L16: Higher is better | M16: ≥ | N16: 0.995 | O16: 0.99 | P16: Defined | Q16: Repeat harness runs, audit log and ops monitoring
A17: 1.a-D5-13 | B17: 1 | C17: Requirements Analysis & Review | D17: 1.a | E17: NL Req Parsing & Classification Agent | F17: D5 | G17: Business value | H17: =INDEX(A_Scoring_Model!$C$5:$C$10,MATCH(F17,A_Scoring_Model!$A$5:$A$10,0)) -> 0.15 | I17: Component-specific | J17: Manual parsing effort reduction | K17: % | L17: Higher is better | M17: ≥ | N17: 0.6 | P17: Default tolerance | Q17: Pilot vs manual baseline, SME survey
A18: 1.a-D5-14 | B18: 1 | C18: Requirements Analysis & Review | D18: 1.a | E18: NL Req Parsing & Classification Agent | F18: D5 | G18: Business value | H18: =INDEX(A_Scoring_Model!$C$5:$C$10,MATCH(F18,A_Scoring_Model!$A$5:$A$10,0)) -> 0.15 | I18: Component-specific | J18: SME acceptance rate | K18: % | L18: Higher is better | M18: ≥ | N18: 0.85 | P18: Default tolerance | Q18: Pilot vs manual baseline, SME survey
A19: 1.a-D6-15 | B19: 1 | C19: Requirements Analysis & Review | D19: 1.a | E19: NL Req Parsing & Classification Agent | F19: D6 | G19: Governance & maintainability | H19: =INDEX(A_Scoring_Model!$C$5:$C$10,MATCH(F19,A_Scoring_Model!$A$5:$A$10,0)) -> 0.1 | I19: Generic | J19: Solution code test coverage | K19: % | L19: Higher is better | M19: ≥ | N19: 0.8 | O19: 0.6 | P19: Defined | Q19: CI reports (coverage, Review Shield, SAST) + doc review
A20: 1.a-D6-16 | B20: 1 | C20: Requirements Analysis & Review | D20: 1.a | E20: NL Req Parsing & Classification Agent | F20: D6 | G20: Governance & maintainability | H20: =INDEX(A_Scoring_Model!$C$5:$C$10,MATCH(F20,A_Scoring_Model!$A$5:$A$10,0)) -> 0.1 | I20: Generic | J20: Review Shield critical findings | K20: count | L20: Lower is better | M20: ≤ | N20: 0 | P20: Default tolerance | Q20: CI reports (coverage, Review Shield, SAST) + doc review
A21: 1.a-D6-17 | B21: 1 | C21: Requirements Analysis & Review | D21: 1.a | E21: NL Req Parsing & Classification Agent | F21: D6 | G21: Governance & maintainability | H21: =INDEX(A_Scoring_Model!$C$5:$C$10,MATCH(F21,A_Scoring_Model!$A$5:$A$10,0)) -> 0.1 | I21: Generic | J21: SAST high findings and exposed secrets | K21: count | L21: Lower is better | M21: ≤ | N21: 0 | P21: Default tolerance | Q21: CI reports (coverage, Review Shield, SAST) + doc review
A22: 1.a-D6-18 | B22: 1 | C22: Requirements Analysis & Review | D22: 1.a | E22: NL Req Parsing & Classification Agent | F22: D6 | G22: Governance & maintainability | H22: =INDEX(A_Scoring_Model!$C$5:$C$10,MATCH(F22,A_Scoring_Model!$A$5:$A$10,0)) -> 0.1 | I22: Generic | J22: Documentation pack complete (README, I/O contract, model card, runbook) | K22: Yes/No | L22: Higher is better | M22: ≥ | N22: 1 | P22: Default tolerance | Q22: CI reports (coverage, Review Shield, SAST) + doc review
A23: 1.a-D6-19 | B23: 1 | C23: Requirements Analysis & Review | D23: 1.a | E23: NL Req Parsing & Classification Agent | F23: D6 | G23: Governance & maintainability | H23: =INDEX(A_Scoring_Model!$C$5:$C$10,MATCH(F23,A_Scoring_Model!$A$5:$A$10,0)) -> 0.1 | I23: Generic | J23: Named owner and support SLA | K23: Yes/No | L23: Higher is better | M23: ≥ | N23: 1 | P23: Default tolerance | Q23: CI reports (coverage, Review Shield, SAST) + doc review
A24: 1.b-D1-01 | B24: 1 | C24: Requirements Analysis & Review | D24: 1.b | E24: Feasibility & Quality Analyzer | F24: D1 | G24: Functional efficacy | H24: =INDEX(A_Scoring_Model!$C$5:$C$10,MATCH(F24,A_Scoring_Model!$A$5:$A$10,0)) -> 0.3 | I24: Component-specific | J24: Requirement-defect detection precision | K24: ratio | L24: Higher is better | M24: ≥ | N24: 0.85 | O24: 0.75 | P24: Defined | Q24: Automated harness run on the shared golden set | R24: 800 requirements with SME-labelled 29148 defects + 120 known conflict pairs
A25: 1.b-D1-02 | B25: 1 | C25: Requirements Analysis & Review | D25: 1.b | E25: Feasibility & Quality Analyzer | F25: D1 | G25: Functional efficacy | H25: =INDEX(A_Scoring_Model!$C$5:$C$10,MATCH(F25,A_Scoring_Model!$A$5:$A$10,0)) -> 0.3 | I25: Component-specific | J25: Requirement-defect detection recall | K25: ratio | L25: Higher is better | M25: ≥ | N25: 0.8 | O25: 0.7 | P25: Defined | Q25: Automated harness run on the shared golden set | R25: 800 requirements with SME-labelled 29148 defects + 120 known conflict pairs
A26: 1.b-D1-03 | B26: 1 | C26: Requirements Analysis & Review | D26: 1.b | E26: Feasibility & Quality Analyzer | F26: D1 | G26: Functional efficacy | H26: =INDEX(A_Scoring_Model!$C$5:$C$10,MATCH(F26,A_Scoring_Model!$A$5:$A$10,0)) -> 0.3 | I26: Component-specific | J26: Conflicting-pair detection recall | K26: ratio | L26: Higher is better | M26: ≥ | N26: 0.75 | O26: 0.6 | P26: Defined | Q26: Automated harness run on the shared golden set | R26: 800 requirements with SME-labelled 29148 defects + 120 known conflict pairs
A27: 1.b-D1-04 | B27: 1 | C27: Requirements Analysis & Review | D27: 1.b | E27: Feasibility & Quality Analyzer | F27: D1 | G27: Functional efficacy | H27: =INDEX(A_Scoring_Model!$C$5:$C$10,MATCH(F27,A_Scoring_Model!$A$5:$A$10,0)) -> 0.3 | I27: Component-specific | J27: Rewrite suggestion acceptance | K27: % | L27: Higher is better | M27: ≥ | N27: 0.7 | O27: 0.55 | P27: Defined | Q27: Automated harness run on the shared golden set | R27: 800 requirements with SME-labelled 29148 defects + 120 known conflict pairs
A28: 1.b-D2-05 | B28: 1 | C28: Requirements Analysis & Review | D28: 1.b | E28: Feasibility & Quality Analyzer | F28: D2 | G28: Reuse & genericity | H28: =INDEX(A_Scoring_Model!$C$5:$C$10,MATCH(F28,A_Scoring_Model!$A$5:$A$10,0)) -> 0.2 | I28: Component-specific | J28: Pluggable rule packs (29148 + group checklists) | K28: Yes/No | L28: Higher is better | M28: ≥ | N28: 1 | P28: Default tolerance | Q28: Architecture review against the L3 contract + cross-product run
A29: 1.b-D2-06 | B29: 1 | C29: Requirements Analysis & Review | D29: 1.b | E29: Feasibility & Quality Analyzer | F29: D2 | G29: Reuse & genericity | H29: =INDEX(A_Scoring_Model!$C$5:$C$10,MATCH(F29,A_Scoring_Model!$A$5:$A$10,0)) -> 0.2 | I29: Generic | J29: Product lines supported with ≤10% efficacy drop (NVMe SSD, UFS, eMMC/uSD, PSSD) | K29: count | L29: Higher is better | M29: ≥ | N29: 3 | O29: 2 | P29: Defined | Q29: Architecture review against the L3 contract + cross-product run
A30: 1.b-D2-07 | B30: 1 | C30: Requirements Analysis & Review | D30: 1.b | E30: Feasibility & Quality Analyzer | F30: D2 | G30: Reuse & genericity | H30: =INDEX(A_Scoring_Model!$C$5:$C$10,MATCH(F30,A_Scoring_Model!$A$5:$A$10,0)) -> 0.2 | I30: Generic | J30: Uses Zion shared services instead of re-implementing them | K30: Yes/No | L30: Higher is better | M30: ≥ | N30: 1 | P30: Default tolerance | Q30: Architecture review against the L3 contract + cross-product run
A31: 1.b-D3-08 | B31: 1 | C31: Requirements Analysis & Review | D31: 1.b | E31: Feasibility & Quality Analyzer | F31: D3 | G31: Scalability & performance | H31: =INDEX(A_Scoring_Model!$C$5:$C$10,MATCH(F31,A_Scoring_Model!$A$5:$A$10,0)) -> 0.15 | I31: Component-specific | J31: Time to analyse 1,000 requirements | K31: min | L31: Lower is better | M31: ≤ | N31: 10 | P31: Default tolerance | Q31: Load / performance test on Zion reference cluster
A32: 1.b-D3-09 | B32: 1 | C32: Requirements Analysis & Review | D32: 1.b | E32: Feasibility & Quality Analyzer | F32: D3 | G32: Scalability & performance | H32: =INDEX(A_Scoring_Model!$C$5:$C$10,MATCH(F32,A_Scoring_Model!$A$5:$A$10,0)) -> 0.15 | I32: Generic | J32: Latency degradation at 10× load | K32: % | L32: Lower is better | M32: ≤ | N32: 0.2 | O32: 0.4 | P32: Defined | Q32: Load / performance test on Zion reference cluster
A33: 1.b-D4-10 | B33: 1 | C33: Requirements Analysis & Review | D33: 1.b | E33: Feasibility & Quality Analyzer | F33: D4 | G33: Reliability & trust | H33: =INDEX(A_Scoring_Model!$C$5:$C$10,MATCH(F33,A_Scoring_Model!$A$5:$A$10,0)) -> 0.1 | I33: Component-specific | J33: False alarm rate | K33: % | L33: Lower is better | M33: ≤ | N33: 0.15 | P33: Default tolerance | Q33: Repeat harness runs, audit log and ops monitoring
A34: 1.b-D4-11 | B34: 1 | C34: Requirements Analysis & Review | D34: 1.b | E34: Feasibility & Quality Analyzer | F34: D4 | G34: Reliability & trust | H34: =INDEX(A_Scoring_Model!$C$5:$C$10,MATCH(F34,A_Scoring_Model!$A$5:$A$10,0)) -> 0.1 | I34: Component-specific | J34: Flags citing rule + text span | K34: % | L34: Higher is better | M34: ≥ | N34: 1 | P34: Default tolerance | Q34: Repeat harness runs, audit log and ops monitoring
A35: 1.b-D4-12 | B35: 1 | C35: Requirements Analysis & Review | D35: 1.b | E35: Feasibility & Quality Analyzer | F35: D4 | G35: Reliability & trust | H35: =INDEX(A_Scoring_Model!$C$5:$C$10,MATCH(F35,A_Scoring_Model!$A$5:$A$10,0)) -> 0.1 | I35: Generic | J35: Service availability | K35: % | L35: Higher is better | M35: ≥ | N35: 0.995 | O35: 0.99 | P35: Defined | Q35: Repeat harness runs, audit log and ops monitoring
A36: 1.b-D5-13 | B36: 1 | C36: Requirements Analysis & Review | D36: 1.b | E36: Feasibility & Quality Analyzer | F36: D5 | G36: Business value | H36: =INDEX(A_Scoring_Model!$C$5:$C$10,MATCH(F36,A_Scoring_Model!$A$5:$A$10,0)) -> 0.15 | I36: Component-specific | J36: Requirement defects escaping into test design (reduction) | K36: % | L36: Higher is better | M36: ≥ | N36: 0.4 | P36: Default tolerance | Q36: Pilot vs manual baseline, SME survey
A37: 1.b-D6-14 | B37: 1 | C37: Requirements Analysis & Review | D37: 1.b | E37: Feasibility & Quality Analyzer | F37: D6 | G37: Governance & maintainability | H37: =INDEX(A_Scoring_Model!$C$5:$C$10,MATCH(F37,A_Scoring_Model!$A$5:$A$10,0)) -> 0.1 | I37: Generic | J37: Solution code test coverage | K37: % | L37: Higher is better | M37: ≥ | N37: 0.8 | O37: 0.6 | P37: Defined | Q37: CI reports (coverage, Review Shield, SAST) + doc review
A38: 1.b-D6-15 | B38: 1 | C38: Requirements Analysis & Review | D38: 1.b | E38: Feasibility & Quality Analyzer | F38: D6 | G38: Governance & maintainability | H38: =INDEX(A_Scoring_Model!$C$5:$C$10,MATCH(F38,A_Scoring_Model!$A$5:$A$10,0)) -> 0.1 | I38: Generic | J38: Review Shield critical findings | K38: count | L38: Lower is better | M38: ≤ | N38: 0 | P38: Default tolerance | Q38: CI reports (coverage, Review Shield, SAST) + doc review
A39: 1.b-D6-16 | B39: 1 | C39: Requirements Analysis & Review | D39: 1.b | E39: Feasibility & Quality Analyzer | F39: D6 | G39: Governance & maintainability | H39: =INDEX(A_Scoring_Model!$C$5:$C$10,MATCH(F39,A_Scoring_Model!$A$5:$A$10,0)) -> 0.1 | I39: Generic | J39: SAST high findings and exposed secrets | K39: count | L39: Lower is better | M39: ≤ | N39: 0 | P39: Default tolerance | Q39: CI reports (coverage, Review Shield, SAST) + doc review
A40: 1.b-D6-17 | B40: 1 | C40: Requirements Analysis & Review | D40: 1.b | E40: Feasibility & Quality Analyzer | F40: D6 | G40: Governance & maintainability | H40: =INDEX(A_Scoring_Model!$C$5:$C$10,MATCH(F40,A_Scoring_Model!$A$5:$A$10,0)) -> 0.1 | I40: Generic | J40: Documentation pack complete (README, I/O contract, model card, runbook) | K40: Yes/No | L40: Higher is better | M40: ≥ | N40: 1 | P40: Default tolerance | Q40: CI reports (coverage, Review Shield, SAST) + doc review
A41: 1.b-D6-18 | B41: 1 | C41: Requirements Analysis & Review | D41: 1.b | E41: Feasibility & Quality Analyzer | F41: D6 | G41: Governance & maintainability | H41: =INDEX(A_Scoring_Model!$C$5:$C$10,MATCH(F41,A_Scoring_Model!$A$5:$A$10,0)) -> 0.1 | I41: Generic | J41: Named owner and support SLA | K41: Yes/No | L41: Higher is better | M41: ≥ | N41: 1 | P41: Default tolerance | Q41: CI reports (coverage, Review Shield, SAST) + doc review
A42: 1.c-D1-01 | B42: 1 | C42: Requirements Analysis & Review | D42: 1.c | E42: RTM Auto-Generator + Risk Scoring | F42: D1 | G42: Functional efficacy | H42: =INDEX(A_Scoring_Model!$C$5:$C$10,MATCH(F42,A_Scoring_Model!$A$5:$A$10,0)) -> 0.3 | I42: Component-specific | J42: Trace-link precision | K42: ratio | L42: Higher is better | M42: ≥ | N42: 0.9 | O42: 0.8 | P42: Defined | Q42: Automated harness run on the shared golden set | R42: Curated RTMs from 2 released products (~6k links) with SME risk rankings
A43: 1.c-D1-02 | B43: 1 | C43: Requirements Analysis & Review | D43: 1.c | E43: RTM Auto-Generator + Risk Scoring | F43: D1 | G43: Functional efficacy | H43: =INDEX(A_Scoring_Model!$C$5:$C$10,MATCH(F43,A_Scoring_Model!$A$5:$A$10,0)) -> 0.3 | I43: Component-specific | J43: Trace-link recall | K43: ratio | L43: Higher is better | M43: ≥ | N43: 0.85 | O43: 0.75 | P43: Defined | Q43: Automated harness run on the shared golden set | R43: Curated RTMs from 2 released products (~6k links) with SME risk rankings
A44: 1.c-D1-03 | B44: 1 | C44: Requirements Analysis & Review | D44: 1.c | E44: RTM Auto-Generator + Risk Scoring | F44: D1 | G44: Functional efficacy | H44: =INDEX(A_Scoring_Model!$C$5:$C$10,MATCH(F44,A_Scoring_Model!$A$5:$A$10,0)) -> 0.3 | I44: Component-specific | J44: Risk rank vs SME (Spearman ρ) | K44: ρ | L44: Higher is better | M44: ≥ | N44: 0.75 | O44: 0.6 | P44: Defined | Q44: Automated harness run on the shared golden set | R44: Curated RTMs from 2 released products (~6k links) with SME risk rankings
A45: 1.c-D1-04 | B45: 1 | C45: Requirements Analysis & Review | D45: 1.c | E45: RTM Auto-Generator + Risk Scoring | F45: D1 | G45: Functional efficacy | H45: =INDEX(A_Scoring_Model!$C$5:$C$10,MATCH(F45,A_Scoring_Model!$A$5:$A$10,0)) -> 0.3 | I45: Component-specific | J45: Orphan requirement / TC detection | K45: % | L45: Higher is better | M45: ≥ | N45: 1 | O45: 0.98 | P45: Defined | Q45: Automated harness run on the shared golden set | R45: Curated RTMs from 2 released products (~6k links) with SME risk rankings
A46: 1.c-D2-05 | B46: 1 | C46: Requirements Analysis & Review | D46: 1.c | E46: RTM Auto-Generator + Risk Scoring | F46: D2 | G46: Reuse & genericity | H46: =INDEX(A_Scoring_Model!$C$5:$C$10,MATCH(F46,A_Scoring_Model!$A$5:$A$10,0)) -> 0.2 | I46: Component-specific | J46: ALM adapters available (Jira, Polarion, TestRail) | K46: count | L46: Higher is better | M46: ≥ | N46: 3 | P46: Default tolerance | Q46: Architecture review against the L3 contract + cross-product run
A47: 1.c-D2-06 | B47: 1 | C47: Requirements Analysis & Review | D47: 1.c | E47: RTM Auto-Generator + Risk Scoring | F47: D2 | G47: Reuse & genericity | H47: =INDEX(A_Scoring_Model!$C$5:$C$10,MATCH(F47,A_Scoring_Model!$A$5:$A$10,0)) -> 0.2 | I47: Generic | J47: Product lines supported with ≤10% efficacy drop (NVMe SSD, UFS, eMMC/uSD, PSSD) | K47: count | L47: Higher is better | M47: ≥ | N47: 3 | O47: 2 | P47: Defined | Q47: Architecture review against the L3 contract + cross-product run
A48: 1.c-D2-07 | B48: 1 | C48: Requirements Analysis & Review | D48: 1.c | E48: RTM Auto-Generator + Risk Scoring | F48: D2 | G48: Reuse & genericity | H48: =INDEX(A_Scoring_Model!$C$5:$C$10,MATCH(F48,A_Scoring_Model!$A$5:$A$10,0)) -> 0.2 | I48: Generic | J48: Uses Zion shared services instead of re-implementing them | K48: Yes/No | L48: Higher is better | M48: ≥ | N48: 1 | P48: Default tolerance | Q48: Architecture review against the L3 contract + cross-product run
A49: 1.c-D3-08 | B49: 1 | C49: Requirements Analysis & Review | D49: 1.c | E49: RTM Auto-Generator + Risk Scoring | F49: D3 | G49: Scalability & performance | H49: =INDEX(A_Scoring_Model!$C$5:$C$10,MATCH(F49,A_Scoring_Model!$A$5:$A$10,0)) -> 0.15 | I49: Component-specific | J49: Full link run: 10k reqs × 50k TCs | K49: min | L49: Lower is better | M49: ≤ | N49: 30 | P49: Default tolerance | Q49: Load / performance test on Zion reference cluster
A50: 1.c-D3-09 | B50: 1 | C50: Requirements Analysis & Review | D50: 1.c | E50: RTM Auto-Generator + Risk Scoring | F50: D3 | G50: Scalability & performance | H50: =INDEX(A_Scoring_Model!$C$5:$C$10,MATCH(F50,A_Scoring_Model!$A$5:$A$10,0)) -> 0.15 | I50: Component-specific | J50: Incremental re-link on delta | K50: min | L50: Lower is better | M50: ≤ | N50: 2 | P50: Default tolerance | Q50: Load / performance test on Zion reference cluster
A51: 1.c-D3-10 | B51: 1 | C51: Requirements Analysis & Review | D51: 1.c | E51: RTM Auto-Generator + Risk Scoring | F51: D3 | G51: Scalability & performance | H51: =INDEX(A_Scoring_Model!$C$5:$C$10,MATCH(F51,A_Scoring_Model!$A$5:$A$10,0)) -> 0.15 | I51: Generic | J51: Latency degradation at 10× load | K51: % | L51: Lower is better | M51: ≤ | N51: 0.2 | O51: 0.4 | P51: Defined | Q51: Load / performance test on Zion reference cluster
A52: 1.c-D4-11 | B52: 1 | C52: Requirements Analysis & Review | D52: 1.c | E52: RTM Auto-Generator + Risk Scoring | F52: D4 | G52: Reliability & trust | H52: =INDEX(A_Scoring_Model!$C$5:$C$10,MATCH(F52,A_Scoring_Model!$A$5:$A$10,0)) -> 0.1 | I52: Component-specific | J52: Low-confidence links (<0.6) routed to human review | K52: % | L52: Higher is better | M52: ≥ | N52: 1 | P52: Default tolerance | Q52: Repeat harness runs, audit log and ops monitoring
A53: 1.c-D4-12 | B53: 1 | C53: Requirements Analysis & Review | D53: 1.c | E53: RTM Auto-Generator + Risk Scoring | F53: D4 | G53: Reliability & trust | H53: =INDEX(A_Scoring_Model!$C$5:$C$10,MATCH(F53,A_Scoring_Model!$A$5:$A$10,0)) -> 0.1 | I53: Generic | J53: Service availability | K53: % | L53: Higher is better | M53: ≥ | N53: 0.995 | O53: 0.99 | P53: Defined | Q53: Repeat harness runs, audit log and ops monitoring
A54: 1.c-D5-13 | B54: 1 | C54: Requirements Analysis & Review | D54: 1.c | E54: RTM Auto-Generator + Risk Scoring | F54: D5 | G54: Business value | H54: =INDEX(A_Scoring_Model!$C$5:$C$10,MATCH(F54,A_Scoring_Model!$A$5:$A$10,0)) -> 0.15 | I54: Component-specific | J54: RTM creation effort reduction | K54: % | L54: Higher is better | M54: ≥ | N54: 0.7 | P54: Default tolerance | Q54: Pilot vs manual baseline, SME survey
A55: 1.c-D5-14 | B55: 1 | C55: Requirements Analysis & Review | D55: 1.c | E55: RTM Auto-Generator + Risk Scoring | F55: D5 | G55: Business value | H55: =INDEX(A_Scoring_Model!$C$5:$C$10,MATCH(F55,A_Scoring_Model!$A$5:$A$10,0)) -> 0.15 | I55: Component-specific | J55: Coverage gaps found before design | K55: % | L55: Higher is better | M55: ≥ | N55: 0.9 | P55: Default tolerance | Q55: Pilot vs manual baseline, SME survey
A56: 1.c-D6-15 | B56: 1 | C56: Requirements Analysis & Review | D56: 1.c | E56: RTM Auto-Generator + Risk Scoring | F56: D6 | G56: Governance & maintainability | H56: =INDEX(A_Scoring_Model!$C$5:$C$10,MATCH(F56,A_Scoring_Model!$A$5:$A$10,0)) -> 0.1 | I56: Generic | J56: Solution code test coverage | K56: % | L56: Higher is better | M56: ≥ | N56: 0.8 | O56: 0.6 | P56: Defined | Q56: CI reports (coverage, Review Shield, SAST) + doc review
A57: 1.c-D6-16 | B57: 1 | C57: Requirements Analysis & Review | D57: 1.c | E57: RTM Auto-Generator + Risk Scoring | F57: D6 | G57: Governance & maintainability | H57: =INDEX(A_Scoring_Model!$C$5:$C$10,MATCH(F57,A_Scoring_Model!$A$5:$A$10,0)) -> 0.1 | I57: Generic | J57: Review Shield critical findings | K57: count | L57: Lower is better | M57: ≤ | N57: 0 | P57: Default tolerance | Q57: CI reports (coverage, Review Shield, SAST) + doc review
A58: 1.c-D6-17 | B58: 1 | C58: Requirements Analysis & Review | D58: 1.c | E58: RTM Auto-Generator + Risk Scoring | F58: D6 | G58: Governance & maintainability | H58: =INDEX(A_Scoring_Model!$C$5:$C$10,MATCH(F58,A_Scoring_Model!$A$5:$A$10,0)) -> 0.1 | I58: Generic | J58: SAST high findings and exposed secrets | K58: count | L58: Lower is better | M58: ≤ | N58: 0 | P58: Default tolerance | Q58: CI reports (coverage, Review Shield, SAST) + doc review
A59: 1.c-D6-18 | B59: 1 | C59: Requirements Analysis & Review | D59: 1.c | E59: RTM Auto-Generator + Risk Scoring | F59: D6 | G59: Governance & maintainability | H59: =INDEX(A_Scoring_Model!$C$5:$C$10,MATCH(F59,A_Scoring_Model!$A$5:$A$10,0)) -> 0.1 | I59: Generic | J59: Documentation pack complete (README, I/O contract, model card, runbook) | K59: Yes/No | L59: Higher is better | M59: ≥ | N59: 1 | P59: Default tolerance | Q59: CI reports (coverage, Review Shield, SAST) + doc review
A60: 1.c-D6-19 | B60: 1 | C60: Requirements Analysis & Review | D60: 1.c | E60: RTM Auto-Generator + Risk Scoring | F60: D6 | G60: Governance & maintainability | H60: =INDEX(A_Scoring_Model!$C$5:$C$10,MATCH(F60,A_Scoring_Model!$A$5:$A$10,0)) -> 0.1 | I60: Generic | J60: Named owner and support SLA | K60: Yes/No | L60: Higher is better | M60: ≥ | N60: 1 | P60: Default tolerance | Q60: CI reports (coverage, Review Shield, SAST) + doc review
A61: 2.a-D1-01 | B61: 2 | C61: Test Planning | D61: 2.a | E61: Test Strategy AI Advisor | F61: D1 | G61: Functional efficacy | H61: =INDEX(A_Scoring_Model!$C$5:$C$10,MATCH(F61,A_Scoring_Model!$A$5:$A$10,0)) -> 0.3 | I61: Component-specific | J61: Section completeness vs ISO/IEC/IEEE 29119-3 | K61: % | L61: Higher is better | M61: ≥ | N61: 0.95 | O61: 0.85 | P61: Defined | Q61: Automated harness run on the shared golden set | R61: 20 approved historical strategies + SME scoring rubric
A62: 2.a-D1-02 | B62: 2 | C62: Test Planning | D62: 2.a | E62: Test Strategy AI Advisor | F62: D1 | G62: Functional efficacy | H62: =INDEX(A_Scoring_Model!$C$5:$C$10,MATCH(F62,A_Scoring_Model!$A$5:$A$10,0)) -> 0.3 | I62: Component-specific | J62: SME rubric score | K62: /5 | L62: Higher is better | M62: ≥ | N62: 4 | O62: 3.3 | P62: Defined | Q62: Automated harness run on the shared golden set | R62: 20 approved historical strategies + SME scoring rubric
A63: 2.a-D1-03 | B63: 2 | C63: Test Planning | D63: 2.a | E63: Test Strategy AI Advisor | F63: D1 | G63: Functional efficacy | H63: =INDEX(A_Scoring_Model!$C$5:$C$10,MATCH(F63,A_Scoring_Model!$A$5:$A$10,0)) -> 0.3 | I63: Component-specific | J63: High risks mapped to a strategy element | K63: % | L63: Higher is better | M63: ≥ | N63: 1 | O63: 0.95 | P63: Defined | Q63: Automated harness run on the shared golden set | R63: 20 approved historical strategies + SME scoring rubric
A64: 2.a-D2-04 | B64: 2 | C64: Test Planning | D64: 2.a | E64: Test Strategy AI Advisor | F64: D2 | G64: Reuse & genericity | H64: =INDEX(A_Scoring_Model!$C$5:$C$10,MATCH(F64,A_Scoring_Model!$A$5:$A$10,0)) -> 0.2 | I64: Component-specific | J64: Template library parameterised by product line | K64: Yes/No | L64: Higher is better | M64: ≥ | N64: 1 | P64: Default tolerance | Q64: Architecture review against the L3 contract + cross-product run
A65: 2.a-D2-05 | B65: 2 | C65: Test Planning | D65: 2.a | E65: Test Strategy AI Advisor | F65: D2 | G65: Reuse & genericity | H65: =INDEX(A_Scoring_Model!$C$5:$C$10,MATCH(F65,A_Scoring_Model!$A$5:$A$10,0)) -> 0.2 | I65: Generic | J65: Product lines supported with ≤10% efficacy drop (NVMe SSD, UFS, eMMC/uSD, PSSD) | K65: count | L65: Higher is better | M65: ≥ | N65: 3 | O65: 2 | P65: Defined | Q65: Architecture review against the L3 contract + cross-product run
A66: 2.a-D2-06 | B66: 2 | C66: Test Planning | D66: 2.a | E66: Test Strategy AI Advisor | F66: D2 | G66: Reuse & genericity | H66: =INDEX(A_Scoring_Model!$C$5:$C$10,MATCH(F66,A_Scoring_Model!$A$5:$A$10,0)) -> 0.2 | I66: Generic | J66: Uses Zion shared services instead of re-implementing them | K66: Yes/No | L66: Higher is better | M66: ≥ | N66: 1 | P66: Default tolerance | Q66: Architecture review against the L3 contract + cross-product run
A67: 2.a-D3-07 | B67: 2 | C67: Test Planning | D67: 2.a | E67: Test Strategy AI Advisor | F67: D3 | G67: Scalability & performance | H67: =INDEX(A_Scoring_Model!$C$5:$C$10,MATCH(F67,A_Scoring_Model!$A$5:$A$10,0)) -> 0.15 | I67: Component-specific | J67: Draft generation time | K67: min | L67: Lower is better | M67: ≤ | N67: 3 | P67: Default tolerance | Q67: Load / performance test on Zion reference cluster
A68: 2.a-D3-08 | B68: 2 | C68: Test Planning | D68: 2.a | E68: Test Strategy AI Advisor | F68: D3 | G68: Scalability & performance | H68: =INDEX(A_Scoring_Model!$C$5:$C$10,MATCH(F68,A_Scoring_Model!$A$5:$A$10,0)) -> 0.15 | I68: Component-specific | J68: Concurrent plans supported | K68: count | L68: Higher is better | M68: ≥ | N68: 50 | P68: Default tolerance | Q68: Load / performance test on Zion reference cluster
A69: 2.a-D3-09 | B69: 2 | C69: Test Planning | D69: 2.a | E69: Test Strategy AI Advisor | F69: D3 | G69: Scalability & performance | H69: =INDEX(A_Scoring_Model!$C$5:$C$10,MATCH(F69,A_Scoring_Model!$A$5:$A$10,0)) -> 0.15 | I69: Generic | J69: Latency degradation at 10× load | K69: % | L69: Lower is better | M69: ≤ | N69: 0.2 | O69: 0.4 | P69: Defined | Q69: Load / performance test on Zion reference cluster
A70: 2.a-D4-10 | B70: 2 | C70: Test Planning | D70: 2.a | E70: Test Strategy AI Advisor | F70: D4 | G70: Reliability & trust | H70: =INDEX(A_Scoring_Model!$C$5:$C$10,MATCH(F70,A_Scoring_Model!$A$5:$A$10,0)) -> 0.1 | I70: Component-specific | J70: Recommendations citing a template / KB source | K70: % | L70: Higher is better | M70: ≥ | N70: 0.9 | P70: Default tolerance | Q70: Repeat harness runs, audit log and ops monitoring
A71: 2.a-D4-11 | B71: 2 | C71: Test Planning | D71: 2.a | E71: Test Strategy AI Advisor | F71: D4 | G71: Reliability & trust | H71: =INDEX(A_Scoring_Model!$C$5:$C$10,MATCH(F71,A_Scoring_Model!$A$5:$A$10,0)) -> 0.1 | I71: Generic | J71: Service availability | K71: % | L71: Higher is better | M71: ≥ | N71: 0.995 | O71: 0.99 | P71: Defined | Q71: Repeat harness runs, audit log and ops monitoring
A72: 2.a-D5-12 | B72: 2 | C72: Test Planning | D72: 2.a | E72: Test Strategy AI Advisor | F72: D5 | G72: Business value | H72: =INDEX(A_Scoring_Model!$C$5:$C$10,MATCH(F72,A_Scoring_Model!$A$5:$A$10,0)) -> 0.15 | I72: Component-specific | J72: Strategy authoring time reduction | K72: % | L72: Higher is better | M72: ≥ | N72: 0.5 | P72: Default tolerance | Q72: Pilot vs manual baseline, SME survey
A73: 2.a-D6-13 | B73: 2 | C73: Test Planning | D73: 2.a | E73: Test Strategy AI Advisor | F73: D6 | G73: Governance & maintainability | H73: =INDEX(A_Scoring_Model!$C$5:$C$10,MATCH(F73,A_Scoring_Model!$A$5:$A$10,0)) -> 0.1 | I73: Generic | J73: Solution code test coverage | K73: % | L73: Higher is better | M73: ≥ | N73: 0.8 | O73: 0.6 | P73: Defined | Q73: CI reports (coverage, Review Shield, SAST) + doc review
A74: 2.a-D6-14 | B74: 2 | C74: Test Planning | D74: 2.a | E74: Test Strategy AI Advisor | F74: D6 | G74: Governance & maintainability | H74: =INDEX(A_Scoring_Model!$C$5:$C$10,MATCH(F74,A_Scoring_Model!$A$5:$A$10,0)) -> 0.1 | I74: Generic | J74: Review Shield critical findings | K74: count | L74: Lower is better | M74: ≤ | N74: 0 | P74: Default tolerance | Q74: CI reports (coverage, Review Shield, SAST) + doc review
A75: 2.a-D6-15 | B75: 2 | C75: Test Planning | D75: 2.a | E75: Test Strategy AI Advisor | F75: D6 | G75: Governance & maintainability | H75: =INDEX(A_Scoring_Model!$C$5:$C$10,MATCH(F75,A_Scoring_Model!$A$5:$A$10,0)) -> 0.1 | I75: Generic | J75: SAST high findings and exposed secrets | K75: count | L75: Lower is better | M75: ≤ | N75: 0 | P75: Default tolerance | Q75: CI reports (coverage, Review Shield, SAST) + doc review
A76: 2.a-D6-16 | B76: 2 | C76: Test Planning | D76: 2.a | E76: Test Strategy AI Advisor | F76: D6 | G76: Governance & maintainability | H76: =INDEX(A_Scoring_Model!$C$5:$C$10,MATCH(F76,A_Scoring_Model!$A$5:$A$10,0)) -> 0.1 | I76: Generic | J76: Documentation pack complete (README, I/O contract, model card, runbook) | K76: Yes/No | L76: Higher is better | M76: ≥ | N76: 1 | P76: Default tolerance | Q76: CI reports (coverage, Review Shield, SAST) + doc review
A77: 2.a-D6-17 | B77: 2 | C77: Test Planning | D77: 2.a | E77: Test Strategy AI Advisor | F77: D6 | G77: Governance & maintainability | H77: =INDEX(A_Scoring_Model!$C$5:$C$10,MATCH(F77,A_Scoring_Model!$A$5:$A$10,0)) -> 0.1 | I77: Generic | J77: Named owner and support SLA | K77: Yes/No | L77: Higher is better | M77: ≥ | N77: 1 | P77: Default tolerance | Q77: CI reports (coverage, Review Shield, SAST) + doc review
A78: 2.b-D1-01 | B78: 2 | C78: Test Planning | D78: 2.b | E78: Effort Estimator ML Model | F78: D1 | G78: Functional efficacy | H78: =INDEX(A_Scoring_Model!$C$5:$C$10,MATCH(F78,A_Scoring_Model!$A$5:$A$10,0)) -> 0.3 | I78: Component-specific | J78: MMRE (mean magnitude of relative error) | K78: % | L78: Lower is better | M78: ≤ | N78: 0.2 | O78: 0.3 | P78: Defined | Q78: Automated harness run on the shared golden set | R78: ≥150 closed projects, planned vs actual effort, time-split hold-out
A79: 2.b-D1-02 | B79: 2 | C79: Test Planning | D79: 2.b | E79: Effort Estimator ML Model | F79: D1 | G79: Functional efficacy | H79: =INDEX(A_Scoring_Model!$C$5:$C$10,MATCH(F79,A_Scoring_Model!$A$5:$A$10,0)) -> 0.3 | I79: Component-specific | J79: PRED(25) | K79: % | L79: Higher is better | M79: ≥ | N79: 0.75 | O79: 0.6 | P79: Defined | Q79: Automated harness run on the shared golden set | R79: ≥150 closed projects, planned vs actual effort, time-split hold-out
A80: 2.b-D1-03 | B80: 2 | C80: Test Planning | D80: 2.b | E80: Effort Estimator ML Model | F80: D1 | G80: Functional efficacy | H80: =INDEX(A_Scoring_Model!$C$5:$C$10,MATCH(F80,A_Scoring_Model!$A$5:$A$10,0)) -> 0.3 | I80: Component-specific | J80: P10–P90 interval coverage | K80: % | L80: Higher is better | M80: ≥ | N80: 0.8 | O80: 0.7 | P80: Defined | Q80: Automated harness run on the shared golden set | R80: ≥150 closed projects, planned vs actual effort, time-split hold-out
A81: 2.b-D2-04 | B81: 2 | C81: Test Planning | D81: 2.b | E81: Effort Estimator ML Model | F81: D2 | G81: Reuse & genericity | H81: =INDEX(A_Scoring_Model!$C$5:$C$10,MATCH(F81,A_Scoring_Model!$A$5:$A$10,0)) -> 0.2 | I81: Component-specific | J81: Common feature schema; per-group calibration layer only | K81: Yes/No | L81: Higher is better | M81: ≥ | N81: 1 | P81: Default tolerance | Q81: Architecture review against the L3 contract + cross-product run
A82: 2.b-D2-05 | B82: 2 | C82: Test Planning | D82: 2.b | E82: Effort Estimator ML Model | F82: D2 | G82: Reuse & genericity | H82: =INDEX(A_Scoring_Model!$C$5:$C$10,MATCH(F82,A_Scoring_Model!$A$5:$A$10,0)) -> 0.2 | I82: Generic | J82: Product lines supported with ≤10% efficacy drop (NVMe SSD, UFS, eMMC/uSD, PSSD) | K82: count | L82: Higher is better | M82: ≥ | N82: 3 | O82: 2 | P82: Defined | Q82: Architecture review against the L3 contract + cross-product run
A83: 2.b-D2-06 | B83: 2 | C83: Test Planning | D83: 2.b | E83: Effort Estimator ML Model | F83: D2 | G83: Reuse & genericity | H83: =INDEX(A_Scoring_Model!$C$5:$C$10,MATCH(F83,A_Scoring_Model!$A$5:$A$10,0)) -> 0.2 | I83: Generic | J83: Uses Zion shared services instead of re-implementing them | K83: Yes/No | L83: Higher is better | M83: ≥ | N83: 1 | P83: Default tolerance | Q83: Architecture review against the L3 contract + cross-product run
A84: 2.b-D3-07 | B84: 2 | C84: Test Planning | D84: 2.b | E84: Effort Estimator ML Model | F84: D3 | G84: Scalability & performance | H84: =INDEX(A_Scoring_Model!$C$5:$C$10,MATCH(F84,A_Scoring_Model!$A$5:$A$10,0)) -> 0.15 | I84: Component-specific | J84: Inference latency | K84: ms | L84: Lower is better | M84: ≤ | N84: 200 | P84: Default tolerance | Q84: Load / performance test on Zion reference cluster
A85: 2.b-D3-08 | B85: 2 | C85: Test Planning | D85: 2.b | E85: Effort Estimator ML Model | F85: D3 | G85: Scalability & performance | H85: =INDEX(A_Scoring_Model!$C$5:$C$10,MATCH(F85,A_Scoring_Model!$A$5:$A$10,0)) -> 0.15 | I85: Component-specific | J85: Retrain time on 5k projects | K85: hr | L85: Lower is better | M85: ≤ | N85: 1 | P85: Default tolerance | Q85: Load / performance test on Zion reference cluster
A86: 2.b-D3-09 | B86: 2 | C86: Test Planning | D86: 2.b | E86: Effort Estimator ML Model | F86: D3 | G86: Scalability & performance | H86: =INDEX(A_Scoring_Model!$C$5:$C$10,MATCH(F86,A_Scoring_Model!$A$5:$A$10,0)) -> 0.15 | I86: Generic | J86: Latency degradation at 10× load | K86: % | L86: Lower is better | M86: ≤ | N86: 0.2 | O86: 0.4 | P86: Defined | Q86: Load / performance test on Zion reference cluster
A87: 2.b-D4-10 | B87: 2 | C87: Test Planning | D87: 2.b | E87: Effort Estimator ML Model | F87: D4 | G87: Reliability & trust | H87: =INDEX(A_Scoring_Model!$C$5:$C$10,MATCH(F87,A_Scoring_Model!$A$5:$A$10,0)) -> 0.1 | I87: Component-specific | J87: Drift PSI | K87: PSI | L87: Lower is better | M87: ≤ | N87: 0.2 | P87: Default tolerance | Q87: Repeat harness runs, audit log and ops monitoring
A88: 2.b-D4-11 | B88: 2 | C88: Test Planning | D88: 2.b | E88: Effort Estimator ML Model | F88: D4 | G88: Reliability & trust | H88: =INDEX(A_Scoring_Model!$C$5:$C$10,MATCH(F88,A_Scoring_Model!$A$5:$A$10,0)) -> 0.1 | I88: Component-specific | J88: Estimates with top-5 SHAP drivers | K88: % | L88: Higher is better | M88: ≥ | N88: 1 | P88: Default tolerance | Q88: Repeat harness runs, audit log and ops monitoring
A89: 2.b-D4-12 | B89: 2 | C89: Test Planning | D89: 2.b | E89: Effort Estimator ML Model | F89: D4 | G89: Reliability & trust | H89: =INDEX(A_Scoring_Model!$C$5:$C$10,MATCH(F89,A_Scoring_Model!$A$5:$A$10,0)) -> 0.1 | I89: Generic | J89: Service availability | K89: % | L89: Higher is better | M89: ≥ | N89: 0.995 | O89: 0.99 | P89: Defined | Q89: Repeat harness runs, audit log and ops monitoring
A90: 2.b-D5-13 | B90: 2 | C90: Test Planning | D90: 2.b | E90: Effort Estimator ML Model | F90: D5 | G90: Business value | H90: =INDEX(A_Scoring_Model!$C$5:$C$10,MATCH(F90,A_Scoring_Model!$A$5:$A$10,0)) -> 0.15 | I90: Component-specific | J90: Estimate-vs-actual variance reduction vs expert baseline | K90: % | L90: Higher is better | M90: ≥ | N90: 0.3 | P90: Default tolerance | Q90: Pilot vs manual baseline, SME survey
A91: 2.b-D6-14 | B91: 2 | C91: Test Planning | D91: 2.b | E91: Effort Estimator ML Model | F91: D6 | G91: Governance & maintainability | H91: =INDEX(A_Scoring_Model!$C$5:$C$10,MATCH(F91,A_Scoring_Model!$A$5:$A$10,0)) -> 0.1 | I91: Generic | J91: Solution code test coverage | K91: % | L91: Higher is better | M91: ≥ | N91: 0.8 | O91: 0.6 | P91: Defined | Q91: CI reports (coverage, Review Shield, SAST) + doc review
A92: 2.b-D6-15 | B92: 2 | C92: Test Planning | D92: 2.b | E92: Effort Estimator ML Model | F92: D6 | G92: Governance & maintainability | H92: =INDEX(A_Scoring_Model!$C$5:$C$10,MATCH(F92,A_Scoring_Model!$A$5:$A$10,0)) -> 0.1 | I92: Generic | J92: Review Shield critical findings | K92: count | L92: Lower is better | M92: ≤ | N92: 0 | P92: Default tolerance | Q92: CI reports (coverage, Review Shield, SAST) + doc review
A93: 2.b-D6-16 | B93: 2 | C93: Test Planning | D93: 2.b | E93: Effort Estimator ML Model | F93: D6 | G93: Governance & maintainability | H93: =INDEX(A_Scoring_Model!$C$5:$C$10,MATCH(F93,A_Scoring_Model!$A$5:$A$10,0)) -> 0.1 | I93: Generic | J93: SAST high findings and exposed secrets | K93: count | L93: Lower is better | M93: ≤ | N93: 0 | P93: Default tolerance | Q93: CI reports (coverage, Review Shield, SAST) + doc review
A94: 2.b-D6-17 | B94: 2 | C94: Test Planning | D94: 2.b | E94: Effort Estimator ML Model | F94: D6 | G94: Governance & maintainability | H94: =INDEX(A_Scoring_Model!$C$5:$C$10,MATCH(F94,A_Scoring_Model!$A$5:$A$10,0)) -> 0.1 | I94: Generic | J94: Documentation pack complete (README, I/O contract, model card, runbook) | K94: Yes/No | L94: Higher is better | M94: ≥ | N94: 1 | P94: Default tolerance | Q94: CI reports (coverage, Review Shield, SAST) + doc review
A95: 2.b-D6-18 | B95: 2 | C95: Test Planning | D95: 2.b | E95: Effort Estimator ML Model | F95: D6 | G95: Governance & maintainability | H95: =INDEX(A_Scoring_Model!$C$5:$C$10,MATCH(F95,A_Scoring_Model!$A$5:$A$10,0)) -> 0.1 | I95: Generic | J95: Named owner and support SLA | K95: Yes/No | L95: Higher is better | M95: ≥ | N95: 1 | P95: Default tolerance | Q95: CI reports (coverage, Review Shield, SAST) + doc review
A96: 2.c-D1-01 | B96: 2 | C96: Test Planning | D96: 2.c | E96: Risk Scoring & Plan Generator | F96: D1 | G96: Functional efficacy | H96: =INDEX(A_Scoring_Model!$C$5:$C$10,MATCH(F96,A_Scoring_Model!$A$5:$A$10,0)) -> 0.3 | I96: Component-specific | J96: Top-10 risk overlap with SME | K96: % | L96: Higher is better | M96: ≥ | N96: 0.8 | O96: 0.65 | P96: Defined | Q96: Automated harness run on the shared golden set | R96: 15 plans with SME risk rankings and review comments
A97: 2.c-D1-02 | B97: 2 | C97: Test Planning | D97: 2.c | E97: Risk Scoring & Plan Generator | F97: D1 | G97: Functional efficacy | H97: =INDEX(A_Scoring_Model!$C$5:$C$10,MATCH(F97,A_Scoring_Model!$A$5:$A$10,0)) -> 0.3 | I97: Component-specific | J97: Plan section completeness | K97: % | L97: Higher is better | M97: ≥ | N97: 0.95 | O97: 0.85 | P97: Defined | Q97: Automated harness run on the shared golden set | R97: 15 plans with SME risk rankings and review comments
A98: 2.c-D1-03 | B98: 2 | C98: Test Planning | D98: 2.c | E98: Risk Scoring & Plan Generator | F98: D1 | G98: Functional efficacy | H98: =INDEX(A_Scoring_Model!$C$5:$C$10,MATCH(F98,A_Scoring_Model!$A$5:$A$10,0)) -> 0.3 | I98: Component-specific | J98: Mitigation relevance (SME) | K98: /5 | L98: Higher is better | M98: ≥ | N98: 4 | O98: 3.3 | P98: Defined | Q98: Automated harness run on the shared golden set | R98: 15 plans with SME risk rankings and review comments
A99: 2.c-D2-04 | B99: 2 | C99: Test Planning | D99: 2.c | E99: Risk Scoring & Plan Generator | F99: D2 | G99: Reuse & genericity | H99: =INDEX(A_Scoring_Model!$C$5:$C$10,MATCH(F99,A_Scoring_Model!$A$5:$A$10,0)) -> 0.2 | I99: Component-specific | J99: FMEA scales and weights in config | K99: Yes/No | L99: Higher is better | M99: ≥ | N99: 1 | P99: Default tolerance | Q99: Architecture review against the L3 contract + cross-product run
A100: 2.c-D2-05 | B100: 2 | C100: Test Planning | D100: 2.c | E100: Risk Scoring & Plan Generator | F100: D2 | G100: Reuse & genericity | H100: =INDEX(A_Scoring_Model!$C$5:$C$10,MATCH(F100,A_Scoring_Model!$A$5:$A$10,0)) -> 0.2 | I100: Generic | J100: Product lines supported with ≤10% efficacy drop (NVMe SSD, UFS, eMMC/uSD, PSSD) | K100: count | L100: Higher is better | M100: ≥ | N100: 3 | O100: 2 | P100: Defined | Q100: Architecture review against the L3 contract + cross-product run
A101: 2.c-D2-06 | B101: 2 | C101: Test Planning | D101: 2.c | E101: Risk Scoring & Plan Generator | F101: D2 | G101: Reuse & genericity | H101: =INDEX(A_Scoring_Model!$C$5:$C$10,MATCH(F101,A_Scoring_Model!$A$5:$A$10,0)) -> 0.2 | I101: Generic | J101: Uses Zion shared services instead of re-implementing them | K101: Yes/No | L101: Higher is better | M101: ≥ | N101: 1 | P101: Default tolerance | Q101: Architecture review against the L3 contract + cross-product run
...

Sheet D_Shared_Services
A1: D · Shared building blocks — build once, reuse across components
A2: A component that re-implements a shared service scores 0 on the D2 'uses shared services' KPI
A4: Code | B4: Shared service | C4: What it provides | D4: Components using it
A5: LLM | B5: LLM gateway & prompt registry | C5: On-prem model routing, token metering, versioned prompt packs, PII / confidentiality filter | D5: =COUNTIF($D$19:$D$49,"●") -> 23
A6: EMB | B6: Embedding & semantic similarity service | C6: One embedding model and vector index for linking, dedup and retrieval | D6: =COUNTIF($E$19:$E$49,"●") -> 7
A7: SPEC | B7: Spec & document ingestion | C7: PDF / DOCX / ReqIF parsing, clause-aware chunking, table extraction | D7: =COUNTIF($F$19:$F$49,"●") -> 3
A8: RULE | B8: Rule & policy engine | C8: YAML / OPA rules for criteria, gates, access and compliance checks | D8: =COUNTIF($G$19:$G$49,"●") -> 8
A9: RISK | B9: Risk scoring library | C9: Likelihood × impact, FMEA RPN and test-impact risk in one calibrated library | D9: =COUNTIF($H$19:$H$49,"●") -> 5
A10: ANOM | B10: Time-series anomaly core | C10: SPC, change-point and isolation-forest detectors with a common alert schema | D10: =COUNTIF($I$19:$I$49,"●") -> 3
A11: LOG | B11: Log parser & signature library | C11: FW trace, host dmesg, NVMe error log, UART parsers and failure signatures | D11: =COUNTIF($J$19:$J$49,"●") -> 7
A12: DOC | B12: Report & document generator | C12: Audience templates rendered to DOCX, PPTX, Confluence and email | D12: =COUNTIF($K$19:$K$49,"●") -> 5
A13: MLOPS | B13: MLOps pipeline & model registry | C13: Feature store, training, drift monitoring, champion / challenger, rollback | D13: =COUNTIF($L$19:$L$49,"●") -> 10
A14: GOLD | B14: Golden dataset & benchmark harness | C14: Versioned golden sets, scripted runs, automatic KPI report for gate G2 | D14: =COUNTIF($M$19:$M$49,"●") -> 31
A16: Component × service usage matrix (● = uses the service)
A18: L3 ID | B18: L3 component | C18: Phase | D18: LLM | E18: EMB | F18: SPEC | G18: RULE | H18: RISK | I18: ANOM | J18: LOG | K18: DOC | L18: MLOPS | M18: GOLD
A19: 1.a | B19: NL Req Parsing & Classification Agent | C19: 1 | D19: ● | F19: ● | M19: ●
A20: 1.b | B20: Feasibility & Quality Analyzer | C20: 1 | D20: ● | E20: ● | G20: ● | M20: ●
A21: 1.c | B21: RTM Auto-Generator + Risk Scoring | C21: 1 | D21: ● | E21: ● | H21: ● | M21: ●
A22: 2.a | B22: Test Strategy AI Advisor | C22: 2 | D22: ● | F22: ● | K22: ● | M22: ●
A23: 2.b | B23: Effort Estimator ML Model | C23: 2 | L23: ● | M23: ●
A24: 2.c | B24: Risk Scoring & Plan Generator | C24: 2 | D24: ● | G24: ● | H24: ● | K24: ● | M24: ●
A25: 3.a | B25: Scenario + LLM Test Case Gen Agent | C25: 3 | D25: ● | E25: ● | M25: ●
A26: 3.b | B26: BDD Writer & Data Synth Agent | C26: 3 | D26: ● | M26: ●
A27: 3.c | B27: Script Dev/Review & Coverage Agent | C27: 3 | D27: ● | J27: ● | M27: ●
A28: 3.d | B28: AI Code Review Agent (Review Shield) | C28: 3 | D28: ● | E28: ● | G28: ● | J28: ● | K28: ● | L28: ● | M28: ●
A29: 4.a | B29: IaC Provisioner Agent | C29: 4 | D29: ● | G29: ● | M29: ●
A30: 4.b | B30: Env Validator & Drift Detector | C30: 4 | I30: ● | L30: ● | M30: ●
A31: 4.c | B31: Access & Security Recommender | C31: 4 | D31: ● | G31: ● | M31: ●
A32: 5.a | B32: Test Orchestrator Agent | C32: 5 | D32: ● | H32: ● | M32: ●
A33: 5.b | B33: Self-Healing Script Agent | C33: 5 | D33: ● | J33: ● | M33: ●
A34: 5.c | B34: Visual AI + Perf Analyzer | C34: 5 | I34: ● | L34: ● | M34: ●
A35: 6.a | B35: Defect Classifier & Severity AI | C35: 6 | D35: ● | J35: ● | L35: ● | M35: ●
A36: 6.b | B36: Duplicate Detector Agent | C36: 6 | E36: ● | J36: ● | L36: ● | M36: ●
A37: 6.c | B37: RCA Analyzer + Pattern Detector | C37: 6 | D37: ● | E37: ● | J37: ● | M37: ●
A38: 7.a | B38: Metrics Analytics Intelligence | C38: 7 | D38: ● | M38: ●
A39: 7.b | B39: Predictive QA ML Model | C39: 7 | L39: ● | M39: ●
A40: 7.c | B40: Auto Report Generator Agent | C40: 7 | D40: ● | K40: ● | M40: ●
A41: 8.a | B41: Exit Criteria Evaluator Agent | C41: 8 | D41: ● | G41: ● | M41: ●
A42: 8.b | B42: Knowledge Extractor Agent | C42: 8 | D42: ● | E42: ● | F42: ● | M42: ●
A43: 8.c | B43: Process Optimizer Agent | C43: 8 | L43: ● | M43: ●
A44: 9.a | B44: Release Gate Validator Agent | C44: 9 | D44: ● | G44: ● | H44: ● | M44: ●
A45: 9.b | B45: Deployment Verifier Agent | C45: 9 | D45: ● | G45: ● | M45: ●
A46: 9.c | B46: Comms Drafter & Rollback Agent | C46: 9 | D46: ● | K46: ● | M46: ●
A47: 10.a | B47: Anomaly Detection Agent | C47: 10 | I47: ● | L47: ● | M47: ●
A48: 10.b | B48: Customer Feedback Analyzer | C48: 10 | D48: ● | J48: ● | M48: ●
A49: 10.c | B49: Hotfix Triage & MLOps Pipeline | C49: 10 | H49: ● | L49: ● | M49: ●

Sheet E_Measurements
A1: E · Measurements — enter benchmark results per group
A2: Yellow cells = input. Percent KPIs as %, Yes/No KPIs as 1 / 0. Scores calculate automatically (100 at Target, 60 at Min, 0 beyond Min).
A4: KPI ID | B4: L3 ID | C4: L3 component | D4: Dim | E4: KPI | F4: Unit | G4: Direction | H4: Target | I4: Min (effective) | J4: grp1 value | K4: grp2 value | L4: grp3 value | M4: Sol PE platform value | N4: grp1 score | O4: grp2 score | P4: grp3 score | Q4: Sol PE platform score
A5: =C_KPI_Benchmark!A5 -> 1.a-D1-01 | B5: =C_KPI_Benchmark!D5 -> 1.a | C5: =C_KPI_Benchmark!E5 -> NL Req Parsing & Classification Agent | D5: =C_KPI_Benchmark!F5 -> D1 | E5: =C_KPI_Benchmark!J5 -> Atomic requirement extraction recall | F5: =C_KPI_Benchmark!K5 -> % | G5: =C_KPI_Benchmark!L5 -> Higher is better | H5: =C_KPI_Benchmark!N5 -> 0.95 | I5: =IF(C_KPI_Benchmark!O5<>"",C_KPI_Benchmark!O5,IF(G5="Higher is better",H5*(1-A_Scoring_Model!$C$16),H5*(1+A_Scoring_Model!$C$16))) -> 0.88 | J5: 0.92 | K5: 0.96 | L5: 0.93 | N5: =IF(J5="","",IF($H5=$I5,IF(OR(AND($G5="Higher is better",J5>=$H5),AND($G5="Lower is better",J5<=$H5)),A_Scoring_Model!$C$14,0),IF($G5="Higher is better",IF(J5>=$H5,A_Scoring_Model!$C$14,IF(J5<$I5,0,A_Scoring_Model!$C$15+(A_Scoring_Model!$C$14-A_Scoring_Model!$C$15)*(J5-$I5)/($H5-$I5))),IF(J5<=$H5,A_Scoring_Model!$C$14,IF(J5>$I5,0,A_Scoring_Model!$C$15+(A_Scoring_Model!$C$14-A_Scoring_Model!$C$15)*($I5-J5)/($I5-$H5)))))) -> 82.857143 | O5: =IF(K5="","",IF($H5=$I5,IF(OR(AND($G5="Higher is better",K5>=$H5),AND($G5="Lower is better",K5<=$H5)),A_Scoring_Model!$C$14,0),IF($G5="Higher is better",IF(K5>=$H5,A_Scoring_Model!$C$14,IF(K5<$I5,0,A_Scoring_Model!$C$15+(A_Scoring_Model!$C$14-A_Scoring_Model!$C$15)*(K5-$I5)/($H5-$I5))),IF(K5<=$H5,A_Scoring_Model!$C$14,IF(K5>$I5,0,A_Scoring_Model!$C$15+(A_Scoring_Model!$C$14-A_Scoring_Model!$C$15)*($I5-K5)/($I5-$H5)))))) -> 100 | P5: =IF(L5="","",IF($H5=$I5,IF(OR(AND($G5="Higher is better",L5>=$H5),AND($G5="Lower is better",L5<=$H5)),A_Scoring_Model!$C$14,0),IF($G5="Higher is better",IF(L5>=$H5,A_Scoring_Model!$C$14,IF(L5<$I5,0,A_Scoring_Model!$C$15+(A_Scoring_Model!$C$14-A_Scoring_Model!$C$15)*(L5-$I5)/($H5-$I5))),IF(L5<=$H5,A_Scoring_Model!$C$14,IF(L5>$I5,0,A_Scoring_Model!$C$15+(A_Scoring_Model!$C$14-A_Scoring_Model!$C$15)*($I5-L5)/($I5-$H5)))))) -> 88.571429 | Q5: =IF(M5="","",IF($H5=$I5,IF(OR(AND($G5="Higher is better",M5>=$H5),AND($G5="Lower is better",M5<=$H5)),A_Scoring_Model!$C$14,0),IF($G5="Higher is better",IF(M5>=$H5,A_Scoring_Model!$C$14,IF(M5<$I5,0,A_Scoring_Model!$C$15+(A_Scoring_Model!$C$14-A_Scoring_Model!$C$15)*(M5-$I5)/($H5-$I5))),IF(M5<=$H5,A_Scoring_Model!$C$14,IF(M5>$I5,0,A_Scoring_Model!$C$15+(A_Scoring_Model!$C$14-A_Scoring_Model!$C$15)*($I5-M5)/($I5-$H5))))))
A6: =C_KPI_Benchmark!A6 -> 1.a-D1-02 | B6: =C_KPI_Benchmark!D6 -> 1.a | C6: =C_KPI_Benchmark!E6 -> NL Req Parsing & Classification Agent | D6: =C_KPI_Benchmark!F6 -> D1 | E6: =C_KPI_Benchmark!J6 -> Classification macro-F1 (func / perf / security / compliance / interface) | F6: =C_KPI_Benchmark!K6 -> F1 | G6: =C_KPI_Benchmark!L6 -> Higher is better | H6: =C_KPI_Benchmark!N6 -> 0.9 | I6: =IF(C_KPI_Benchmark!O6<>"",C_KPI_Benchmark!O6,IF(G6="Higher is better",H6*(1-A_Scoring_Model!$C$16),H6*(1+A_Scoring_Model!$C$16))) -> 0.82 | J6: 0.86 | K6: 0.92 | L6: 0.88 | N6: =IF(J6="","",IF($H6=$I6,IF(OR(AND($G6="Higher is better",J6>=$H6),AND($G6="Lower is better",J6<=$H6)),A_Scoring_Model!$C$14,0),IF($G6="Higher is better",IF(J6>=$H6,A_Scoring_Model!$C$14,IF(J6<$I6,0,A_Scoring_Model!$C$15+(A_Scoring_Model!$C$14-A_Scoring_Model!$C$15)*(J6-$I6)/($H6-$I6))),IF(J6<=$H6,A_Scoring_Model!$C$14,IF(J6>$I6,0,A_Scoring_Model!$C$15+(A_Scoring_Model!$C$14-A_Scoring_Model!$C$15)*($I6-J6)/($I6-$H6)))))) -> 80 | O6: =IF(K6="","",IF($H6=$I6,IF(OR(AND($G6="Higher is better",K6>=$H6),AND($G6="Lower is better",K6<=$H6)),A_Scoring_Model!$C$14,0),IF($G6="Higher is better",IF(K6>=$H6,A_Scoring_Model!$C$14,IF(K6<$I6,0,A_Scoring_Model!$C$15+(A_Scoring_Model!$C$14-A_Scoring_Model!$C$15)*(K6-$I6)/($H6-$I6))),IF(K6<=$H6,A_Scoring_Model!$C$14,IF(K6>$I6,0,A_Scoring_Model!$C$15+(A_Scoring_Model!$C$14-A_Scoring_Model!$C$15)*($I6-K6)/($I6-$H6)))))) -> 100 | P6: =IF(L6="","",IF($H6=$I6,IF(OR(AND($G6="Higher is better",L6>=$H6),AND($G6="Lower is better",L6<=$H6)),A_Scoring_Model!$C$14,0),IF($G6="Higher is better",IF(L6>=$H6,A_Scoring_Model!$C$14,IF(L6<$I6,0,A_Scoring_Model!$C$15+(A_Scoring_Model!$C$14-A_Scoring_Model!$C$15)*(L6-$I6)/($H6-$I6))),IF(L6<=$H6,A_Scoring_Model!$C$14,IF(L6>$I6,0,A_Scoring_Model!$C$15+(A_Scoring_Model!$C$14-A_Scoring_Model!$C$15)*($I6-L6)/($I6-$H6)))))) -> 90 | Q6: =IF(M6="","",IF($H6=$I6,IF(OR(AND($G6="Higher is better",M6>=$H6),AND($G6="Lower is better",M6<=$H6)),A_Scoring_Model!$C$14,0),IF($G6="Higher is better",IF(M6>=$H6,A_Scoring_Model!$C$14,IF(M6<$I6,0,A_Scoring_Model!$C$15+(A_Scoring_Model!$C$14-A_Scoring_Model!$C$15)*(M6-$I6)/($H6-$I6))),IF(M6<=$H6,A_Scoring_Model!$C$14,IF(M6>$I6,0,A_Scoring_Model!$C$15+(A_Scoring_Model!$C$14-A_Scoring_Model!$C$15)*($I6-M6)/($I6-$H6))))))
A7: =C_KPI_Benchmark!A7 -> 1.a-D1-03 | B7: =C_KPI_Benchmark!D7 -> 1.a | C7: =C_KPI_Benchmark!E7 -> NL Req Parsing & Classification Agent | D7: =C_KPI_Benchmark!F7 -> D1 | E7: =C_KPI_Benchmark!J7 -> Source-clause traceability | F7: =C_KPI_Benchmark!K7 -> % | G7: =C_KPI_Benchmark!L7 -> Higher is better | H7: =C_KPI_Benchmark!N7 -> 1 | I7: =IF(C_KPI_Benchmark!O7<>"",C_KPI_Benchmark!O7,IF(G7="Higher is better",H7*(1-A_Scoring_Model!$C$16),H7*(1+A_Scoring_Model!$C$16))) -> 0.98 | J7: 0.99 | K7: 1 | L7: 1 | N7: =IF(J7="","",IF($H7=$I7,IF(OR(AND($G7="Higher is better",J7>=$H7),AND($G7="Lower is better",J7<=$H7)),A_Scoring_Model!$C$14,0),IF($G7="Higher is better",IF(J7>=$H7,A_Scoring_Model!$C$14,IF(J7<$I7,0,A_Scoring_Model!$C$15+(A_Scoring_Model!$C$14-A_Scoring_Model!$C$15)*(J7-$I7)/($H7-$I7))),IF(J7<=$H7,A_Scoring_Model!$C$14,IF(J7>$I7,0,A_Scoring_Model!$C$15+(A_Scoring_Model!$C$14-A_Scoring_Model!$C$15)*($I7-J7)/($I7-$H7)))))) -> 80 | O7: =IF(K7="","",IF($H7=$I7,IF(OR(AND($G7="Higher is better",K7>=$H7),AND($G7="Lower is better",K7<=$H7)),A_Scoring_Model!$C$14,0),IF($G7="Higher is better",IF(K7>=$H7,A_Scoring_Model!$C$14,IF(K7<$I7,0,A_Scoring_Model!$C$15+(A_Scoring_Model!$C$14-A_Scoring_Model!$C$15)*(K7-$I7)/($H7-$I7))),IF(K7<=$H7,A_Scoring_Model!$C$14,IF(K7>$I7,0,A_Scoring_Model!$C$15+(A_Scoring_Model!$C$14-A_Scoring_Model!$C$15)*($I7-K7)/($I7-$H7)))))) -> 100 | P7: =IF(L7="","",IF($H7=$I7,IF(OR(AND($G7="Higher is better",L7>=$H7),AND($G7="Lower is better",L7<=$H7)),A_Scoring_Model!$C$14,0),IF($G7="Higher is better",IF(L7>=$H7,A_Scoring_Model!$C$14,IF(L7<$I7,0,A_Scoring_Model!$C$15+(A_Scoring_Model!$C$14-A_Scoring_Model!$C$15)*(L7-$I7)/($H7-$I7))),IF(L7<=$H7,A_Scoring_Model!$C$14,IF(L7>$I7,0,A_Scoring_Model!$C$15+(A_Scoring_Model!$C$14-A_Scoring_Model!$C$15)*($I7-L7)/($I7-$H7)))))) -> 100 | Q7: =IF(M7="","",IF($H7=$I7,IF(OR(AND($G7="Higher is better",M7>=$H7),AND($G7="Lower is better",M7<=$H7)),A_Scoring_Model!$C$14,0),IF($G7="Higher is better",IF(M7>=$H7,A_Scoring_Model!$C$14,IF(M7<$I7,0,A_Scoring_Model!$C$15+(A_Scoring_Model!$C$14-A_Scoring_Model!$C$15)*(M7-$I7)/($H7-$I7))),IF(M7<=$H7,A_Scoring_Model!$C$14,IF(M7>$I7,0,A_Scoring_Model!$C$15+(A_Scoring_Model!$C$14-A_Scoring_Model!$C$15)*($I7-M7)/($I7-$H7))))))
A8: =C_KPI_Benchmark!A8 -> 1.a-D2-04 | B8: =C_KPI_Benchmark!D8 -> 1.a | C8: =C_KPI_Benchmark!E8 -> NL Req Parsing & Classification Agent | D8: =C_KPI_Benchmark!F8 -> D2 | E8: =C_KPI_Benchmark!J8 -> Taxonomy and rules in YAML / prompt packs, no code change per group | F8: =C_KPI_Benchmark!K8 -> Yes/No | G8: =C_KPI_Benchmark!L8 -> Higher is better | H8: =C_KPI_Benchmark!N8 -> 1 | I8: =IF(C_KPI_Benchmark!O8<>"",C_KPI_Benchmark!O8,IF(G8="Higher is better",H8*(1-A_Scoring_Model!$C$16),H8*(1+A_Scoring_Model!$C$16))) -> 0.8 | J8: 1 | K8: 0 | L8: 1 | N8: =IF(J8="","",IF($H8=$I8,IF(OR(AND($G8="Higher is better",J8>=$H8),AND($G8="Lower is better",J8<=$H8)),A_Scoring_Model!$C$14,0),IF($G8="Higher is better",IF(J8>=$H8,A_Scoring_Model!$C$14,IF(J8<$I8,0,A_Scoring_Model!$C$15+(A_Scoring_Model!$C$14-A_Scoring_Model!$C$15)*(J8-$I8)/($H8-$I8))),IF(J8<=$H8,A_Scoring_Model!$C$14,IF(J8>$I8,0,A_Scoring_Model!$C$15+(A_Scoring_Model!$C$14-A_Scoring_Model!$C$15)*($I8-J8)/($I8-$H8)))))) -> 100 | O8: =IF(K8="","",IF($H8=$I8,IF(OR(AND($G8="Higher is better",K8>=$H8),AND($G8="Lower is better",K8<=$H8)),A_Scoring_Model!$C$14,0),IF($G8="Higher is better",IF(K8>=$H8,A_Scoring_Model!$C$14,IF(K8<$I8,0,A_Scoring_Model!$C$15+(A_Scoring_Model!$C$14-A_Scoring_Model!$C$15)*(K8-$I8)/($H8-$I8))),IF(K8<=$H8,A_Scoring_Model!$C$14,IF(K8>$I8,0,A_Scoring_Model!$C$15+(A_Scoring_Model!$C$14-A_Scoring_Model!$C$15)*($I8-K8)/($I8-$H8)))))) -> 0 | P8: =IF(L8="","",IF($H8=$I8,IF(OR(AND($G8="Higher is better",L8>=$H8),AND($G8="Lower is better",L8<=$H8)),A_Scoring_Model!$C$14,0),IF($G8="Higher is better",IF(L8>=$H8,A_Scoring_Model!$C$14,IF(L8<$I8,0,A_Scoring_Model!$C$15+(A_Scoring_Model!$C$14-A_Scoring_Model!$C$15)*(L8-$I8)/($H8-$I8))),IF(L8<=$H8,A_Scoring_Model!$C$14,IF(L8>$I8,0,A_Scoring_Model!$C$15+(A_Scoring_Model!$C$14-A_Scoring_Model!$C$15)*($I8-L8)/($I8-$H8)))))) -> 100 | Q8: =IF(M8="","",IF($H8=$I8,IF(OR(AND($G8="Higher is better",M8>=$H8),AND($G8="Lower is better",M8<=$H8)),A_Scoring_Model!$C$14,0),IF($G8="Higher is better",IF(M8>=$H8,A_Scoring_Model!$C$14,IF(M8<$I8,0,A_Scoring_Model!$C$15+(A_Scoring_Model!$C$14-A_Scoring_Model!$C$15)*(M8-$I8)/($H8-$I8))),IF(M8<=$H8,A_Scoring_Model!$C$14,IF(M8>$I8,0,A_Scoring_Model!$C$15+(A_Scoring_Model!$C$14-A_Scoring_Model!$C$15)*($I8-M8)/($I8-$H8))))))
A9: =C_KPI_Benchmark!A9 -> 1.a-D2-05 | B9: =C_KPI_Benchmark!D9 -> 1.a | C9: =C_KPI_Benchmark!E9 -> NL Req Parsing & Classification Agent | D9: =C_KPI_Benchmark!F9 -> D2 | E9: =C_KPI_Benchmark!J9 -> Product lines supported with ≤10% efficacy drop (NVMe SSD, UFS, eMMC/uSD, PSSD) | F9: =C_KPI_Benchmark!K9 -> count | G9: =C_KPI_Benchmark!L9 -> Higher is better | H9: =C_KPI_Benchmark!N9 -> 3 | I9: =IF(C_KPI_Benchmark!O9<>"",C_KPI_Benchmark!O9,IF(G9="Higher is better",H9*(1-A_Scoring_Model!$C$16),H9*(1+A_Scoring_Model!$C$16))) -> 2 | J9: 2 | K9: 1 | L9: 3 | N9: =IF(J9="","",IF($H9=$I9,IF(OR(AND($G9="Higher is better",J9>=$H9),AND($G9="Lower is better",J9<=$H9)),A_Scoring_Model!$C$14,0),IF($G9="Higher is better",IF(J9>=$H9,A_Scoring_Model!$C$14,IF(J9<$I9,0,A_Scoring_Model!$C$15+(A_Scoring_Model!$C$14-A_Scoring_Model!$C$15)*(J9-$I9)/($H9-$I9))),IF(J9<=$H9,A_Scoring_Model!$C$14,IF(J9>$I9,0,A_Scoring_Model!$C$15+(A_Scoring_Model!$C$14-A_Scoring_Model!$C$15)*($I9-J9)/($I9-$H9)))))) -> 60 | O9: =IF(K9="","",IF($H9=$I9,IF(OR(AND($G9="Higher is better",K9>=$H9),AND($G9="Lower is better",K9<=$H9)),A_Scoring_Model!$C$14,0),IF($G9="Higher is better",IF(K9>=$H9,A_Scoring_Model!$C$14,IF(K9<$I9,0,A_Scoring_Model!$C$15+(A_Scoring_Model!$C$14-A_Scoring_Model!$C$15)*(K9-$I9)/($H9-$I9))),IF(K9<=$H9,A_Scoring_Model!$C$14,IF(K9>$I9,0,A_Scoring_Model!$C$15+(A_Scoring_Model!$C$14-A_Scoring_Model!$C$15)*($I9-K9)/($I9-$H9)))))) -> 0 | P9: =IF(L9="","",IF($H9=$I9,IF(OR(AND($G9="Higher is better",L9>=$H9),AND($G9="Lower is better",L9<=$H9)),A_Scoring_Model!$C$14,0),IF($G9="Higher is better",IF(L9>=$H9,A_Scoring_Model!$C$14,IF(L9<$I9,0,A_Scoring_Model!$C$15+(A_Scoring_Model!$C$14-A_Scoring_Model!$C$15)*(L9-$I9)/($H9-$I9))),IF(L9<=$H9,A_Scoring_Model!$C$14,IF(L9>$I9,0,A_Scoring_Model!$C$15+(A_Scoring_Model!$C$14-A_Scoring_Model!$C$15)*($I9-L9)/($I9-$H9)))))) -> 100 | Q9: =IF(M9="","",IF($H9=$I9,IF(OR(AND($G9="Higher is better",M9>=$H9),AND($G9="Lower is better",M9<=$H9)),A_Scoring_Model!$C$14,0),IF($G9="Higher is better",IF(M9>=$H9,A_Scoring_Model!$C$14,IF(M9<$I9,0,A_Scoring_Model!$C$15+(A_Scoring_Model!$C$14-A_Scoring_Model!$C$15)*(M9-$I9)/($H9-$I9))),IF(M9<=$H9,A_Scoring_Model!$C$14,IF(M9>$I9,0,A_Scoring_Model!$C$15+(A_Scoring_Model!$C$14-A_Scoring_Model!$C$15)*($I9-M9)/($I9-$H9))))))
A10: =C_KPI_Benchmark!A10 -> 1.a-D2-06 | B10: =C_KPI_Benchmark!D10 -> 1.a | C10: =C_KPI_Benchmark!E10 -> NL Req Parsing & Classification Agent | D10: =C_KPI_Benchmark!F10 -> D2 | E10: =C_KPI_Benchmark!J10 -> Uses Zion shared services instead of re-implementing them | F10: =C_KPI_Benchmark!K10 -> Yes/No | G10: =C_KPI_Benchmark!L10 -> Higher is better | H10: =C_KPI_Benchmark!N10 -> 1 | I10: =IF(C_KPI_Benchmark!O10<>"",C_KPI_Benchmark!O10,IF(G10="Higher is better",H10*(1-A_Scoring_Model!$C$16),H10*(1+A_Scoring_Model!$C$16))) -> 0.8 | J10: 1 | K10: 0 | L10: 1 | N10: =IF(J10="","",IF($H10=$I10,IF(OR(AND($G10="Higher is better",J10>=$H10),AND($G10="Lower is better",J10<=$H10)),A_Scoring_Model!$C$14,0),IF($G10="Higher is better",IF(J10>=$H10,A_Scoring_Model!$C$14,IF(J10<$I10,0,A_Scoring_Model!$C$15+(A_Scoring_Model!$C$14-A_Scoring_Model!$C$15)*(J10-$I10)/($H10-$I10))),IF(J10<=$H10,A_Scoring_Model!$C$14,IF(J10>$I10,0,A_Scoring_Model!$C$15+(A_Scoring_Model!$C$14-A_Scoring_Model!$C$15)*($I10-J10)/($I10-$H10)))))) -> 100 | O10: =IF(K10="","",IF($H10=$I10,IF(OR(AND($G10="Higher is better",K10>=$H10),AND($G10="Lower is better",K10<=$H10)),A_Scoring_Model!$C$14,0),IF($G10="Higher is better",IF(K10>=$H10,A_Scoring_Model!$C$14,IF(K10<$I10,0,A_Scoring_Model!$C$15+(A_Scoring_Model!$C$14-A_Scoring_Model!$C$15)*(K10-$I10)/($H10-$I10))),IF(K10<=$H10,A_Scoring_Model!$C$14,IF(K10>$I10,0,A_Scoring_Model!$C$15+(A_Scoring_Model!$C$14-A_Scoring_Model!$C$15)*($I10-K10)/($I10-$H10)))))) -> 0 | P10: =IF(L10="","",IF($H10=$I10,IF(OR(AND($G10="Higher is better",L10>=$H10),AND($G10="Lower is better",L10<=$H10)),A_Scoring_Model!$C$14,0),IF($G10="Higher is better",IF(L10>=$H10,A_Scoring_Model!$C$14,IF(L10<$I10,0,A_Scoring_Model!$C$15+(A_Scoring_Model!$C$14-A_Scoring_Model!$C$15)*(L10-$I10)/($H10-$I10))),IF(L10<=$H10,A_Scoring_Model!$C$14,IF(L10>$I10,0,A_Scoring_Model!$C$15+(A_Scoring_Model!$C$14-A_Scoring_Model!$C$15)*($I10-L10)/($I10-$H10)))))) -> 100 | Q10: =IF(M10="","",IF($H10=$I10,IF(OR(AND($G10="Higher is better",M10>=$H10),AND($G10="Lower is better",M10<=$H10)),A_Scoring_Model!$C$14,0),IF($G10="Higher is better",IF(M10>=$H10,A_Scoring_Model!$C$14,IF(M10<$I10,0,A_Scoring_Model!$C$15+(A_Scoring_Model!$C$14-A_Scoring_Model!$C$15)*(M10-$I10)/($H10-$I10))),IF(M10<=$H10,A_Scoring_Model!$C$14,IF(M10>$I10,0,A_Scoring_Model!$C$15+(A_Scoring_Model!$C$14-A_Scoring_Model!$C$15)*($I10-M10)/($I10-$H10))))))
A11: =C_KPI_Benchmark!A11 -> 1.a-D3-07 | B11: =C_KPI_Benchmark!D11 -> 1.a | C11: =C_KPI_Benchmark!E11 -> NL Req Parsing & Classification Agent | D11: =C_KPI_Benchmark!F11 -> D3 | E11: =C_KPI_Benchmark!J11 -> Throughput | F11: =C_KPI_Benchmark!K11 -> pages/hr | G11: =C_KPI_Benchmark!L11 -> Higher is better | H11: =C_KPI_Benchmark!N11 -> 300 | I11: =IF(C_KPI_Benchmark!O11<>"",C_KPI_Benchmark!O11,IF(G11="Higher is better",H11*(1-A_Scoring_Model!$C$16),H11*(1+A_Scoring_Model!$C$16))) -> 240 | J11: 270 | K11: 320 | L11: 290 | N11: =IF(J11="","",IF($H11=$I11,IF(OR(AND($G11="Higher is better",J11>=$H11),AND($G11="Lower is better",J11<=$H11)),A_Scoring_Model!$C$14,0),IF($G11="Higher is better",IF(J11>=$H11,A_Scoring_Model!$C$14,IF(J11<$I11,0,A_Scoring_Model!$C$15+(A_Scoring_Model!$C$14-A_Scoring_Model!$C$15)*(J11-$I11)/($H11-$I11))),IF(J11<=$H11,A_Scoring_Model!$C$14,IF(J11>$I11,0,A_Scoring_Model!$C$15+(A_Scoring_Model!$C$14-A_Scoring_Model!$C$15)*($I11-J11)/($I11-$H11)))))) -> 80 | O11: =IF(K11="","",IF($H11=$I11,IF(OR(AND($G11="Higher is better",K11>=$H11),AND($G11="Lower is better",K11<=$H11)),A_Scoring_Model!$C$14,0),IF($G11="Higher is better",IF(K11>=$H11,A_Scoring_Model!$C$14,IF(K11<$I11,0,A_Scoring_Model!$C$15+(A_Scoring_Model!$C$14-A_Scoring_Model!$C$15)*(K11-$I11)/($H11-$I11))),IF(K11<=$H11,A_Scoring_Model!$C$14,IF(K11>$I11,0,A_Scoring_Model!$C$15+(A_Scoring_Model!$C$14-A_Scoring_Model!$C$15)*($I11-K11)/($I11-$H11)))))) -> 100 | P11: =IF(L11="","",IF($H11=$I11,IF(OR(AND($G11="Higher is better",L11>=$H11),AND($G11="Lower is better",L11<=$H11)),A_Scoring_Model!$C$14,0),IF($G11="Higher is better",IF(L11>=$H11,A_Scoring_Model!$C$14,IF(L11<$I11,0,A_Scoring_Model!$C$15+(A_Scoring_Model!$C$14-A_Scoring_Model!$C$15)*(L11-$I11)/($H11-$I11))),IF(L11<=$H11,A_Scoring_Model!$C$14,IF(L11>$I11,0,A_Scoring_Model!$C$15+(A_Scoring_Model!$C$14-A_Scoring_Model!$C$15)*($I11-L11)/($I11-$H11)))))) -> 93.333333 | Q11: =IF(M11="","",IF($H11=$I11,IF(OR(AND($G11="Higher is better",M11>=$H11),AND($G11="Lower is better",M11<=$H11)),A_Scoring_Model!$C$14,0),IF($G11="Higher is better",IF(M11>=$H11,A_Scoring_Model!$C$14,IF(M11<$I11,0,A_Scoring_Model!$C$15+(A_Scoring_Model!$C$14-A_Scoring_Model!$C$15)*(M11-$I11)/($H11-$I11))),IF(M11<=$H11,A_Scoring_Model!$C$14,IF(M11>$I11,0,A_Scoring_Model!$C$15+(A_Scoring_Model!$C$14-A_Scoring_Model!$C$15)*($I11-M11)/($I11-$H11))))))
A12: =C_KPI_Benchmark!A12 -> 1.a-D3-08 | B12: =C_KPI_Benchmark!D12 -> 1.a | C12: =C_KPI_Benchmark!E12 -> NL Req Parsing & Classification Agent | D12: =C_KPI_Benchmark!F12 -> D3 | E12: =C_KPI_Benchmark!J12 -> p95 latency per page | F12: =C_KPI_Benchmark!K12 -> s | G12: =C_KPI_Benchmark!L12 -> Lower is better | H12: =C_KPI_Benchmark!N12 -> 8 | I12: =IF(C_KPI_Benchmark!O12<>"",C_KPI_Benchmark!O12,IF(G12="Higher is better",H12*(1-A_Scoring_Model!$C$16),H12*(1+A_Scoring_Model!$C$16))) -> 9.6 | J12: 9 | K12: 7 | L12: 8.3 | N12: =IF(J12="","",IF($H12=$I12,IF(OR(AND($G12="Higher is better",J12>=$H12),AND($G12="Lower is better",J12<=$H12)),A_Scoring_Model!$C$14,0),IF($G12="Higher is better",IF(J12>=$H12,A_Scoring_Model!$C$14,IF(J12<$I12,0,A_Scoring_Model!$C$15+(A_Scoring_Model!$C$14-A_Scoring_Model!$C$15)*(J12-$I12)/($H12-$I12))),IF(J12<=$H12,A_Scoring_Model!$C$14,IF(J12>$I12,0,A_Scoring_Model!$C$15+(A_Scoring_Model!$C$14-A_Scoring_Model!$C$15)*($I12-J12)/($I12-$H12)))))) -> 75 | O12: =IF(K12="","",IF($H12=$I12,IF(OR(AND($G12="Higher is better",K12>=$H12),AND($G12="Lower is better",K12<=$H12)),A_Scoring_Model!$C$14,0),IF($G12="Higher is better",IF(K12>=$H12,A_Scoring_Model!$C$14,IF(K12<$I12,0,A_Scoring_Model!$C$15+(A_Scoring_Model!$C$14-A_Scoring_Model!$C$15)*(K12-$I12)/($H12-$I12))),IF(K12<=$H12,A_Scoring_Model!$C$14,IF(K12>$I12,0,A_Scoring_Model!$C$15+(A_Scoring_Model!$C$14-A_Scoring_Model!$C$15)*($I12-K12)/($I12-$H12)))))) -> 100 | P12: =IF(L12="","",IF($H12=$I12,IF(OR(AND($G12="Higher is better",L12>=$H12),AND($G12="Lower is better",L12<=$H12)),A_Scoring_Model!$C$14,0),IF($G12="Higher is better",IF(L12>=$H12,A_Scoring_Model!$C$14,IF(L12<$I12,0,A_Scoring_Model!$C$15+(A_Scoring_Model!$C$14-A_Scoring_Model!$C$15)*(L12-$I12)/($H12-$I12))),IF(L12<=$H12,A_Scoring_Model!$C$14,IF(L12>$I12,0,A_Scoring_Model!$C$15+(A_Scoring_Model!$C$14-A_Scoring_Model!$C$15)*($I12-L12)/($I12-$H12)))))) -> 92.5 | Q12: =IF(M12="","",IF($H12=$I12,IF(OR(AND($G12="Higher is better",M12>=$H12),AND($G12="Lower is better",M12<=$H12)),A_Scoring_Model!$C$14,0),IF($G12="Higher is better",IF(M12>=$H12,A_Scoring_Model!$C$14,IF(M12<$I12,0,A_Scoring_Model!$C$15+(A_Scoring_Model!$C$14-A_Scoring_Model!$C$15)*(M12-$I12)/($H12-$I12))),IF(M12<=$H12,A_Scoring_Model!$C$14,IF(M12>$I12,0,A_Scoring_Model!$C$15+(A_Scoring_Model!$C$14-A_Scoring_Model!$C$15)*($I12-M12)/($I12-$H12))))))
A13: =C_KPI_Benchmark!A13 -> 1.a-D3-09 | B13: =C_KPI_Benchmark!D13 -> 1.a | C13: =C_KPI_Benchmark!E13 -> NL Req Parsing & Classification Agent | D13: =C_KPI_Benchmark!F13 -> D3 | E13: =C_KPI_Benchmark!J13 -> Latency degradation at 10× load | F13: =C_KPI_Benchmark!K13 -> % | G13: =C_KPI_Benchmark!L13 -> Lower is better | H13: =C_KPI_Benchmark!N13 -> 0.2 | I13: =IF(C_KPI_Benchmark!O13<>"",C_KPI_Benchmark!O13,IF(G13="Higher is better",H13*(1-A_Scoring_Model!$C$16),H13*(1+A_Scoring_Model!$C$16))) -> 0.4 | J13: 0.28 | K13: 0.18 | L13: 0.22 | N13: =IF(J13="","",IF($H13=$I13,IF(OR(AND($G13="Higher is better",J13>=$H13),AND($G13="Lower is better",J13<=$H13)),A_Scoring_Model!$C$14,0),IF($G13="Higher is better",IF(J13>=$H13,A_Scoring_Model!$C$14,IF(J13<$I13,0,A_Scoring_Model!$C$15+(A_Scoring_Model!$C$14-A_Scoring_Model!$C$15)*(J13-$I13)/($H13-$I13))),IF(J13<=$H13,A_Scoring_Model!$C$14,IF(J13>$I13,0,A_Scoring_Model!$C$15+(A_Scoring_Model!$C$14-A_Scoring_Model!$C$15)*($I13-J13)/($I13-$H13)))))) -> 84 | O13: =IF(K13="","",IF($H13=$I13,IF(OR(AND($G13="Higher is better",K13>=$H13),AND($G13="Lower is better",K13<=$H13)),A_Scoring_Model!$C$14,0),IF($G13="Higher is better",IF(K13>=$H13,A_Scoring_Model!$C$14,IF(K13<$I13,0,A_Scoring_Model!$C$15+(A_Scoring_Model!$C$14-A_Scoring_Model!$C$15)*(K13-$I13)/($H13-$I13))),IF(K13<=$H13,A_Scoring_Model!$C$14,IF(K13>$I13,0,A_Scoring_Model!$C$15+(A_Scoring_Model!$C$14-A_Scoring_Model!$C$15)*($I13-K13)/($I13-$H13)))))) -> 100 | P13: =IF(L13="","",IF($H13=$I13,IF(OR(AND($G13="Higher is better",L13>=$H13),AND($G13="Lower is better",L13<=$H13)),A_Scoring_Model!$C$14,0),IF($G13="Higher is better",IF(L13>=$H13,A_Scoring_Model!$C$14,IF(L13<$I13,0,A_Scoring_Model!$C$15+(A_Scoring_Model!$C$14-A_Scoring_Model!$C$15)*(L13-$I13)/($H13-$I13))),IF(L13<=$H13,A_Scoring_Model!$C$14,IF(L13>$I13,0,A_Scoring_Model!$C$15+(A_Scoring_Model!$C$14-A_Scoring_Model!$C$15)*($I13-L13)/($I13-$H13)))))) -> 96 | Q13: =IF(M13="","",IF($H13=$I13,IF(OR(AND($G13="Higher is better",M13>=$H13),AND($G13="Lower is better",M13<=$H13)),A_Scoring_Model!$C$14,0),IF($G13="Higher is better",IF(M13>=$H13,A_Scoring_Model!$C$14,IF(M13<$I13,0,A_Scoring_Model!$C$15+(A_Scoring_Model!$C$14-A_Scoring_Model!$C$15)*(M13-$I13)/($H13-$I13))),IF(M13<=$H13,A_Scoring_Model!$C$14,IF(M13>$I13,0,A_Scoring_Model!$C$15+(A_Scoring_Model!$C$14-A_Scoring_Model!$C$15)*($I13-M13)/($I13-$H13))))))
A14: =C_KPI_Benchmark!A14 -> 1.a-D4-10 | B14: =C_KPI_Benchmark!D14 -> 1.a | C14: =C_KPI_Benchmark!E14 -> NL Req Parsing & Classification Agent | D14: =C_KPI_Benchmark!F14 -> D4 | E14: =C_KPI_Benchmark!J14 -> Hallucinated requirements | F14: =C_KPI_Benchmark!K14 -> % | G14: =C_KPI_Benchmark!L14 -> Lower is better | H14: =C_KPI_Benchmark!N14 -> 0.01 | I14: =IF(C_KPI_Benchmark!O14<>"",C_KPI_Benchmark!O14,IF(G14="Higher is better",H14*(1-A_Scoring_Model!$C$16),H14*(1+A_Scoring_Model!$C$16))) -> 0.012 | J14: 0.012 | K14: 0.008 | L14: 0.011 | N14: =IF(J14="","",IF($H14=$I14,IF(OR(AND($G14="Higher is better",J14>=$H14),AND($G14="Lower is better",J14<=$H14)),A_Scoring_Model!$C$14,0),IF($G14="Higher is better",IF(J14>=$H14,A_Scoring_Model!$C$14,IF(J14<$I14,0,A_Scoring_Model!$C$15+(A_Scoring_Model!$C$14-A_Scoring_Model!$C$15)*(J14-$I14)/($H14-$I14))),IF(J14<=$H14,A_Scoring_Model!$C$14,IF(J14>$I14,0,A_Scoring_Model!$C$15+(A_Scoring_Model!$C$14-A_Scoring_Model!$C$15)*($I14-J14)/($I14-$H14)))))) -> 60 | O14: =IF(K14="","",IF($H14=$I14,IF(OR(AND($G14="Higher is better",K14>=$H14),AND($G14="Lower is better",K14<=$H14)),A_Scoring_Model!$C$14,0),IF($G14="Higher is better",IF(K14>=$H14,A_Scoring_Model!$C$14,IF(K14<$I14,0,A_Scoring_Model!$C$15+(A_Scoring_Model!$C$14-A_Scoring_Model!$C$15)*(K14-$I14)/($H14-$I14))),IF(K14<=$H14,A_Scoring_Model!$C$14,IF(K14>$I14,0,A_Scoring_Model!$C$15+(A_Scoring_Model!$C$14-A_Scoring_Model!$C$15)*($I14-K14)/($I14-$H14)))))) -> 100 | P14: =IF(L14="","",IF($H14=$I14,IF(OR(AND($G14="Higher is better",L14>=$H14),AND($G14="Lower is better",L14<=$H14)),A_Scoring_Model!$C$14,0),IF($G14="Higher is better",IF(L14>=$H14,A_Scoring_Model!$C$14,IF(L14<$I14,0,A_Scoring_Model!$C$15+(A_Scoring_Model!$C$14-A_Scoring_Model!$C$15)*(L14-$I14)/($H14-$I14))),IF(L14<=$H14,A_Scoring_Model!$C$14,IF(L14>$I14,0,A_Scoring_Model!$C$15+(A_Scoring_Model!$C$14-A_Scoring_Model!$C$15)*($I14-L14)/($I14-$H14)))))) -> 80 | Q14: =IF(M14="","",IF($H14=$I14,IF(OR(AND($G14="Higher is better",M14>=$H14),AND($G14="Lower is better",M14<=$H14)),A_Scoring_Model!$C$14,0),IF($G14="Higher is better",IF(M14>=$H14,A_Scoring_Model!$C$14,IF(M14<$I14,0,A_Scoring_Model!$C$15+(A_Scoring_Model!$C$14-A_Scoring_Model!$C$15)*(M14-$I14)/($H14-$I14))),IF(M14<=$H14,A_Scoring_Model!$C$14,IF(M14>$I14,0,A_Scoring_Model!$C$15+(A_Scoring_Model!$C$14-A_Scoring_Model!$C$15)*($I14-M14)/($I14-$H14))))))
A15: =C_KPI_Benchmark!A15 -> 1.a-D4-11 | B15: =C_KPI_Benchmark!D15 -> 1.a | C15: =C_KPI_Benchmark!E15 -> NL Req Parsing & Classification Agent | D15: =C_KPI_Benchmark!F15 -> D4 | E15: =C_KPI_Benchmark!J15 -> Run-to-run agreement (temperature 0) | F15: =C_KPI_Benchmark!K15 -> % | G15: =C_KPI_Benchmark!L15 -> Higher is better | H15: =C_KPI_Benchmark!N15 -> 0.97 | I15: =IF(C_KPI_Benchmark!O15<>"",C_KPI_Benchmark!O15,IF(G15="Higher is better",H15*(1-A_Scoring_Model!$C$16),H15*(1+A_Scoring_Model!$C$16))) -> 0.776 | J15: 0.95 | K15: 0.98 | L15: 0.97 | N15: =IF(J15="","",IF($H15=$I15,IF(OR(AND($G15="Higher is better",J15>=$H15),AND($G15="Lower is better",J15<=$H15)),A_Scoring_Model!$C$14,0),IF($G15="Higher is better",IF(J15>=$H15,A_Scoring_Model!$C$14,IF(J15<$I15,0,A_Scoring_Model!$C$15+(A_Scoring_Model!$C$14-A_Scoring_Model!$C$15)*(J15-$I15)/($H15-$I15))),IF(J15<=$H15,A_Scoring_Model!$C$14,IF(J15>$I15,0,A_Scoring_Model!$C$15+(A_Scoring_Model!$C$14-A_Scoring_Model!$C$15)*($I15-J15)/($I15-$H15)))))) -> 95.876289 | O15: =IF(K15="","",IF($H15=$I15,IF(OR(AND($G15="Higher is better",K15>=$H15),AND($G15="Lower is better",K15<=$H15)),A_Scoring_Model!$C$14,0),IF($G15="Higher is better",IF(K15>=$H15,A_Scoring_Model!$C$14,IF(K15<$I15,0,A_Scoring_Model!$C$15+(A_Scoring_Model!$C$14-A_Scoring_Model!$C$15)*(K15-$I15)/($H15-$I15))),IF(K15<=$H15,A_Scoring_Model!$C$14,IF(K15>$I15,0,A_Scoring_Model!$C$15+(A_Scoring_Model!$C$14-A_Scoring_Model!$C$15)*($I15-K15)/($I15-$H15)))))) -> 100 | P15: =IF(L15="","",IF($H15=$I15,IF(OR(AND($G15="Higher is better",L15>=$H15),AND($G15="Lower is better",L15<=$H15)),A_Scoring_Model!$C$14,0),IF($G15="Higher is better",IF(L15>=$H15,A_Scoring_Model!$C$14,IF(L15<$I15,0,A_Scoring_Model!$C$15+(A_Scoring_Model!$C$14-A_Scoring_Model!$C$15)*(L15-$I15)/($H15-$I15))),IF(L15<=$H15,A_Scoring_Model!$C$14,IF(L15>$I15,0,A_Scoring_Model!$C$15+(A_Scoring_Model!$C$14-A_Scoring_Model!$C$15)*($I15-L15)/($I15-$H15)))))) -> 100 | Q15: =IF(M15="","",IF($H15=$I15,IF(OR(AND($G15="Higher is better",M15>=$H15),AND($G15="Lower is better",M15<=$H15)),A_Scoring_Model!$C$14,0),IF($G15="Higher is better",IF(M15>=$H15,A_Scoring_Model!$C$14,IF(M15<$I15,0,A_Scoring_Model!$C$15+(A_Scoring_Model!$C$14-A_Scoring_Model!$C$15)*(M15-$I15)/($H15-$I15))),IF(M15<=$H15,A_Scoring_Model!$C$14,IF(M15>$I15,0,A_Scoring_Model!$C$15+(A_Scoring_Model!$C$14-A_Scoring_Model!$C$15)*($I15-M15)/($I15-$H15))))))
A16: =C_KPI_Benchmark!A16 -> 1.a-D4-12 | B16: =C_KPI_Benchmark!D16 -> 1.a | C16: =C_KPI_Benchmark!E16 -> NL Req Parsing & Classification Agent | D16: =C_KPI_Benchmark!F16 -> D4 | E16: =C_KPI_Benchmark!J16 -> Service availability | F16: =C_KPI_Benchmark!K16 -> % | G16: =C_KPI_Benchmark!L16 -> Higher is better | H16: =C_KPI_Benchmark!N16 -> 0.995 | I16: =IF(C_KPI_Benchmark!O16<>"",C_KPI_Benchmark!O16,IF(G16="Higher is better",H16*(1-A_Scoring_Model!$C$16),H16*(1+A_Scoring_Model!$C$16))) -> 0.99 | J16: 0.993 | K16: 0.99 | L16: 0.996 | N16: =IF(J16="","",IF($H16=$I16,IF(OR(AND($G16="Higher is better",J16>=$H16),AND($G16="Lower is better",J16<=$H16)),A_Scoring_Model!$C$14,0),IF($G16="Higher is better",IF(J16>=$H16,A_Scoring_Model!$C$14,IF(J16<$I16,0,A_Scoring_Model!$C$15+(A_Scoring_Model!$C$14-A_Scoring_Model!$C$15)*(J16-$I16)/($H16-$I16))),IF(J16<=$H16,A_Scoring_Model!$C$14,IF(J16>$I16,0,A_Scoring_Model!$C$15+(A_Scoring_Model!$C$14-A_Scoring_Model!$C$15)*($I16-J16)/($I16-$H16)))))) -> 84 | O16: =IF(K16="","",IF($H16=$I16,IF(OR(AND($G16="Higher is better",K16>=$H16),AND($G16="Lower is better",K16<=$H16)),A_Scoring_Model!$C$14,0),IF($G16="Higher is better",IF(K16>=$H16,A_Scoring_Model!$C$14,IF(K16<$I16,0,A_Scoring_Model!$C$15+(A_Scoring_Model!$C$14-A_Scoring_Model!$C$15)*(K16-$I16)/($H16-$I16))),IF(K16<=$H16,A_Scoring_Model!$C$14,IF(K16>$I16,0,A_Scoring_Model!$C$15+(A_Scoring_Model!$C$14-A_Scoring_Model!$C$15)*($I16-K16)/($I16-$H16)))))) -> 60 | P16: =IF(L16="","",IF($H16=$I16,IF(OR(AND($G16="Higher is better",L16>=$H16),AND($G16="Lower is better",L16<=$H16)),A_Scoring_Model!$C$14,0),IF($G16="Higher is better",IF(L16>=$H16,A_Scoring_Model!$C$14,IF(L16<$I16,0,A_Scoring_Model!$C$15+(A_Scoring_Model!$C$14-A_Scoring_Model!$C$15)*(L16-$I16)/($H16-$I16))),IF(L16<=$H16,A_Scoring_Model!$C$14,IF(L16>$I16,0,A_Scoring_Model!$C$15+(A_Scoring_Model!$C$14-A_Scoring_Model!$C$15)*($I16-L16)/($I16-$H16)))))) -> 100 | Q16: =IF(M16="","",IF($H16=$I16,IF(OR(AND($G16="Higher is better",M16>=$H16),AND($G16="Lower is better",M16<=$H16)),A_Scoring_Model!$C$14,0),IF($G16="Higher is better",IF(M16>=$H16,A_Scoring_Model!$C$14,IF(M16<$I16,0,A_Scoring_Model!$C$15+(A_Scoring_Model!$C$14-A_Scoring_Model!$C$15)*(M16-$I16)/($H16-$I16))),IF(M16<=$H16,A_Scoring_Model!$C$14,IF(M16>$I16,0,A_Scoring_Model!$C$15+(A_Scoring_Model!$C$14-A_Scoring_Model!$C$15)*($I16-M16)/($I16-$H16))))))
... A23: =C_KPI_Benchmark!A23 -> 1.a-D6-19 | B23: =C_KPI_Benchmark!D23 -> 1.a | C23: =C_KPI_Benchmark!E23 -> NL Req Parsing & Classification Agent | D23: =C_KPI_Benchmark!F23 -> D6 | E23: =C_KPI_Benchmark!J23 -> Named owner and support SLA | F23: =C_KPI_Benchmark!K23 -> Yes/No | G23: =C_KPI_Benchmark!L23 -> Higher is better | H23: =C_KPI_Benchmark!N23 -> 1 | I23: =IF(C_KPI_Benchmark!O23<>"",C_KPI_Benchmark!O23,IF(G23="Higher is better",H23*(1-A_Scoring_Model!$C$16),H23*(1+A_Scoring_Model!$C$16))) -> 0.8 | J23: 1 | K23: 1 | L23: 1 | N23: =IF(J23="","",IF($H23=$I23,IF(OR(AND($G23="Higher is better",J23>=$H23),AND($G23="Lower is better",J23<=$H23)),A_Scoring_Model!$C$14,0),IF($G23="Higher is better",IF(J23>=$H23,A_Scoring_Model!$C$14,IF(J23<$I23,0,A_Scoring_Model!$C$15+(A_Scoring_Model!$C$14-A_Scoring_Model!$C$15)*(J23-$I23)/($H23-$I23))),IF(J23<=$H23,A_Scoring_Model!$C$14,IF(J23>$I23,0,A_Scoring_Model!$C$15+(A_Scoring_Model!$C$14-A_Scoring_Model!$C$15)*($I23-J23)/($I23-$H23)))))) -> 100 | O23: =IF(K23="","",IF($H23=$I23,IF(OR(AND($G23="Higher is better",K23>=$H23),AND($G23="Lower is better",K23<=$H23)),A_Scoring_Model!$C$14,0),IF($G23="Higher is better",IF(K23>=$H23,A_Scoring_Model!$C$14,IF(K23<$I23,0,A_Scoring_Model!$C$15+(A_Scoring_Model!$C$14-A_Scoring_Model!$C$15)*(K23-$I23)/($H23-$I23))),IF(K23<=$H23,A_Scoring_Model!$C$14,IF(K23>$I23,0,A_Scoring_Model!$C$15+(A_Scoring_Model!$C$14-A_Scoring_Model!$C$15)*($I23-K23)/($I23-$H23)))))) -> 100 | P23: =IF(L23="","",IF($H23=$I23,IF(OR(AND($G23="Higher is better",L23>=$H23),AND($G23="Lower is better",L23<=$H23)),A_Scoring_Model!$C$14,0),IF($G23="Higher is better",IF(L23>=$H23,A_Scoring_Model!$C$14,IF(L23<$I23,0,A_Scoring_Model!$C$15+(A_Scoring_Model!$C$14-A_Scoring_Model!$C$15)*(L23-$I23)/($H23-$I23))),IF(L23<=$H23,A_Scoring_Model!$C$14,IF(L23>$I23,0,A_Scoring_Model!$C$15+(A_Scoring_Model!$C$14-A_Scoring_Model!$C$15)*($I23-L23)/($I23-$H23)))))) -> 100 | Q23: =IF(M23="","",IF($H23=$I23,IF(OR(AND($G23="Higher is better",M23>=$H23),AND($G23="Lower is better",M23<=$H23)),A_Scoring_Model!$C$14,0),IF($G23="Higher is better",IF(M23>=$H23,A_Scoring_Model!$C$14,IF(M23<$I23,0,A_Scoring_Model!$C$15+(A_Scoring_Model!$C$14-A_Scoring_Model!$C$15)*(M23-$I23)/($H23-$I23))),IF(M23<=$H23,A_Scoring_Model!$C$14,IF(M23>$I23,0,A_Scoring_Model!$C$15+(A_Scoring_Model!$C$14-A_Scoring_Model!$C$15)*($I23-M23)/($I23-$H23))))))
A24: =C_KPI_Benchmark!A24 -> 1.b-D1-01 | B24: =C_KPI_Benchmark!D24 -> 1.b | C24: =C_KPI_Benchmark!E24 -> Feasibility & Quality Analyzer | D24: =C_KPI_Benchmark!F24 -> D1 | E24: =C_KPI_Benchmark!J24 -> Requirement-defect detection precision | F24: =C_KPI_Benchmark!K24 -> ratio | G24: =C_KPI_Benchmark!L24 -> Higher is better | H24: =C_KPI_Benchmark!N24 -> 0.85 | I24: =IF(C_KPI_Benchmark!O24<>"",C_KPI_Benchmark!O24,IF(G24="Higher is better",H24*(1-A_Scoring_Model!$C$16),H24*(1+A_Scoring_Model!$C$16))) -> 0.75 | N24: =IF(J24="","",IF($H24=$I24,IF(OR(AND($G24="Higher is better",J24>=$H24),AND($G24="Lower is better",J24<=$H24)),A_Scoring_Model!$C$14,0),IF($G24="Higher is better",IF(J24>=$H24,A_Scoring_Model!$C$14,IF(J24<$I24,0,A_Scoring_Model!$C$15+(A_Scoring_Model!$C$14-A_Scoring_Model!$C$15)*(J24-$I24)/($H24-$I24))),IF(J24<=$H24,A_Scoring_Model!$C$14,IF(J24>$I24,0,A_Scoring_Model!$C$15+(A_Scoring_Model!$C$14-A_Scoring_Model!$C$15)*($I24-J24)/($I24-$H24)))))) | O24: =IF(K24="","",IF($H24=$I24,IF(OR(AND($G24="Higher is better",K24>=$H24),AND($G24="Lower is better",K24<=$H24)),A_Scoring_Model!$C$14,0),IF($G24="Higher is better",IF(K24>=$H24,A_Scoring_Model!$C$14,IF(K24<$I24,0,A_Scoring_Model!$C$15+(A_Scoring_Model!$C$14-A_Scoring_Model!$C$15)*(K24-$I24)/($H24-$I24))),IF(K24<=$H24,A_Scoring_Model!$C$14,IF(K24>$I24,0,A_Scoring_Model!$C$15+(A_Scoring_Model!$C$14-A_Scoring_Model!$C$15)*($I24-K24)/($I24-$H24)))))) | P24: =IF(L24="","",IF($H24=$I24,IF(OR(AND($G24="Higher is better",L24>=$H24),AND($G24="Lower is better",L24<=$H24)),A_Scoring_Model!$C$14,0),IF($G24="Higher is better",IF(L24>=$H24,A_Scoring_Model!$C$14,IF(L24<$I24,0,A_Scoring_Model!$C$15+(A_Scoring_Model!$C$14-A_Scoring_Model!$C$15)*(L24-$I24)/($H24-$I24))),IF(L24<=$H24,A_Scoring_Model!$C$14,IF(L24>$I24,0,A_Scoring_Model!$C$15+(A_Scoring_Model!$C$14-A_Scoring_Model!$C$15)*($I24-L24)/($I24-$H24)))))) | Q24: =IF(M24="","",IF($H24=$I24,IF(OR(AND($G24="Higher is better",M24>=$H24),AND($G24="Lower is better",M24<=$H24)),A_Scoring_Model!$C$14,0),IF($G24="Higher is better",IF(M24>=$H24,A_Scoring_Model!$C$14,IF(M24<$I24,0,A_Scoring_Model!$C$15+(A_Scoring_Model!$C$14-A_Scoring_Model!$C$15)*(M24-$I24)/($H24-$I24))),IF(M24<=$H24,A_Scoring_Model!$C$14,IF(M24>$I24,0,A_Scoring_Model!$C$15+(A_Scoring_Model!$C$14-A_Scoring_Model!$C$15)*($I24-M24)/($I24-$H24))))))
A25: =C_KPI_Benchmark!A25 -> 1.b-D1-02 | B25: =C_KPI_Benchmark!D25 -> 1.b | C25: =C_KPI_Benchmark!E25 -> Feasibility & Quality Analyzer | D25: =C_KPI_Benchmark!F25 -> D1 | E25: =C_KPI_Benchmark!J25 -> Requirement-defect detection recall | F25: =C_KPI_Benchmark!K25 -> ratio | G25: =C_KPI_Benchmark!L25 -> Higher is better | H25: =C_KPI_Benchmark!N25 -> 0.8 | I25: =IF(C_KPI_Benchmark!O25<>"",C_KPI_Benchmark!O25,IF(G25="Higher is better",H25*(1-A_Scoring_Model!$C$16),H25*(1+A_Scoring_Model!$C$16))) -> 0.7 | N25: =IF(J25="","",IF($H25=$I25,IF(OR(AND($G25="Higher is better",J25>=$H25),AND($G25="Lower is better",J25<=$H25)),A_Scoring_Model!$C$14,0),IF($G25="Higher is better",IF(J25>=$H25,A_Scoring_Model!$C$14,IF(J25<$I25,0,A_Scoring_Model!$C$15+(A_Scoring_Model!$C$14-A_Scoring_Model!$C$15)*(J25-$I25)/($H25-$I25))),IF(J25<=$H25,A_Scoring_Model!$C$14,IF(J25>$I25,0,A_Scoring_Model!$C$15+(A_Scoring_Model!$C$14-A_Scoring_Model!$C$15)*($I25-J25)/($I25-$H25)))))) | O25: =IF(K25="","",IF($H25=$I25,IF(OR(AND($G25="Higher is better",K25>=$H25),AND($G25="Lower is better",K25<=$H25)),A_Scoring_Model!$C$14,0),IF($G25="Higher is better",IF(K25>=$H25,A_Scoring_Model!$C$14,IF(K25<$I25,0,A_Scoring_Model!$C$15+(A_Scoring_Model!$C$14-A_Scoring_Model!$C$15)*(K25-$I25)/($H25-$I25))),IF(K25<=$H25,A_Scoring_Model!$C$14,IF(K25>$I25,0,A_Scoring_Model!$C$15+(A_Scoring_Model!$C$14-A_Scoring_Model!$C$15)*($I25-K25)/($I25-$H25)))))) | P25: =IF(L25="","",IF($H25=$I25,IF(OR(AND($G25="Higher is better",L25>=$H25),AND($G25="Lower is better",L25<=$H25)),A_Scoring_Model!$C$14,0),IF($G25="Higher is better",IF(L25>=$H25,A_Scoring_Model!$C$14,IF(L25<$I25,0,A_Scoring_Model!$C$15+(A_Scoring_Model!$C$14-A_Scoring_Model!$C$15)*(L25-$I25)/($H25-$I25))),IF(L25<=$H25,A_Scoring_Model!$C$14,IF(L25>$I25,0,A_Scoring_Model!$C$15+(A_Scoring_Model!$C$14-A_Scoring_Model!$C$15)*($I25-L25)/($I25-$H25)))))) | Q25: =IF(M25="","",IF($H25=$I25,IF(OR(AND($G25="Higher is better",M25>=$H25),AND($G25="Lower is better",M25<=$H25)),A_Scoring_Model!$C$14,0),IF($G25="Higher is better",IF(M25>=$H25,A_Scoring_Model!$C$14,IF(M25<$I25,0,A_Scoring_Model!$C$15+(A_Scoring_Model!$C$14-A_Scoring_Model!$C$15)*(M25-$I25)/($H25-$I25))),IF(M25<=$H25,A_Scoring_Model!$C$14,IF(M25>$I25,0,A_Scoring_Model!$C$15+(A_Scoring_Model!$C$14-A_Scoring_Model!$C$15)*($I25-M25)/($I25-$H25))))))
A26: =C_KPI_Benchmark!A26 -> 1.b-D1-03 | B26: =C_KPI_Benchmark!D26 -> 1.b | C26: =C_KPI_Benchmark!E26 -> Feasibility & Quality Analyzer | D26: =C_KPI_Benchmark!F26 -> D1 | E26: =C_KPI_Benchmark!J26 -> Conflicting-pair detection recall | F26: =C_KPI_Benchmark!K26 -> ratio | G26: =C_KPI_Benchmark!L26 -> Higher is better | H26: =C_KPI_Benchmark!N26 -> 0.75 | I26: =IF(C_KPI_Benchmark!O26<>"",C_KPI_Benchmark!O26,IF(G26="Higher is better",H26*(1-A_Scoring_Model!$C$16),H26*(1+A_Scoring_Model!$C$16))) -> 0.6 | N26: =IF(J26="","",IF($H26=$I26,IF(OR(AND($G26="Higher is better",J26>=$H26),AND($G26="Lower is better",J26<=$H26)),A_Scoring_Model!$C$14,0),IF($G26="Higher is better",IF(J26>=$H26,A_Scoring_Model!$C$14,IF(J26<$I26,0,A_Scoring_Model!$C$15+(A_Scoring_Model!$C$14-A_Scoring_Model!$C$15)*(J26-$I26)/($H26-$I26))),IF(J26<=$H26,A_Scoring_Model!$C$14,IF(J26>$I26,0,A_Scoring_Model!$C$15+(A_Scoring_Model!$C$14-A_Scoring_Model!$C$15)*($I26-J26)/($I26-$H26)))))) | O26: =IF(K26="","",IF($H26=$I26,IF(OR(AND($G26="Higher is better",K26>=$H26),AND($G26="Lower is better",K26<=$H26)),A_Scoring_Model!$C$14,0),IF($G26="Higher is better",IF(K26>=$H26,A_Scoring_Model!$C$14,IF(K26<$I26,0,A_Scoring_Model!$C$15+(A_Scoring_Model!$C$14-A_Scoring_Model!$C$15)*(K26-$I26)/($H26-$I26))),IF(K26<=$H26,A_Scoring_Model!$C$14,IF(K26>$I26,0,A_Scoring_Model!$C$15+(A_Scoring_Model!$C$14-A_Scoring_Model!$C$15)*($I26-K26)/($I26-$H26)))))) | P26: =IF(L26="","",IF($H26=$I26,IF(OR(AND($G26="Higher is better",L26>=$H26),AND($G26="Lower is better",L26<=$H26)),A_Scoring_Model!$C$14,0),IF($G26="Higher is better",IF(L26>=$H26,A_Scoring_Model!$C$14,IF(L26<$I26,0,A_Scoring_Model!$C$15+(A_Scoring_Model!$C$14-A_Scoring_Model!$C$15)*(L26-$I26)/($H26-$I26))),IF(L26<=$H26,A_Scoring_Model!$C$14,IF(L26>$I26,0,A_Scoring_Model!$C$15+(A_Scoring_Model!$C$14-A_Scoring_Model!$C$15)*($I26-L26)/($I26-$H26)))))) | Q26: =IF(M26="","",IF($H26=$I26,IF(OR(AND($G26="Higher is better",M26>=$H26),AND($G26="Lower is better",M26<=$H26)),A_Scoring_Model!$C$14,0),IF($G26="Higher is better",IF(M26>=$H26,A_Scoring_Model!$C$14,IF(M26<$I26,0,A_Scoring_Model!$C$15+(A_Scoring_Model!$C$14-A_Scoring_Model!$C$15)*(M26-$I26)/($H26-$I26))),IF(M26<=$H26,A_Scoring_Model!$C$14,IF(M26>$I26,0,A_Scoring_Model!$C$15+(A_Scoring_Model!$C$14-A_Scoring_Model!$C$15)*($I26-M26)/($I26-$H26))))))
A27: =C_KPI_Benchmark!A27 -> 1.b-D1-04 | B27: =C_KPI_Benchmark!D27 -> 1.b | C27: =C_KPI_Benchmark!E27 -> Feasibility & Quality Analyzer | D27: =C_KPI_Benchmark!F27 -> D1 | E27: =C_KPI_Benchmark!J27 -> Rewrite suggestion acceptance | F27: =C_KPI_Benchmark!K27 -> % | G27: =C_KPI_Benchmark!L27 -> Higher is better | H27: =C_KPI_Benchmark!N27 -> 0.7 | I27: =IF(C_KPI_Benchmark!O27<>"",C_KPI_Benchmark!O27,IF(G27="Higher is better",H27*(1-A_Scoring_Model!$C$16),H27*(1+A_Scoring_Model!$C$16))) -> 0.55 | N27: =IF(J27="","",IF($H27=$I27,IF(OR(AND($G27="Higher is better",J27>=$H27),AND($G27="Lower is better",J27<=$H27)),A_Scoring_Model!$C$14,0),IF($G27="Higher is better",IF(J27>=$H27,A_Scoring_Model!$C$14,IF(J27<$I27,0,A_Scoring_Model!$C$15+(A_Scoring_Model!$C$14-A_Scoring_Model!$C$15)*(J27-$I27)/($H27-$I27))),IF(J27<=$H27,A_Scoring_Model!$C$14,IF(J27>$I27,0,A_Scoring_Model!$C$15+(A_Scoring_Model!$C$14-A_Scoring_Model!$C$15)*($I27-J27)/($I27-$H27)))))) | O27: =IF(K27="","",IF($H27=$I27,IF(OR(AND($G27="Higher is better",K27>=$H27),AND($G27="Lower is better",K27<=$H27)),A_Scoring_Model!$C$14,0),IF($G27="Higher is better",IF(K27>=$H27,A_Scoring_Model!$C$14,IF(K27<$I27,0,A_Scoring_Model!$C$15+(A_Scoring_Model!$C$14-A_Scoring_Model!$C$15)*(K27-$I27)/($H27-$I27))),IF(K27<=$H27,A_Scoring_Model!$C$14,IF(K27>$I27,0,A_Scoring_Model!$C$15+(A_Scoring_Model!$C$14-A_Scoring_Model!$C$15)*($I27-K27)/($I27-$H27)))))) | P27: =IF(L27="","",IF($H27=$I27,IF(OR(AND($G27="Higher is better",L27>=$H27),AND($G27="Lower is better",L27<=$H27)),A_Scoring_Model!$C$14,0),IF($G27="Higher is better",IF(L27>=$H27,A_Scoring_Model!$C$14,IF(L27<$I27,0,A_Scoring_Model!$C$15+(A_Scoring_Model!$C$14-A_Scoring_Model!$C$15)*(L27-$I27)/($H27-$I27))),IF(L27<=$H27,A_Scoring_Model!$C$14,IF(L27>$I27,0,A_Scoring_Model!$C$15+(A_Scoring_Model!$C$14-A_Scoring_Model!$C$15)*($I27-L27)/($I27-$H27)))))) | Q27: =IF(M27="","",IF($H27=$I27,IF(OR(AND($G27="Higher is better",M27>=$H27),AND($G27="Lower is better",M27<=$H27)),A_Scoring_Model!$C$14,0),IF($G27="Higher is better",IF(M27>=$H27,A_Scoring_Model!$C$14,IF(M27<$I27,0,A_Scoring_Model!$C$15+(A_Scoring_Model!$C$14-A_Scoring_Model!$C$15)*(M27-$I27)/($H27-$I27))),IF(M27<=$H27,A_Scoring_Model!$C$14,IF(M27>$I27,0,A_Scoring_Model!$C$15+(A_Scoring_Model!$C$14-A_Scoring_Model!$C$15)*($I27-M27)/($I27-$H27))))))
A28: =C_KPI_Benchmark!A28 -> 1.b-D2-05 | B28: =C_KPI_Benchmark!D28 -> 1.b | C28: =C_KPI_Benchmark!E28 -> Feasibility & Quality Analyzer | D28: =C_KPI_Benchmark!F28 -> D2 | E28: =C_KPI_Benchmark!J28 -> Pluggable rule packs (29148 + group checklists) | F28: =C_KPI_Benchmark!K28 -> Yes/No | G28: =C_KPI_Benchmark!L28 -> Higher is better | H28: =C_KPI_Benchmark!N28 -> 1 | I28: =IF(C_KPI_Benchmark!O28<>"",C_KPI_Benchmark!O28,IF(G28="Higher is better",H28*(1-A_Scoring_Model!$C$16),H28*(1+A_Scoring_Model!$C$16))) -> 0.8 | N28: =IF(J28="","",IF($H28=$I28,IF(OR(AND($G28="Higher is better",J28>=$H28),AND($G28="Lower is better",J28<=$H28)),A_Scoring_Model!$C$14,0),IF($G28="Higher is better",IF(J28>=$H28,A_Scoring_Model!$C$14,IF(J28<$I28,0,A_Scoring_Model!$C$15+(A_Scoring_Model!$C$14-A_Scoring_Model!$C$15)*(J28-$I28)/($H28-$I28))),IF(J28<=$H28,A_Scoring_Model!$C$14,IF(J28>$I28,0,A_Scoring_Model!$C$15+(A_Scoring_Model!$C$14-A_Scoring_Model!$C$15)*($I28-J28)/($I28-$H28)))))) | O28: =IF(K28="","",IF($H28=$I28,IF(OR(AND($G28="Higher is better",K28>=$H28),AND($G28="Lower is better",K28<=$H28)),A_Scoring_Model!$C$14,0),IF($G28="Higher is better",IF(K28>=$H28,A_Scoring_Model!$C$14,IF(K28<$I28,0,A_Scoring_Model!$C$15+(A_Scoring_Model!$C$14-A_Scoring_Model!$C$15)*(K28-$I28)/($H28-$I28))),IF(K28<=$H28,A_Scoring_Model!$C$14,IF(K28>$I28,0,A_Scoring_Model!$C$15+(A_Scoring_Model!$C$14-A_Scoring_Model!$C$15)*($I28-K28)/($I28-$H28)))))) | P28: =IF(L28="","",IF($H28=$I28,IF(OR(AND($G28="Higher is better",L28>=$H28),AND($G28="Lower is better",L28<=$H28)),A_Scoring_Model!$C$14,0),IF($G28="Higher is better",IF(L28>=$H28,A_Scoring_Model!$C$14,IF(L28<$I28,0,A_Scoring_Model!$C$15+(A_Scoring_Model!$C$14-A_Scoring_Model!$C$15)*(L28-$I28)/($H28-$I28))),IF(L28<=$H28,A_Scoring_Model!$C$14,IF(L28>$I28,0,A_Scoring_Model!$C$15+(A_Scoring_Model!$C$14-A_Scoring_Model!$C$15)*($I28-L28)/($I28-$H28)))))) | Q28: =IF(M28="","",IF($H28=$I28,IF(OR(AND($G28="Higher is better",M28>=$H28),AND($G28="Lower is better",M28<=$H28)),A_Scoring_Model!$C$14,0),IF($G28="Higher is better",IF(M28>=$H28,A_Scoring_Model!$C$14,IF(M28<$I28,0,A_Scoring_Model!$C$15+(A_Scoring_Model!$C$14-A_Scoring_Model!$C$15)*(M28-$I28)/($H28-$I28))),IF(M28<=$H28,A_Scoring_Model!$C$14,IF(M28>$I28,0,A_Scoring_Model!$C$15+(A_Scoring_Model!$C$14-A_Scoring_Model!$C$15)*($I28-M28)/($I28-$H28))))))
A29: =C_KPI_Benchmark!A29 -> 1.b-D2-06 | B29: =C_KPI_Benchmark!D29 -> 1.b | C29: =C_KPI_Benchmark!E29 -> Feasibility & Quality Analyzer | D29: =C_KPI_Benchmark!F29 -> D2 | E29: =C_KPI_Benchmark!J29 -> Product lines supported with ≤10% efficacy drop (NVMe SSD, UFS, eMMC/uSD, PSSD) | F29: =C_KPI_Benchmark!K29 -> count | G29: =C_KPI_Benchmark!L29 -> Higher is better | H29: =C_KPI_Benchmark!N29 -> 3 | I29: =IF(C_KPI_Benchmark!O29<>"",C_KPI_Benchmark!O29,IF(G29="Higher is better",H29*(1-A_Scoring_Model!$C$16),H29*(1+A_Scoring_Model!$C$16))) -> 2 | N29: =IF(J29="","",IF($H29=$I29,IF(OR(AND($G29="Higher is better",J29>=$H29),AND($G29="Lower is better",J29<=$H29)),A_Scoring_Model!$C$14,0),IF($G29="Higher is better",IF(J29>=$H29,A_Scoring_Model!$C$14,IF(J29<$I29,0,A_Scoring_Model!$C$15+(A_Scoring_Model!$C$14-A_Scoring_Model!$C$15)*(J29-$I29)/($H29-$I29))),IF(J29<=$H29,A_Scoring_Model!$C$14,IF(J29>$I29,0,A_Scoring_Model!$C$15+(A_Scoring_Model!$C$14-A_Scoring_Model!$C$15)*($I29-J29)/($I29-$H29)))))) | O29: =IF(K29="","",IF($H29=$I29,IF(OR(AND($G29="Higher is better",K29>=$H29),AND($G29="Lower is better",K29<=$H29)),A_Scoring_Model!$C$14,0),IF($G29="Higher is better",IF(K29>=$H29,A_Scoring_Model!$C$14,IF(K29<$I29,0,A_Scoring_Model!$C$15+(A_Scoring_Model!$C$14-A_Scoring_Model!$C$15)*(K29-$I29)/($H29-$I29))),IF(K29<=$H29,A_Scoring_Model!$C$14,IF(K29>$I29,0,A_Scoring_Model!$C$15+(A_Scoring_Model!$C$14-A_Scoring_Model!$C$15)*($I29-K29)/($I29-$H29)))))) | P29: =IF(L29="","",IF($H29=$I29,IF(OR(AND($G29="Higher is better",L29>=$H29),AND($G29="Lower is better",L29<=$H29)),A_Scoring_Model!$C$14,0),IF($G29="Higher is better",IF(L29>=$H29,A_Scoring_Model!$C$14,IF(L29<$I29,0,A_Scoring_Model!$C$15+(A_Scoring_Model!$C$14-A_Scoring_Model!$C$15)*(L29-$I29)/($H29-$I29))),IF(L29<=$H29,A_Scoring_Model!$C$14,IF(L29>$I29,0,A_Scoring_Model!$C$15+(A_Scoring_Model!$C$14-A_Scoring_Model!$C$15)*($I29-L29)/($I29-$H29)))))) | Q29: =IF(M29="","",IF($H29=$I29,IF(OR(AND($G29="Higher is better",M29>=$H29),AND($G29="Lower is better",M29<=$H29)),A_Scoring_Model!$C$14,0),IF($G29="Higher is better",IF(M29>=$H29,A_Scoring_Model!$C$14,IF(M29<$I29,0,A_Scoring_Model!$C$15+(A_Scoring_Model!$C$14-A_Scoring_Model!$C$15)*(M29-$I29)/($H29-$I29))),IF(M29<=$H29,A_Scoring_Model!$C$14,IF(M29>$I29,0,A_Scoring_Model!$C$15+(A_Scoring_Model!$C$14-A_Scoring_Model!$C$15)*($I29-M29)/($I29-$H29))))))
A30: =C_KPI_Benchmark!A30 -> 1.b-D2-07 | B30: =C_KPI_Benchmark!D30 -> 1.b | C30: =C_KPI_Benchmark!E30 -> Feasibility & Quality Analyzer | D30: =C_KPI_Benchmark!F30 -> D2 | E30: =C_KPI_Benchmark!J30 -> Uses Zion shared services instead of re-implementing them | F30: =C_KPI_Benchmark!K30 -> Yes/No | G30: =C_KPI_Benchmark!L30 -> Higher is better | H30: =C_KPI_Benchmark!N30 -> 1 | I30: =IF(C_KPI_Benchmark!O30<>"",C_KPI_Benchmark!O30,IF(G30="Higher is better",H30*(1-A_Scoring_Model!$C$16),H30*(1+A_Scoring_Model!$C$16))) -> 0.8 | N30: =IF(J30="","",IF($H30=$I30,IF(OR(AND($G30="Higher is better",J30>=$H30),AND($G30="Lower is better",J30<=$H30)),A_Scoring_Model!$C$14,0),IF($G30="Higher is better",IF(J30>=$H30,A_Scoring_Model!$C$14,IF(J30<$I30,0,A_Scoring_Model!$C$15+(A_Scoring_Model!$C$14-A_Scoring_Model!$C$15)*(J30-$I30)/($H30-$I30))),IF(J30<=$H30,A_Scoring_Model!$C$14,IF(J30>$I30,0,A_Scoring_Model!$C$15+(A_Scoring_Model!$C$14-A_Scoring_Model!$C$15)*($I30-J30)/($I30-$H30)))))) | O30: =IF(K30="","",IF($H30=$I30,IF(OR(AND($G30="Higher is better",K30>=$H30),AND($G30="Lower is better",K30<=$H30)),A_Scoring_Model!$C$14,0),IF($G30="Higher is better",IF(K30>=$H30,A_Scoring_Model!$C$14,IF(K30<$I30,0,A_Scoring_Model!$C$15+(A_Scoring_Model!$C$14-A_Scoring_Model!$C$15)*(K30-$I30)/($H30-$I30))),IF(K30<=$H30,A_Scoring_Model!$C$14,IF(K30>$I30,0,A_Scoring_Model!$C$15+(A_Scoring_Model!$C$14-A_Scoring_Model!$C$15)*($I30-K30)/($I30-$H30)))))) | P30: =IF(L30="","",IF($H30=$I30,IF(OR(AND($G30="Higher is better",L30>=$H30),AND($G30="Lower is better",L30<=$H30)),A_Scoring_Model!$C$14,0),IF($G30="Higher is better",IF(L30>=$H30,A_Scoring_Model!$C$14,IF(L30<$I30,0,A_Scoring_Model!$C$15+(A_Scoring_Model!$C$14-A_Scoring_Model!$C$15)*(L30-$I30)/($H30-$I30))),IF(L30<=$H30,A_Scoring_Model!$C$14,IF(L30>$I30,0,A_Scoring_Model!$C$15+(A_Scoring_Model!$C$14-A_Scoring_Model!$C$15)*($I30-L30)/($I30-$H30)))))) | Q30: =IF(M30="","",IF($H30=$I30,IF(OR(AND($G30="Higher is better",M30>=$H30),AND($G30="Lower is better",M30<=$H30)),A_Scoring_Model!$C$14,0),IF($G30="Higher is better",IF(M30>=$H30,A_Scoring_Model!$C$14,IF(M30<$I30,0,A_Scoring_Model!$C$15+(A_Scoring_Model!$C$14-A_Scoring_Model!$C$15)*(M30-$I30)/($H30-$I30))),IF(M30<=$H30,A_Scoring_Model!$C$14,IF(M30>$I30,0,A_Scoring_Model!$C$15+(A_Scoring_Model!$C$14-A_Scoring_Model!$C$15)*($I30-M30)/($I30-$H30))))))
A31: =C_KPI_Benchmark!A31 -> 1.b-D3-08 | B31: =C_KPI_Benchmark!D31 -> 1.b | C31: =C_KPI_Benchmark!E31 -> Feasibility & Quality Analyzer | D31: =C_KPI_Benchmark!F31 -> D3 | E31: =C_KPI_Benchmark!J31 -> Time to analyse 1,000 requirements | F31: =C_KPI_Benchmark!K31 -> min | G31: =C_KPI_Benchmark!L31 -> Lower is better | H31: =C_KPI_Benchmark!N31 -> 10 | I31: =IF(C_KPI_Benchmark!O31<>"",C_KPI_Benchmark!O31,IF(G31="Higher is better",H31*(1-A_Scoring_Model!$C$16),H31*(1+A_Scoring_Model!$C$16))) -> 12 | N31: =IF(J31="","",IF($H31=$I31,IF(OR(AND($G31="Higher is better",J31>=$H31),AND($G31="Lower is better",J31<=$H31)),A_Scoring_Model!$C$14,0),IF($G31="Higher is better",IF(J31>=$H31,A_Scoring_Model!$C$14,IF(J31<$I31,0,A_Scoring_Model!$C$15+(A_Scoring_Model!$C$14-A_Scoring_Model!$C$15)*(J31-$I31)/($H31-$I31))),IF(J31<=$H31,A_Scoring_Model!$C$14,IF(J31>$I31,0,A_Scoring_Model!$C$15+(A_Scoring_Model!$C$14-A_Scoring_Model!$C$15)*($I31-J31)/($I31-$H31)))))) | O31: =IF(K31="","",IF($H31=$I31,IF(OR(AND($G31="Higher is better",K31>=$H31),AND($G31="Lower is better",K31<=$H31)),A_Scoring_Model!$C$14,0),IF($G31="Higher is better",IF(K31>=$H31,A_Scoring_Model!$C$14,IF(K31<$I31,0,A_Scoring_Model!$C$15+(A_Scoring_Model!$C$14-A_Scoring_Model!$C$15)*(K31-$I31)/($H31-$I31))),IF(K31<=$H31,A_Scoring_Model!$C$14,IF(K31>$I31,0,A_Scoring_Model!$C$15+(A_Scoring_Model!$C$14-A_Scoring_Model!$C$15)*($I31-K31)/($I31-$H31)))))) | P31: =IF(L31="","",IF($H31=$I31,IF(OR(AND($G31="Higher is better",L31>=$H31),AND($G31="Lower is better",L31<=$H31)),A_Scoring_Model!$C$14,0),IF($G31="Higher is better",IF(L31>=$H31,A_Scoring_Model!$C$14,IF(L31<$I31,0,A_Scoring_Model!$C$15+(A_Scoring_Model!$C$14-A_Scoring_Model!$C$15)*(L31-$I31)/($H31-$I31))),IF(L31<=$H31,A_Scoring_Model!$C$14,IF(L31>$I31,0,A_Scoring_Model!$C$15+(A_Scoring_Model!$C$14-A_Scoring_Model!$C$15)*($I31-L31)/($I31-$H31)))))) | Q31: =IF(M31="","",IF($H31=$I31,IF(OR(AND($G31="Higher is better",M31>=$H31),AND($G31="Lower is better",M31<=$H31)),A_Scoring_Model!$C$14,0),IF($G31="Higher is better",IF(M31>=$H31,A_Scoring_Model!$C$14,IF(M31<$I31,0,A_Scoring_Model!$C$15+(A_Scoring_Model!$C$14-A_Scoring_Model!$C$15)*(M31-$I31)/($H31-$I31))),IF(M31<=$H31,A_Scoring_Model!$C$14,IF(M31>$I31,0,A_Scoring_Model!$C$15+(A_Scoring_Model!$C$14-A_Scoring_Model!$C$15)*($I31-M31)/($I31-$H31))))))
A32: =C_KPI_Benchmark!A32 -> 1.b-D3-09 | B32: =C_KPI_Benchmark!D32 -> 1.b | C32: =C_KPI_Benchmark!E32 -> Feasibility & Quality Analyzer | D32: =C_KPI_Benchmark!F32 -> D3 | E32: =C_KPI_Benchmark!J32 -> Latency degradation at 10× load | F32: =C_KPI_Benchmark!K32 -> % | G32: =C_KPI_Benchmark!L32 -> Lower is better | H32: =C_KPI_Benchmark!N32 -> 0.2 | I32: =IF(C_KPI_Benchmark!O32<>"",C_KPI_Benchmark!O32,IF(G32="Higher is better",H32*(1-A_Scoring_Model!$C$16),H32*(1+A_Scoring_Model!$C$16))) -> 0.4 | N32: =IF(J32="","",IF($H32=$I32,IF(OR(AND($G32="Higher is better",J32>=$H32),AND($G32="Lower is better",J32<=$H32)),A_Scoring_Model!$C$14,0),IF($G32="Higher is better",IF(J32>=$H32,A_Scoring_Model!$C$14,IF(J32<$I32,0,A_Scoring_Model!$C$15+(A_Scoring_Model!$C$14-A_Scoring_Model!$C$15)*(J32-$I32)/($H32-$I32))),IF(J32<=$H32,A_Scoring_Model!$C$14,IF(J32>$I32,0,A_Scoring_Model!$C$15+(A_Scoring_Model!$C$14-A_Scoring_Model!$C$15)*($I32-J32)/($I32-$H32)))))) | O32: =IF(K32="","",IF($H32=$I32,IF(OR(AND($G32="Higher is better",K32>=$H32),AND($G32="Lower is better",K32<=$H32)),A_Scoring_Model!$C$14,0),IF($G32="Higher is better",IF(K32>=$H32,A_Scoring_Model!$C$14,IF(K32<$I32,0,A_Scoring_Model!$C$15+(A_Scoring_Model!$C$14-A_Scoring_Model!$C$15)*(K32-$I32)/($H32-$I32))),IF(K32<=$H32,A_Scoring_Model!$C$14,IF(K32>$I32,0,A_Scoring_Model!$C$15+(A_Scoring_Model!$C$14-A_Scoring_Model!$C$15)*($I32-K32)/($I32-$H32)))))) | P32: =IF(L32="","",IF($H32=$I32,IF(OR(AND($G32="Higher is better",L32>=$H32),AND($G32="Lower is better",L32<=$H32)),A_Scoring_Model!$C$14,0),IF($G32="Higher is better",IF(L32>=$H32,A_Scoring_Model!$C$14,IF(L32<$I32,0,A_Scoring_Model!$C$15+(A_Scoring_Model!$C$14-A_Scoring_Model!$C$15)*(L32-$I32)/($H32-$I32))),IF(L32<=$H32,A_Scoring_Model!$C$14,IF(L32>$I32,0,A_Scoring_Model!$C$15+(A_Scoring_Model!$C$14-A_Scoring_Model!$C$15)*($I32-L32)/($I32-$H32)))))) | Q32: =IF(M32="","",IF($H32=$I32,IF(OR(AND($G32="Higher is better",M32>=$H32),AND($G32="Lower is better",M32<=$H32)),A_Scoring_Model!$C$14,0),IF($G32="Higher is better",IF(M32>=$H32,A_Scoring_Model!$C$14,IF(M32<$I32,0,A_Scoring_Model!$C$15+(A_Scoring_Model!$C$14-A_Scoring_Model!$C$15)*(M32-$I32)/($H32-$I32))),IF(M32<=$H32,A_Scoring_Model!$C$14,IF(M32>$I32,0,A_Scoring_Model!$C$15+(A_Scoring_Model!$C$14-A_Scoring_Model!$C$15)*($I32-M32)/($I32-$H32))))))
A33: =C_KPI_Benchmark!A33 -> 1.b-D4-10 | B33: =C_KPI_Benchmark!D33 -> 1.b | C33: =C_KPI_Benchmark!E33 -> Feasibility & Quality Analyzer | D33: =C_KPI_Benchmark!F33 -> D4 | E33: =C_KPI_Benchmark!J33 -> False alarm rate | F33: =C_KPI_Benchmark!K33 -> % | G33: =C_KPI_Benchmark!L33 -> Lower is better | H33: =C_KPI_Benchmark!N33 -> 0.15 | I33: =IF(C_KPI_Benchmark!O33<>"",C_KPI_Benchmark!O33,IF(G33="Higher is better",H33*(1-A_Scoring_Model!$C$16),H33*(1+A_Scoring_Model!$C$16))) -> 0.18 | N33: =IF(J33="","",IF($H33=$I33,IF(OR(AND($G33="Higher is better",J33>=$H33),AND($G33="Lower is better",J33<=$H33)),A_Scoring_Model!$C$14,0),IF($G33="Higher is better",IF(J33>=$H33,A_Scoring_Model!$C$14,IF(J33<$I33,0,A_Scoring_Model!$C$15+(A_Scoring_Model!$C$14-A_Scoring_Model!$C$15)*(J33-$I33)/($H33-$I33))),IF(J33<=$H33,A_Scoring_Model!$C$14,IF(J33>$I33,0,A_Scoring_Model!$C$15+(A_Scoring_Model!$C$14-A_Scoring_Model!$C$15)*($I33-J33)/($I33-$H33)))))) | O33: =IF(K33="","",IF($H33=$I33,IF(OR(AND($G33="Higher is better",K33>=$H33),AND($G33="Lower is better",K33<=$H33)),A_Scoring_Model!$C$14,0),IF($G33="Higher is better",IF(K33>=$H33,A_Scoring_Model!$C$14,IF(K33<$I33,0,A_Scoring_Model!$C$15+(A_Scoring_Model!$C$14-A_Scoring_Model!$C$15)*(K33-$I33)/($H33-$I33))),IF(K33<=$H33,A_Scoring_Model!$C$14,IF(K33>$I33,0,A_Scoring_Model!$C$15+(A_Scoring_Model!$C$14-A_Scoring_Model!$C$15)*($I33-K33)/($I33-$H33)))))) | P33: =IF(L33="","",IF($H33=$I33,IF(OR(AND($G33="Higher is better",L33>=$H33),AND($G33="Lower is better",L33<=$H33)),A_Scoring_Model!$C$14,0),IF($G33="Higher is better",IF(L33>=$H33,A_Scoring_Model!$C$14,IF(L33<$I33,0,A_Scoring_Model!$C$15+(A_Scoring_Model!$C$14-A_Scoring_Model!$C$15)*(L33-$I33)/($H33-$I33))),IF(L33<=$H33,A_Scoring_Model!$C$14,IF(L33>$I33,0,A_Scoring_Model!$C$15+(A_Scoring_Model!$C$14-A_Scoring_Model!$C$15)*($I33-L33)/($I33-$H33)))))) | Q33: =IF(M33="","",IF($H33=$I33,IF(OR(AND($G33="Higher is better",M33>=$H33),AND($G33="Lower is better",M33<=$H33)),A_Scoring_Model!$C$14,0),IF($G33="Higher is better",IF(M33>=$H33,A_Scoring_Model!$C$14,IF(M33<$I33,0,A_Scoring_Model!$C$15+(A_Scoring_Model!$C$14-A_Scoring_Model!$C$15)*(M33-$I33)/($H33-$I33))),IF(M33<=$H33,A_Scoring_Model!$C$14,IF(M33>$I33,0,A_Scoring_Model!$C$15+(A_Scoring_Model!$C$14-A_Scoring_Model!$C$15)*($I33-M33)/($I33-$H33))))))
A34: =C_KPI_Benchmark!A34 -> 1.b-D4-11 | B34: =C_KPI_Benchmark!D34 -> 1.b | C34: =C_KPI_Benchmark!E34 -> Feasibility & Quality Analyzer | D34: =C_KPI_Benchmark!F34 -> D4 | E34: =C_KPI_Benchmark!J34 -> Flags citing rule + text span | F34: =C_KPI_Benchmark!K34 -> % | G34: =C_KPI_Benchmark!L34 -> Higher is better | H34: =C_KPI_Benchmark!N34 -> 1 | I34: =IF(C_KPI_Benchmark!O34<>"",C_KPI_Benchmark!O34,IF(G34="Higher is better",H34*(1-A_Scoring_Model!$C$16),H34*(1+A_Scoring_Model!$C$16))) -> 0.8 | N34: =IF(J34="","",IF($H34=$I34,IF(OR(AND($G34="Higher is better",J34>=$H34),AND($G34="Lower is better",J34<=$H34)),A_Scoring_Model!$C$14,0),IF($G34="Higher is better",IF(J34>=$H34,A_Scoring_Model!$C$14,IF(J34<$I34,0,A_Scoring_Model!$C$15+(A_Scoring_Model!$C$14-A_Scoring_Model!$C$15)*(J34-$I34)/($H34-$I34))),IF(J34<=$H34,A_Scoring_Model!$C$14,IF(J34>$I34,0,A_Scoring_Model!$C$15+(A_Scoring_Model!$C$14-A_Scoring_Model!$C$15)*($I34-J34)/($I34-$H34)))))) | O34: =IF(K34="","",IF($H34=$I34,IF(OR(AND($G34="Higher is better",K34>=$H34),AND($G34="Lower is better",K34<=$H34)),A_Scoring_Model!$C$14,0),IF($G34="Higher is better",IF(K34>=$H34,A_Scoring_Model!$C$14,IF(K34<$I34,0,A_Scoring_Model!$C$15+(A_Scoring_Model!$C$14-A_Scoring_Model!$C$15)*(K34-$I34)/($H34-$I34))),IF(K34<=$H34,A_Scoring_Model!$C$14,IF(K34>$I34,0,A_Scoring_Model!$C$15+(A_Scoring_Model!$C$14-A_Scoring_Model!$C$15)*($I34-K34)/($I34-$H34)))))) | P34: =IF(L34="","",IF($H34=$I34,IF(OR(AND($G34="Higher is better",L34>=$H34),AND($G34="Lower is better",L34<=$H34)),A_Scoring_Model!$C$14,0),IF($G34="Higher is better",IF(L34>=$H34,A_Scoring_Model!$C$14,IF(L34<$I34,0,A_Scoring_Model!$C$15+(A_Scoring_Model!$C$14-A_Scoring_Model!$C$15)*(L34-$I34)/($H34-$I34))),IF(L34<=$H34,A_Scoring_Model!$C$14,IF(L34>$I34,0,A_Scoring_Model!$C$15+(A_Scoring_Model!$C$14-A_Scoring_Model!$C$15)*($I34-L34)/($I34-$H34)))))) | Q34: =IF(M34="","",IF($H34=$I34,IF(OR(AND($G34="Higher is better",M34>=$H34),AND($G34="Lower is better",M34<=$H34)),A_Scoring_Model!$C$14,0),IF($G34="Higher is better",IF(M34>=$H34,A_Scoring_Model!$C$14,IF(M34<$I34,0,A_Scoring_Model!$C$15+(A_Scoring_Model!$C$14-A_Scoring_Model!$C$15)*(M34-$I34)/($H34-$I34))),IF(M34<=$H34,A_Scoring_Model!$C$14,IF(M34>$I34,0,A_Scoring_Model!$C$15+(A_Scoring_Model!$C$14-A_Scoring_Model!$C$15)*($I34-M34)/($I34-$H34))))))
A35: =C_KPI_Benchmark!A35 -> 1.b-D4-12 | B35: =C_KPI_Benchmark!D35 -> 1.b | C35: =C_KPI_Benchmark!E35 -> Feasibility & Quality Analyzer | D35: =C_KPI_Benchmark!F35 -> D4 | E35: =C_KPI_Benchmark!J35 -> Service availability | F35: =C_KPI_Benchmark!K35 -> % | G35: =C_KPI_Benchmark!L35 -> Higher is better | H35: =C_KPI_Benchmark!N35 -> 0.995 | I35: =IF(C_KPI_Benchmark!O35<>"",C_KPI_Benchmark!O35,IF(G35="Higher is better",H35*(1-A_Scoring_Model!$C$16),H35*(1+A_Scoring_Model!$C$16))) -> 0.99 | N35: =IF(J35="","",IF($H35=$I35,IF(OR(AND($G35="Higher is better",J35>=$H35),AND($G35="Lower is better",J35<=$H35)),A_Scoring_Model!$C$14,0),IF($G35="Higher is better",IF(J35>=$H35,A_Scoring_Model!$C$14,IF(J35<$I35,0,A_Scoring_Model!$C$15+(A_Scoring_Model!$C$14-A_Scoring_Model!$C$15)*(J35-$I35)/($H35-$I35))),IF(J35<=$H35,A_Scoring_Model!$C$14,IF(J35>$I35,0,A_Scoring_Model!$C$15+(A_Scoring_Model!$C$14-A_Scoring_Model!$C$15)*($I35-J35)/($I35-$H35)))))) | O35: =IF(K35="","",IF($H35=$I35,IF(OR(AND($G35="Higher is better",K35>=$H35),AND($G35="Lower is better",K35<=$H35)),A_Scoring_Model!$C$14,0),IF($G35="Higher is better",IF(K35>=$H35,A_Scoring_Model!$C$14,IF(K35<$I35,0,A_Scoring_Model!$C$15+(A_Scoring_Model!$C$14-A_Scoring_Model!$C$15)*(K35-$I35)/($H35-$I35))),IF(K35<=$H35,A_Scoring_Model!$C$14,IF(K35>$I35,0,A_Scoring_Model!$C$15+(A_Scoring_Model!$C$14-A_Scoring_Model!$C$15)*($I35-K35)/($I35-$H35)))))) | P35: =IF(L35="","",IF($H35=$I35,IF(OR(AND($G35="Higher is better",L35>=$H35),AND($G35="Lower is better",L35<=$H35)),A_Scoring_Model!$C$14,0),IF($G35="Higher is better",IF(L35>=$H35,A_Scoring_Model!$C$14,IF(L35<$I35,0,A_Scoring_Model!$C$15+(A_Scoring_Model!$C$14-A_Scoring_Model!$C$15)*(L35-$I35)/($H35-$I35))),IF(L35<=$H35,A_Scoring_Model!$C$14,IF(L35>$I35,0,A_Scoring_Model!$C$15+(A_Scoring_Model!$C$14-A_Scoring_Model!$C$15)*($I35-L35)/($I35-$H35)))))) | Q35: =IF(M35="","",IF($H35=$I35,IF(OR(AND($G35="Higher is better",M35>=$H35),AND($G35="Lower is better",M35<=$H35)),A_Scoring_Model!$C$14,0),IF($G35="Higher is better",IF(M35>=$H35,A_Scoring_Model!$C$14,IF(M35<$I35,0,A_Scoring_Model!$C$15+(A_Scoring_Model!$C$14-A_Scoring_Model!$C$15)*(M35-$I35)/($H35-$I35))),IF(M35<=$H35,A_Scoring_Model!$C$14,IF(M35>$I35,0,A_Scoring_Model!$C$15+(A_Scoring_Model!$C$14-A_Scoring_Model!$C$15)*($I35-M35)/($I35-$H35))))))
... A166: =C_KPI_Benchmark!A166 -> 3.c-D6-18 | B166: =C_KPI_Benchmark!D166 -> 3.c | C166: =C_KPI_Benchmark!E166 -> Script Dev/Review & Coverage Agent | D166: =C_KPI_Benchmark!F166 -> D6 | E166: =C_KPI_Benchmark!J166 -> Named owner and support SLA | F166: =C_KPI_Benchmark!K166 -> Yes/No | G166: =C_KPI_Benchmark!L166 -> Higher is better | H166: =C_KPI_Benchmark!N166 -> 1 | I166: =IF(C_KPI_Benchmark!O166<>"",C_KPI_Benchmark!O166,IF(G166="Higher is better",H166*(1-A_Scoring_Model!$C$16),H166*(1+A_Scoring_Model!$C$16))) -> 0.8 | N166: =IF(J166="","",IF($H166=$I166,IF(OR(AND($G166="Higher is better",J166>=$H166),AND($G166="Lower is better",J166<=$H166)),A_Scoring_Model!$C$14,0),IF($G166="Higher is better",IF(J166>=$H166,A_Scoring_Model!$C$14,IF(J166<$I166,0,A_Scoring_Model!$C$15+(A_Scoring_Model!$C$14-A_Scoring_Model!$C$15)*(J166-$I166)/($H166-$I166))),IF(J166<=$H166,A_Scoring_Model!$C$14,IF(J166>$I166,0,A_Scoring_Model!$C$15+(A_Scoring_Model!$C$14-A_Scoring_Model!$C$15)*($I166-J166)/($I166-$H166)))))) | O166: =IF(K166="","",IF($H166=$I166,IF(OR(AND($G166="Higher is better",K166>=$H166),AND($G166="Lower is better",K166<=$H166)),A_Scoring_Model!$C$14,0),IF($G166="Higher is better",IF(K166>=$H166,A_Scoring_Model!$C$14,IF(K166<$I166,0,A_Scoring_Model!$C$15+(A_Scoring_Model!$C$14-A_Scoring_Model!$C$15)*(K166-$I166)/($H166-$I166))),IF(K166<=$H166,A_Scoring_Model!$C$14,IF(K166>$I166,0,A_Scoring_Model!$C$15+(A_Scoring_Model!$C$14-A_Scoring_Model!$C$15)*($I166-K166)/($I166-$H166)))))) | P166: =IF(L166="","",IF($H166=$I166,IF(OR(AND($G166="Higher is better",L166>=$H166),AND($G166="Lower is better",L166<=$H166)),A_Scoring_Model!$C$14,0),IF($G166="Higher is better",IF(L166>=$H166,A_Scoring_Model!$C$14,IF(L166<$I166,0,A_Scoring_Model!$C$15+(A_Scoring_Model!$C$14-A_Scoring_Model!$C$15)*(L166-$I166)/($H166-$I166))),IF(L166<=$H166,A_Scoring_Model!$C$14,IF(L166>$I166,0,A_Scoring_Model!$C$15+(A_Scoring_Model!$C$14-A_Scoring_Model!$C$15)*($I166-L166)/($I166-$H166)))))) | Q166: =IF(M166="","",IF($H166=$I166,IF(OR(AND($G166="Higher is better",M166>=$H166),AND($G166="Lower is better",M166<=$H166)),A_Scoring_Model!$C$14,0),IF($G166="Higher is better",IF(M166>=$H166,A_Scoring_Model!$C$14,IF(M166<$I166,0,A_Scoring_Model!$C$15+(A_Scoring_Model!$C$14-A_Scoring_Model!$C$15)*(M166-$I166)/($H166-$I166))),IF(M166<=$H166,A_Scoring_Model!$C$14,IF(M166>$I166,0,A_Scoring_Model!$C$15+(A_Scoring_Model!$C$14-A_Scoring_Model!$C$15)*($I166-M166)/($I166-$H166))))))
A167: =C_KPI_Benchmark!A167 -> 3.d-D1-01 | B167: =C_KPI_Benchmark!D167 -> 3.d | C167: =C_KPI_Benchmark!E167 -> AI Code Review Agent (Review Shield) | D167: =C_KPI_Benchmark!F167 -> D1 | E167: =C_KPI_Benchmark!J167 -> Critical/High defect detection recall on the seeded-defect golden set | F167: =C_KPI_Benchmark!K167 -> recall | G167: =C_KPI_Benchmark!L167 -> Higher is better | H167: =C_KPI_Benchmark!N167 -> 0.85 | I167: =IF(C_KPI_Benchmark!O167<>"",C_KPI_Benchmark!O167,IF(G167="Higher is better",H167*(1-A_Scoring_Model!$C$16),H167*(1+A_Scoring_Model!$C$16))) -> 0.7 | M167: 0.6 | N167: =IF(J167="","",IF($H167=$I167,IF(OR(AND($G167="Higher is better",J167>=$H167),AND($G167="Lower is better",J167<=$H167)),A_Scoring_Model!$C$14,0),IF($G167="Higher is better",IF(J167>=$H167,A_Scoring_Model!$C$14,IF(J167<$I167,0,A_Scoring_Model!$C$15+(A_Scoring_Model!$C$14-A_Scoring_Model!$C$15)*(J167-$I167)/($H167-$I167))),IF(J167<=$H167,A_Scoring_Model!$C$14,IF(J167>$I167,0,A_Scoring_Model!$C$15+(A_Scoring_Model!$C$14-A_Scoring_Model!$C$15)*($I167-J167)/($I167-$H167)))))) | O167: =IF(K167="","",IF($H167=$I167,IF(OR(AND($G167="Higher is better",K167>=$H167),AND($G167="Lower is better",K167<=$H167)),A_Scoring_Model!$C$14,0),IF($G167="Higher is better",IF(K167>=$H167,A_Scoring_Model!$C$14,IF(K167<$I167,0,A_Scoring_Model!$C$15+(A_Scoring_Model!$C$14-A_Scoring_Model!$C$15)*(K167-$I167)/($H167-$I167))),IF(K167<=$H167,A_Scoring_Model!$C$14,IF(K167>$I167,0,A_Scoring_Model!$C$15+(A_Scoring_Model!$C$14-A_Scoring_Model!$C$15)*($I167-K167)/($I167-$H167)))))) | P167: =IF(L167="","",IF($H167=$I167,IF(OR(AND($G167="Higher is better",L167>=$H167),AND($G167="Lower is better",L167<=$H167)),A_Scoring_Model!$C$14,0),IF($G167="Higher is better",IF(L167>=$H167,A_Scoring_Model!$C$14,IF(L167<$I167,0,A_Scoring_Model!$C$15+(A_Scoring_Model!$C$14-A_Scoring_Model!$C$15)*(L167-$I167)/($H167-$I167))),IF(L167<=$H167,A_Scoring_Model!$C$14,IF(L167>$I167,0,A_Scoring_Model!$C$15+(A_Scoring_Model!$C$14-A_Scoring_Model!$C$15)*($I167-L167)/($I167-$H167)))))) | Q167: =IF(M167="","",IF($H167=$I167,IF(OR(AND($G167="Higher is better",M167>=$H167),AND($G167="Lower is better",M167<=$H167)),A_Scoring_Model!$C$14,0),IF($G167="Higher is better",IF(M167>=$H167,A_Scoring_Model!$C$14,IF(M167<$I167,0,A_Scoring_Model!$C$15+(A_Scoring_Model!$C$14-A_Scoring_Model!$C$15)*(M167-$I167)/($H167-$I167))),IF(M167<=$H167,A_Scoring_Model!$C$14,IF(M167>$I167,0,A_Scoring_Model!$C$15+(A_Scoring_Model!$C$14-A_Scoring_Model!$C$15)*($I167-M167)/($I167-$H167)))))) -> 0
A168: =C_KPI_Benchmark!A168 -> 3.d-D1-02 | B168: =C_KPI_Benchmark!D168 -> 3.d | C168: =C_KPI_Benchmark!E168 -> AI Code Review Agent (Review Shield) | D168: =C_KPI_Benchmark!F168 -> D1 | E168: =C_KPI_Benchmark!J168 -> Comment precision (comments that are real, actionable defects) | F168: =C_KPI_Benchmark!K168 -> precision | G168: =C_KPI_Benchmark!L168 -> Higher is better | H168: =C_KPI_Benchmark!N168 -> 0.8 | I168: =IF(C_KPI_Benchmark!O168<>"",C_KPI_Benchmark!O168,IF(G168="Higher is better",H168*(1-A_Scoring_Model!$C$16),H168*(1+A_Scoring_Model!$C$16))) -> 0.65 | M168: 0.4 | N168: =IF(J168="","",IF($H168=$I168,IF(OR(AND($G168="Higher is better",J168>=$H168),AND($G168="Lower is better",J168<=$H168)),A_Scoring_Model!$C$14,0),IF($G168="Higher is better",IF(J168>=$H168,A_Scoring_Model!$C$14,IF(J168<$I168,0,A_Scoring_Model!$C$15+(A_Scoring_Model!$C$14-A_Scoring_Model!$C$15)*(J168-$I168)/($H168-$I168))),IF(J168<=$H168,A_Scoring_Model!$C$14,IF(J168>$I168,0,A_Scoring_Model!$C$15+(A_Scoring_Model!$C$14-A_Scoring_Model!$C$15)*($I168-J168)/($I168-$H168)))))) | O168: =IF(K168="","",IF($H168=$I168,IF(OR(AND($G168="Higher is better",K168>=$H168),AND($G168="Lower is better",K168<=$H168)),A_Scoring_Model!$C$14,0),IF($G168="Higher is better",IF(K168>=$H168,A_Scoring_Model!$C$14,IF(K168<$I168,0,A_Scoring_Model!$C$15+(A_Scoring_Model!$C$14-A_Scoring_Model!$C$15)*(K168-$I168)/($H168-$I168))),IF(K168<=$H168,A_Scoring_Model!$C$14,IF(K168>$I168,0,A_Scoring_Model!$C$15+(A_Scoring_Model!$C$14-A_Scoring_Model!$C$15)*($I168-K168)/($I168-$H168)))))) | P168: =IF(L168="","",IF($H168=$I168,IF(OR(AND($G168="Higher is better",L168>=$H168),AND($G168="Lower is better",L168<=$H168)),A_Scoring_Model!$C$14,0),IF($G168="Higher is better",IF(L168>=$H168,A_Scoring_Model!$C$14,IF(L168<$I168,0,A_Scoring_Model!$C$15+(A_Scoring_Model!$C$14-A_Scoring_Model!$C$15)*(L168-$I168)/($H168-$I168))),IF(L168<=$H168,A_Scoring_Model!$C$14,IF(L168>$I168,0,A_Scoring_Model!$C$15+(A_Scoring_Model!$C$14-A_Scoring_Model!$C$15)*($I168-L168)/($I168-$H168)))))) | Q168: =IF(M168="","",IF($H168=$I168,IF(OR(AND($G168="Higher is better",M168>=$H168),AND($G168="Lower is better",M168<=$H168)),A_Scoring_Model!$C$14,0),IF($G168="Higher is better",IF(M168>=$H168,A_Scoring_Model!$C$14,IF(M168<$I168,0,A_Scoring_Model!$C$15+(A_Scoring_Model!$C$14-A_Scoring_Model!$C$15)*(M168-$I168)/($H168-$I168))),IF(M168<=$H168,A_Scoring_Model!$C$14,IF(M168>$I168,0,A_Scoring_Model!$C$15+(A_Scoring_Model!$C$14-A_Scoring_Model!$C$15)*($I168-M168)/($I168-$H168)))))) -> 0
A169: =C_KPI_Benchmark!A169 -> 3.d-D1-03 | B169: =C_KPI_Benchmark!D169 -> 3.d | C169: =C_KPI_Benchmark!E169 -> AI Code Review Agent (Review Shield) | D169: =C_KPI_Benchmark!F169 -> D1 | E169: =C_KPI_Benchmark!J169 -> Severity classification agreement with the SME rubric | F169: =C_KPI_Benchmark!K169 -> agreement | G169: =C_KPI_Benchmark!L169 -> Higher is better | H169: =C_KPI_Benchmark!N169 -> 0.85 | I169: =IF(C_KPI_Benchmark!O169<>"",C_KPI_Benchmark!O169,IF(G169="Higher is better",H169*(1-A_Scoring_Model!$C$16),H169*(1+A_Scoring_Model!$C$16))) -> 0.7 | M169: 0.45 | N169: =IF(J169="","",IF($H169=$I169,IF(OR(AND($G169="Higher is better",J169>=$H169),AND($G169="Lower is better",J169<=$H169)),A_Scoring_Model!$C$14,0),IF($G169="Higher is better",IF(J169>=$H169,A_Scoring_Model!$C$14,IF(J169<$I169,0,A_Scoring_Model!$C$15+(A_Scoring_Model!$C$14-A_Scoring_Model!$C$15)*(J169-$I169)/($H169-$I169))),IF(J169<=$H169,A_Scoring_Model!$C$14,IF(J169>$I169,0,A_Scoring_Model!$C$15+(A_Scoring_Model!$C$14-A_Scoring_Model!$C$15)*($I169-J169)/($I169-$H169)))))) | O169: =IF(K169="","",IF($H169=$I169,IF(OR(AND($G169="Higher is better",K169>=$H169),AND($G169="Lower is better",K169<=$H169)),A_Scoring_Model!$C$14,0),IF($G169="Higher is better",IF(K169>=$H169,A_Scoring_Model!$C$14,IF(K169<$I169,0,A_Scoring_Model!$C$15+(A_Scoring_Model!$C$14-A_Scoring_Model!$C$15)*(K169-$I169)/($H169-$I169))),IF(K169<=$H169,A_Scoring_Model!$C$14,IF(K169>$I169,0,A_Scoring_Model!$C$15+(A_Scoring_Model!$C$14-A_Scoring_Model!$C$15)*($I169-K169)/($I169-$H169)))))) | P169: =IF(L169="","",IF($H169=$I169,IF(OR(AND($G169="Higher is better",L169>=$H169),AND($G169="Lower is better",L169<=$H169)),A_Scoring_Model!$C$14,0),IF($G169="Higher is better",IF(L169>=$H169,A_Scoring_Model!$C$14,IF(L169<$I169,0,A_Scoring_Model!$C$15+(A_Scoring_Model!$C$14-A_Scoring_Model!$C$15)*(L169-$I169)/($H169-$I169))),IF(L169<=$H169,A_Scoring_Model!$C$14,IF(L169>$I169,0,A_Scoring_Model!$C$15+(A_Scoring_Model!$C$14-A_Scoring_Model!$C$15)*($I169-L169)/($I169-$H169)))))) | Q169: =IF(M169="","",IF($H169=$I169,IF(OR(AND($G169="Higher is better",M169>=$H169),AND($G169="Lower is better",M169<=$H169)),A_Scoring_Model!$C$14,0),IF($G169="Higher is better",IF(M169>=$H169,A_Scoring_Model!$C$14,IF(M169<$I169,0,A_Scoring_Model!$C$15+(A_Scoring_Model!$C$14-A_Scoring_Model!$C$15)*(M169-$I169)/($H169-$I169))),IF(M169<=$H169,A_Scoring_Model!$C$14,IF(M169>$I169,0,A_Scoring_Model!$C$15+(A_Scoring_Model!$C$14-A_Scoring_Model!$C$15)*($I169-M169)/($I169-$H169)))))) -> 0
A170: =C_KPI_Benchmark!A170 -> 3.d-D1-04 | B170: =C_KPI_Benchmark!D170 -> 3.d | C170: =C_KPI_Benchmark!E170 -> AI Code Review Agent (Review Shield) | D170: =C_KPI_Benchmark!F170 -> D1 | E170: =C_KPI_Benchmark!J170 -> Scope compliance: comments inside the allowed defect categories | F170: =C_KPI_Benchmark!K170 -> % | G170: =C_KPI_Benchmark!L170 -> Higher is better | H170: =C_KPI_Benchmark!N170 -> 0.95 | I170: =IF(C_KPI_Benchmark!O170<>"",C_KPI_Benchmark!O170,IF(G170="Higher is better",H170*(1-A_Scoring_Model!$C$16),H170*(1+A_Scoring_Model!$C$16))) -> 0.85 | M170: 0.36 | N170: =IF(J170="","",IF($H170=$I170,IF(OR(AND($G170="Higher is better",J170>=$H170),AND($G170="Lower is better",J170<=$H170)),A_Scoring_Model!$C$14,0),IF($G170="Higher is better",IF(J170>=$H170,A_Scoring_Model!$C$14,IF(J170<$I170,0,A_Scoring_Model!$C$15+(A_Scoring_Model!$C$14-A_Scoring_Model!$C$15)*(J170-$I170)/($H170-$I170))),IF(J170<=$H170,A_Scoring_Model!$C$14,IF(J170>$I170,0,A_Scoring_Model!$C$15+(A_Scoring_Model!$C$14-A_Scoring_Model!$C$15)*($I170-J170)/($I170-$H170)))))) | O170: =IF(K170="","",IF($H170=$I170,IF(OR(AND($G170="Higher is better",K170>=$H170),AND($G170="Lower is better",K170<=$H170)),A_Scoring_Model!$C$14,0),IF($G170="Higher is better",IF(K170>=$H170,A_Scoring_Model!$C$14,IF(K170<$I170,0,A_Scoring_Model!$C$15+(A_Scoring_Model!$C$14-A_Scoring_Model!$C$15)*(K170-$I170)/($H170-$I170))),IF(K170<=$H170,A_Scoring_Model!$C$14,IF(K170>$I170,0,A_Scoring_Model!$C$15+(A_Scoring_Model!$C$14-A_Scoring_Model!$C$15)*($I170-K170)/($I170-$H170)))))) | P170: =IF(L170="","",IF($H170=$I170,IF(OR(AND($G170="Higher is better",L170>=$H170),AND($G170="Lower is better",L170<=$H170)),A_Scoring_Model!$C$14,0),IF($G170="Higher is better",IF(L170>=$H170,A_Scoring_Model!$C$14,IF(L170<$I170,0,A_Scoring_Model!$C$15+(A_Scoring_Model!$C$14-A_Scoring_Model!$C$15)*(L170-$I170)/($H170-$I170))),IF(L170<=$H170,A_Scoring_Model!$C$14,IF(L170>$I170,0,A_Scoring_Model!$C$15+(A_Scoring_Model!$C$14-A_Scoring_Model!$C$15)*($I170-L170)/($I170-$H170)))))) | Q170: =IF(M170="","",IF($H170=$I170,IF(OR(AND($G170="Higher is better",M170>=$H170),AND($G170="Lower is better",M170<=$H170)),A_Scoring_Model!$C$14,0),IF($G170="Higher is better",IF(M170>=$H170,A_Scoring_Model!$C$14,IF(M170<$I170,0,A_Scoring_Model!$C$15+(A_Scoring_Model!$C$14-A_Scoring_Model!$C$15)*(M170-$I170)/($H170-$I170))),IF(M170<=$H170,A_Scoring_Model!$C$14,IF(M170>$I170,0,A_Scoring_Model!$C$15+(A_Scoring_Model!$C$14-A_Scoring_Model!$C$15)*($I170-M170)/($I170-$H170)))))) -> 0
A171: =C_KPI_Benchmark!A171 -> 3.d-D1-05 | B171: =C_KPI_Benchmark!D171 -> 3.d | C171: =C_KPI_Benchmark!E171 -> AI Code Review Agent (Review Shield) | D171: =C_KPI_Benchmark!F171 -> D1 | E171: =C_KPI_Benchmark!J171 -> Changed-line coverage (all changed files and lines analysed) | F171: =C_KPI_Benchmark!K171 -> % | G171: =C_KPI_Benchmark!L171 -> Higher is better | H171: =C_KPI_Benchmark!N171 -> 1 | I171: =IF(C_KPI_Benchmark!O171<>"",C_KPI_Benchmark!O171,IF(G171="Higher is better",H171*(1-A_Scoring_Model!$C$16),H171*(1+A_Scoring_Model!$C$16))) -> 0.98 | M171: 0.98 | N171: =IF(J171="","",IF($H171=$I171,IF(OR(AND($G171="Higher is better",J171>=$H171),AND($G171="Lower is better",J171<=$H171)),A_Scoring_Model!$C$14,0),IF($G171="Higher is better",IF(J171>=$H171,A_Scoring_Model!$C$14,IF(J171<$I171,0,A_Scoring_Model!$C$15+(A_Scoring_Model!$C$14-A_Scoring_Model!$C$15)*(J171-$I171)/($H171-$I171))),IF(J171<=$H171,A_Scoring_Model!$C$14,IF(J171>$I171,0,A_Scoring_Model!$C$15+(A_Scoring_Model!$C$14-A_Scoring_Model!$C$15)*($I171-J171)/($I171-$H171)))))) | O171: =IF(K171="","",IF($H171=$I171,IF(OR(AND($G171="Higher is better",K171>=$H171),AND($G171="Lower is better",K171<=$H171)),A_Scoring_Model!$C$14,0),IF($G171="Higher is better",IF(K171>=$H171,A_Scoring_Model!$C$14,IF(K171<$I171,0,A_Scoring_Model!$C$15+(A_Scoring_Model!$C$14-A_Scoring_Model!$C$15)*(K171-$I171)/($H171-$I171))),IF(K171<=$H171,A_Scoring_Model!$C$14,IF(K171>$I171,0,A_Scoring_Model!$C$15+(A_Scoring_Model!$C$14-A_Scoring_Model!$C$15)*($I171-K171)/($I171-$H171)))))) | P171: =IF(L171="","",IF($H171=$I171,IF(OR(AND($G171="Higher is better",L171>=$H171),AND($G171="Lower is better",L171<=$H171)),A_Scoring_Model!$C$14,0),IF($G171="Higher is better",IF(L171>=$H171,A_Scoring_Model!$C$14,IF(L171<$I171,0,A_Scoring_Model!$C$15+(A_Scoring_Model!$C$14-A_Scoring_Model!$C$15)*(L171-$I171)/($H171-$I171))),IF(L171<=$H171,A_Scoring_Model!$C$14,IF(L171>$I171,0,A_Scoring_Model!$C$15+(A_Scoring_Model!$C$14-A_Scoring_Model!$C$15)*($I171-L171)/($I171-$H171)))))) | Q171: =IF(M171="","",IF($H171=$I171,IF(OR(AND($G171="Higher is better",M171>=$H171),AND($G171="Lower is better",M171<=$H171)),A_Scoring_Model!$C$14,0),IF($G171="Higher is better",IF(M171>=$H171,A_Scoring_Model!$C$14,IF(M171<$I171,0,A_Scoring_Model!$C$15+(A_Scoring_Model!$C$14-A_Scoring_Model!$C$15)*(M171-$I171)/($H171-$I171))),IF(M171<=$H171,A_Scoring_Model!$C$14,IF(M171>$I171,0,A_Scoring_Model!$C$15+(A_Scoring_Model!$C$14-A_Scoring_Model!$C$15)*($I171-M171)/($I171-$H171)))))) -> 60
A172: =C_KPI_Benchmark!A172 -> 3.d-D1-06 | B172: =C_KPI_Benchmark!D172 -> 3.d | C172: =C_KPI_Benchmark!E172 -> AI Code Review Agent (Review Shield) | D172: =C_KPI_Benchmark!F172 -> D1 | E172: =C_KPI_Benchmark!J172 -> Duplicate or repeated comments within one review | F172: =C_KPI_Benchmark!K172 -> % | G172: =C_KPI_Benchmark!L172 -> Lower is better | H172: =C_KPI_Benchmark!N172 -> 0.05 | I172: =IF(C_KPI_Benchmark!O172<>"",C_KPI_Benchmark!O172,IF(G172="Higher is better",H172*(1-A_Scoring_Model!$C$16),H172*(1+A_Scoring_Model!$C$16))) -> 0.1 | M172: 0.08 | N172: =IF(J172="","",IF($H172=$I172,IF(OR(AND($G172="Higher is better",J172>=$H172),AND($G172="Lower is better",J172<=$H172)),A_Scoring_Model!$C$14,0),IF($G172="Higher is better",IF(J172>=$H172,A_Scoring_Model!$C$14,IF(J172<$I172,0,A_Scoring_Model!$C$15+(A_Scoring_Model!$C$14-A_Scoring_Model!$C$15)*(J172-$I172)/($H172-$I172))),IF(J172<=$H172,A_Scoring_Model!$C$14,IF(J172>$I172,0,A_Scoring_Model!$C$15+(A_Scoring_Model!$C$14-A_Scoring_Model!$C$15)*($I172-J172)/($I172-$H172)))))) | O172: =IF(K172="","",IF($H172=$I172,IF(OR(AND($G172="Higher is better",K172>=$H172),AND($G172="Lower is better",K172<=$H172)),A_Scoring_Model!$C$14,0),IF($G172="Higher is better",IF(K172>=$H172,A_Scoring_Model!$C$14,IF(K172<$I172,0,A_Scoring_Model!$C$15+(A_Scoring_Model!$C$14-A_Scoring_Model!$C$15)*(K172-$I172)/($H172-$I172))),IF(K172<=$H172,A_Scoring_Model!$C$14,IF(K172>$I172,0,A_Scoring_Model!$C$15+(A_Scoring_Model!$C$14-A_Scoring_Model!$C$15)*($I172-K172)/($I172-$H172)))))) | P172: =IF(L172="","",IF($H172=$I172,IF(OR(AND($G172="Higher is better",L172>=$H172),AND($G172="Lower is better",L172<=$H172)),A_Scoring_Model!$C$14,0),IF($G172="Higher is better",IF(L172>=$H172,A_Scoring_Model!$C$14,IF(L172<$I172,0,A_Scoring_Model!$C$15+(A_Scoring_Model!$C$14-A_Scoring_Model!$C$15)*(L172-$I172)/($H172-$I172))),IF(L172<=$H172,A_Scoring_Model!$C$14,IF(L172>$I172,0,A_Scoring_Model!$C$15+(A_Scoring_Model!$C$14-A_Scoring_Model!$C$15)*($I172-L172)/($I172-$H172)))))) | Q172: =IF(M172="","",IF($H172=$I172,IF(OR(AND($G172="Higher is better",M172>=$H172),AND($G172="Lower is better",M172<=$H172)),A_Scoring_Model!$C$14,0),IF($G172="Higher is better",IF(M172>=$H172,A_Scoring_Model!$C$14,IF(M172<$I172,0,A_Scoring_Model!$C$15+(A_Scoring_Model!$C$14-A_Scoring_Model!$C$15)*(M172-$I172)/($H172-$I172))),IF(M172<=$H172,A_Scoring_Model!$C$14,IF(M172>$I172,0,A_Scoring_Model!$C$15+(A_Scoring_Model!$C$14-A_Scoring_Model!$C$15)*($I172-M172)/($I172-$H172)))))) -> 76
A173: =C_KPI_Benchmark!A173 -> 3.d-D1-07 | B173: =C_KPI_Benchmark!D173 -> 3.d | C173: =C_KPI_Benchmark!E173 -> AI Code Review Agent (Review Shield) | D173: =C_KPI_Benchmark!F173 -> D1 | E173: =C_KPI_Benchmark!J173 -> Findings carrying a concrete fix (code or explicit instruction) | F173: =C_KPI_Benchmark!K173 -> % | G173: =C_KPI_Benchmark!L173 -> Higher is better | H173: =C_KPI_Benchmark!N173 -> 0.9 | I173: =IF(C_KPI_Benchmark!O173<>"",C_KPI_Benchmark!O173,IF(G173="Higher is better",H173*(1-A_Scoring_Model!$C$16),H173*(1+A_Scoring_Model!$C$16))) -> 0.75 | M173: 0.85 | N173: =IF(J173="","",IF($H173=$I173,IF(OR(AND($G173="Higher is better",J173>=$H173),AND($G173="Lower is better",J173<=$H173)),A_Scoring_Model!$C$14,0),IF($G173="Higher is better",IF(J173>=$H173,A_Scoring_Model!$C$14,IF(J173<$I173,0,A_Scoring_Model!$C$15+(A_Scoring_Model!$C$14-A_Scoring_Model!$C$15)*(J173-$I173)/($H173-$I173))),IF(J173<=$H173,A_Scoring_Model!$C$14,IF(J173>$I173,0,A_Scoring_Model!$C$15+(A_Scoring_Model!$C$14-A_Scoring_Model!$C$15)*($I173-J173)/($I173-$H173)))))) | O173: =IF(K173="","",IF($H173=$I173,IF(OR(AND($G173="Higher is better",K173>=$H173),AND($G173="Lower is better",K173<=$H173)),A_Scoring_Model!$C$14,0),IF($G173="Higher is better",IF(K173>=$H173,A_Scoring_Model!$C$14,IF(K173<$I173,0,A_Scoring_Model!$C$15+(A_Scoring_Model!$C$14-A_Scoring_Model!$C$15)*(K173-$I173)/($H173-$I173))),IF(K173<=$H173,A_Scoring_Model!$C$14,IF(K173>$I173,0,A_Scoring_Model!$C$15+(A_Scoring_Model!$C$14-A_Scoring_Model!$C$15)*($I173-K173)/($I173-$H173)))))) | P173: =IF(L173="","",IF($H173=$I173,IF(OR(AND($G173="Higher is better",L173>=$H173),AND($G173="Lower is better",L173<=$H173)),A_Scoring_Model!$C$14,0),IF($G173="Higher is better",IF(L173>=$H173,A_Scoring_Model!$C$14,IF(L173<$I173,0,A_Scoring_Model!$C$15+(A_Scoring_Model!$C$14-A_Scoring_Model!$C$15)*(L173-$I173)/($H173-$I173))),IF(L173<=$H173,A_Scoring_Model!$C$14,IF(L173>$I173,0,A_Scoring_Model!$C$15+(A_Scoring_Model!$C$14-A_Scoring_Model!$C$15)*($I173-L173)/($I173-$H173)))))) | Q173: =IF(M173="","",IF($H173=$I173,IF(OR(AND($G173="Higher is better",M173>=$H173),AND($G173="Lower is better",M173<=$H173)),A_Scoring_Model!$C$14,0),IF($G173="Higher is better",IF(M173>=$H173,A_Scoring_Model!$C$14,IF(M173<$I173,0,A_Scoring_Model!$C$15+(A_Scoring_Model!$C$14-A_Scoring_Model!$C$15)*(M173-$I173)/($H173-$I173))),IF(M173<=$H173,A_Scoring_Model!$C$14,IF(M173>$I173,0,A_Scoring_Model!$C$15+(A_Scoring_Model!$C$14-A_Scoring_Model!$C$15)*($I173-M173)/($I173-$H173)))))) -> 86.666667
A174: =C_KPI_Benchmark!A174 -> 3.d-D2-08 | B174: =C_KPI_Benchmark!D174 -> 3.d | C174: =C_KPI_Benchmark!E174 -> AI Code Review Agent (Review Shield) | D174: =C_KPI_Benchmark!F174 -> D2 | E174: =C_KPI_Benchmark!J174 -> SCM platforms supported (Bitbucket, GitHub, GitLab) | F174: =C_KPI_Benchmark!K174 -> count | G174: =C_KPI_Benchmark!L174 -> Higher is better | H174: =C_KPI_Benchmark!N174 -> 3 | I174: =IF(C_KPI_Benchmark!O174<>"",C_KPI_Benchmark!O174,IF(G174="Higher is better",H174*(1-A_Scoring_Model!$C$16),H174*(1+A_Scoring_Model!$C$16))) -> 2 | M174: 1 | N174: =IF(J174="","",IF($H174=$I174,IF(OR(AND($G174="Higher is better",J174>=$H174),AND($G174="Lower is better",J174<=$H174)),A_Scoring_Model!$C$14,0),IF($G174="Higher is better",IF(J174>=$H174,A_Scoring_Model!$C$14,IF(J174<$I174,0,A_Scoring_Model!$C$15+(A_Scoring_Model!$C$14-A_Scoring_Model!$C$15)*(J174-$I174)/($H174-$I174))),IF(J174<=$H174,A_Scoring_Model!$C$14,IF(J174>$I174,0,A_Scoring_Model!$C$15+(A_Scoring_Model!$C$14-A_Scoring_Model!$C$15)*($I174-J174)/($I174-$H174)))))) | O174: =IF(K174="","",IF($H174=$I174,IF(OR(AND($G174="Higher is better",K174>=$H174),AND($G174="Lower is better",K174<=$H174)),A_Scoring_Model!$C$14,0),IF($G174="Higher is better",IF(K174>=$H174,A_Scoring_Model!$C$14,IF(K174<$I174,0,A_Scoring_Model!$C$15+(A_Scoring_Model!$C$14-A_Scoring_Model!$C$15)*(K174-$I174)/($H174-$I174))),IF(K174<=$H174,A_Scoring_Model!$C$14,IF(K174>$I174,0,A_Scoring_Model!$C$15+(A_Scoring_Model!$C$14-A_Scoring_Model!$C$15)*($I174-K174)/($I174-$H174)))))) | P174: =IF(L174="","",IF($H174=$I174,IF(OR(AND($G174="Higher is better",L174>=$H174),AND($G174="Lower is better",L174<=$H174)),A_Scoring_Model!$C$14,0),IF($G174="Higher is better",IF(L174>=$H174,A_Scoring_Model!$C$14,IF(L174<$I174,0,A_Scoring_Model!$C$15+(A_Scoring_Model!$C$14-A_Scoring_Model!$C$15)*(L174-$I174)/($H174-$I174))),IF(L174<=$H174,A_Scoring_Model!$C$14,IF(L174>$I174,0,A_Scoring_Model!$C$15+(A_Scoring_Model!$C$14-A_Scoring_Model!$C$15)*($I174-L174)/($I174-$H174)))))) | Q174: =IF(M174="","",IF($H174=$I174,IF(OR(AND($G174="Higher is better",M174>=$H174),AND($G174="Lower is better",M174<=$H174)),A_Scoring_Model!$C$14,0),IF($G174="Higher is better",IF(M174>=$H174,A_Scoring_Model!$C$14,IF(M174<$I174,0,A_Scoring_Model!$C$15+(A_Scoring_Model!$C$14-A_Scoring_Model!$C$15)*(M174-$I174)/($H174-$I174))),IF(M174<=$H174,A_Scoring_Model!$C$14,IF(M174>$I174,0,A_Scoring_Model!$C$15+(A_Scoring_Model!$C$14-A_Scoring_Model!$C$15)*($I174-M174)/($I174-$H174)))))) -> 0
A175: =C_KPI_Benchmark!A175 -> 3.d-D2-09 | B175: =C_KPI_Benchmark!D175 -> 3.d | C175: =C_KPI_Benchmark!E175 -> AI Code Review Agent (Review Shield) | D175: =C_KPI_Benchmark!F175 -> D2 | E175: =C_KPI_Benchmark!J175 -> Languages covered with domain-aware rules | F175: =C_KPI_Benchmark!K175 -> count | G175: =C_KPI_Benchmark!L175 -> Higher is better | H175: =C_KPI_Benchmark!N175 -> 4 | I175: =IF(C_KPI_Benchmark!O175<>"",C_KPI_Benchmark!O175,IF(G175="Higher is better",H175*(1-A_Scoring_Model!$C$16),H175*(1+A_Scoring_Model!$C$16))) -> 3 | M175: 4 | N175: =IF(J175="","",IF($H175=$I175,IF(OR(AND($G175="Higher is better",J175>=$H175),AND($G175="Lower is better",J175<=$H175)),A_Scoring_Model!$C$14,0),IF($G175="Higher is better",IF(J175>=$H175,A_Scoring_Model!$C$14,IF(J175<$I175,0,A_Scoring_Model!$C$15+(A_Scoring_Model!$C$14-A_Scoring_Model!$C$15)*(J175-$I175)/($H175-$I175))),IF(J175<=$H175,A_Scoring_Model!$C$14,IF(J175>$I175,0,A_Scoring_Model!$C$15+(A_Scoring_Model!$C$14-A_Scoring_Model!$C$15)*($I175-J175)/($I175-$H175)))))) | O175: =IF(K175="","",IF($H175=$I175,IF(OR(AND($G175="Higher is better",K175>=$H175),AND($G175="Lower is better",K175<=$H175)),A_Scoring_Model!$C$14,0),IF($G175="Higher is better",IF(K175>=$H175,A_Scoring_Model!$C$14,IF(K175<$I175,0,A_Scoring_Model!$C$15+(A_Scoring_Model!$C$14-A_Scoring_Model!$C$15)*(K175-$I175)/($H175-$I175))),IF(K175<=$H175,A_Scoring_Model!$C$14,IF(K175>$I175,0,A_Scoring_Model!$C$15+(A_Scoring_Model!$C$14-A_Scoring_Model!$C$15)*($I175-K175)/($I175-$H175)))))) | P175: =IF(L175="","",IF($H175=$I175,IF(OR(AND($G175="Higher is better",L175>=$H175),AND($G175="Lower is better",L175<=$H175)),A_Scoring_Model!$C$14,0),IF($G175="Higher is better",IF(L175>=$H175,A_Scoring_Model!$C$14,IF(L175<$I175,0,A_Scoring_Model!$C$15+(A_Scoring_Model!$C$14-A_Scoring_Model!$C$15)*(L175-$I175)/($H175-$I175))),IF(L175<=$H175,A_Scoring_Model!$C$14,IF(L175>$I175,0,A_Scoring_Model!$C$15+(A_Scoring_Model!$C$14-A_Scoring_Model!$C$15)*($I175-L175)/($I175-$H175)))))) | Q175: =IF(M175="","",IF($H175=$I175,IF(OR(AND($G175="Higher is better",M175>=$H175),AND($G175="Lower is better",M175<=$H175)),A_Scoring_Model!$C$14,0),IF($G175="Higher is better",IF(M175>=$H175,A_Scoring_Model!$C$14,IF(M175<$I175,0,A_Scoring_Model!$C$15+(A_Scoring_Model!$C$14-A_Scoring_Model!$C$15)*(M175-$I175)/($H175-$I175))),IF(M175<=$H175,A_Scoring_Model!$C$14,IF(M175>$I175,0,A_Scoring_Model!$C$15+(A_Scoring_Model!$C$14-A_Scoring_Model!$C$15)*($I175-M175)/($I175-$H175)))))) -> 100
A176: =C_KPI_Benchmark!A176 -> 3.d-D2-10 | B176: =C_KPI_Benchmark!D176 -> 3.d | C176: =C_KPI_Benchmark!E176 -> AI Code Review Agent (Review Shield) | D176: =C_KPI_Benchmark!F176 -> D2 | E176: =C_KPI_Benchmark!J176 -> Per-repository feature configuration without code change | F176: =C_KPI_Benchmark!K176 -> Yes/No | G176: =C_KPI_Benchmark!L176 -> Higher is better | H176: =C_KPI_Benchmark!N176 -> 1 | I176: =IF(C_KPI_Benchmark!O176<>"",C_KPI_Benchmark!O176,IF(G176="Higher is better",H176*(1-A_Scoring_Model!$C$16),H176*(1+A_Scoring_Model!$C$16))) -> 0.8 | M176: 1 | N176: =IF(J176="","",IF($H176=$I176,IF(OR(AND($G176="Higher is better",J176>=$H176),AND($G176="Lower is better",J176<=$H176)),A_Scoring_Model!$C$14,0),IF($G176="Higher is better",IF(J176>=$H176,A_Scoring_Model!$C$14,IF(J176<$I176,0,A_Scoring_Model!$C$15+(A_Scoring_Model!$C$14-A_Scoring_Model!$C$15)*(J176-$I176)/($H176-$I176))),IF(J176<=$H176,A_Scoring_Model!$C$14,IF(J176>$I176,0,A_Scoring_Model!$C$15+(A_Scoring_Model!$C$14-A_Scoring_Model!$C$15)*($I176-J176)/($I176-$H176)))))) | O176: =IF(K176="","",IF($H176=$I176,IF(OR(AND($G176="Higher is better",K176>=$H176),AND($G176="Lower is better",K176<=$H176)),A_Scoring_Model!$C$14,0),IF($G176="Higher is better",IF(K176>=$H176,A_Scoring_Model!$C$14,IF(K176<$I176,0,A_Scoring_Model!$C$15+(A_Scoring_Model!$C$14-A_Scoring_Model!$C$15)*(K176-$I176)/($H176-$I176))),IF(K176<=$H176,A_Scoring_Model!$C$14,IF(K176>$I176,0,A_Scoring_Model!$C$15+(A_Scoring_Model!$C$14-A_Scoring_Model!$C$15)*($I176-K176)/($I176-$H176)))))) | P176: =IF(L176="","",IF($H176=$I176,IF(OR(AND($G176="Higher is better",L176>=$H176),AND($G176="Lower is better",L176<=$H176)),A_Scoring_Model!$C$14,0),IF($G176="Higher is better",IF(L176>=$H176,A_Scoring_Model!$C$14,IF(L176<$I176,0,A_Scoring_Model!$C$15+(A_Scoring_Model!$C$14-A_Scoring_Model!$C$15)*(L176-$I176)/($H176-$I176))),IF(L176<=$H176,A_Scoring_Model!$C$14,IF(L176>$I176,0,A_Scoring_Model!$C$15+(A_Scoring_Model!$C$14-A_Scoring_Model!$C$15)*($I176-L176)/($I176-$H176)))))) | Q176: =IF(M176="","",IF($H176=$I176,IF(OR(AND($G176="Higher is better",M176>=$H176),AND($G176="Lower is better",M176<=$H176)),A_Scoring_Model!$C$14,0),IF($G176="Higher is better",IF(M176>=$H176,A_Scoring_Model!$C$14,IF(M176<$I176,0,A_Scoring_Model!$C$15+(A_Scoring_Model!$C$14-A_Scoring_Model!$C$15)*(M176-$I176)/($H176-$I176))),IF(M176<=$H176,A_Scoring_Model!$C$14,IF(M176>$I176,0,A_Scoring_Model!$C$15+(A_Scoring_Model!$C$14-A_Scoring_Model!$C$15)*($I176-M176)/($I176-$H176)))))) -> 100
A177: =C_KPI_Benchmark!A177 -> 3.d-D2-11 | B177: =C_KPI_Benchmark!D177 -> 3.d | C177: =C_KPI_Benchmark!E177 -> AI Code Review Agent (Review Shield) | D177: =C_KPI_Benchmark!F177 -> D2 | E177: =C_KPI_Benchmark!J177 -> Sol PE groups with active usage | F177: =C_KPI_Benchmark!K177 -> groups | G177: =C_KPI_Benchmark!L177 -> Higher is better | H177: =C_KPI_Benchmark!N177 -> 2 | I177: =IF(C_KPI_Benchmark!O177<>"",C_KPI_Benchmark!O177,IF(G177="Higher is better",H177*(1-A_Scoring_Model!$C$16),H177*(1+A_Scoring_Model!$C$16))) -> 1 | M177: 2 | N177: =IF(J177="","",IF($H177=$I177,IF(OR(AND($G177="Higher is better",J177>=$H177),AND($G177="Lower is better",J177<=$H177)),A_Scoring_Model!$C$14,0),IF($G177="Higher is better",IF(J177>=$H177,A_Scoring_Model!$C$14,IF(J177<$I177,0,A_Scoring_Model!$C$15+(A_Scoring_Model!$C$14-A_Scoring_Model!$C$15)*(J177-$I177)/($H177-$I177))),IF(J177<=$H177,A_Scoring_Model!$C$14,IF(J177>$I177,0,A_Scoring_Model!$C$15+(A_Scoring_Model!$C$14-A_Scoring_Model!$C$15)*($I177-J177)/($I177-$H177)))))) | O177: =IF(K177="","",IF($H177=$I177,IF(OR(AND($G177="Higher is better",K177>=$H177),AND($G177="Lower is better",K177<=$H177)),A_Scoring_Model!$C$14,0),IF($G177="Higher is better",IF(K177>=$H177,A_Scoring_Model!$C$14,IF(K177<$I177,0,A_Scoring_Model!$C$15+(A_Scoring_Model!$C$14-A_Scoring_Model!$C$15)*(K177-$I177)/($H177-$I177))),IF(K177<=$H177,A_Scoring_Model!$C$14,IF(K177>$I177,0,A_Scoring_Model!$C$15+(A_Scoring_Model!$C$14-A_Scoring_Model!$C$15)*($I177-K177)/($I177-$H177)))))) | P177: =IF(L177="","",IF($H177=$I177,IF(OR(AND($G177="Higher is better",L177>=$H177),AND($G177="Lower is better",L177<=$H177)),A_Scoring_Model!$C$14,0),IF($G177="Higher is better",IF(L177>=$H177,A_Scoring_Model!$C$14,IF(L177<$I177,0,A_Scoring_Model!$C$15+(A_Scoring_Model!$C$14-A_Scoring_Model!$C$15)*(L177-$I177)/($H177-$I177))),IF(L177<=$H177,A_Scoring_Model!$C$14,IF(L177>$I177,0,A_Scoring_Model!$C$15+(A_Scoring_Model!$C$14-A_Scoring_Model!$C$15)*($I177-L177)/($I177-$H177)))))) | Q177: =IF(M177="","",IF($H177=$I177,IF(OR(AND($G177="Higher is better",M177>=$H177),AND($G177="Lower is better",M177<=$H177)),A_Scoring_Model!$C$14,0),IF($G177="Higher is better",IF(M177>=$H177,A_Scoring_Model!$C$14,IF(M177<$I177,0,A_Scoring_Model!$C$15+(A_Scoring_Model!$C$14-A_Scoring_Model!$C$15)*(M177-$I177)/($H177-$I177))),IF(M177<=$H177,A_Scoring_Model!$C$14,IF(M177>$I177,0,A_Scoring_Model!$C$15+(A_Scoring_Model!$C$14-A_Scoring_Model!$C$15)*($I177-M177)/($I177-$H177)))))) -> 100
A178: =C_KPI_Benchmark!A178 -> 3.d-D2-12 | B178: =C_KPI_Benchmark!D178 -> 3.d | C178: =C_KPI_Benchmark!E178 -> AI Code Review Agent (Review Shield) | D178: =C_KPI_Benchmark!F178 -> D2 | E178: =C_KPI_Benchmark!J178 -> Product lines supported with ≤10% efficacy drop (NVMe SSD, UFS, eMMC/uSD, PSSD) | F178: =C_KPI_Benchmark!K178 -> count | G178: =C_KPI_Benchmark!L178 -> Higher is better | H178: =C_KPI_Benchmark!N178 -> 3 | I178: =IF(C_KPI_Benchmark!O178<>"",C_KPI_Benchmark!O178,IF(G178="Higher is better",H178*(1-A_Scoring_Model!$C$16),H178*(1+A_Scoring_Model!$C$16))) -> 2 | M178: 3 | N178: =IF(J178="","",IF($H178=$I178,IF(OR(AND($G178="Higher is better",J178>=$H178),AND($G178="Lower is better",J178<=$H178)),A_Scoring_Model!$C$14,0),IF($G178="Higher is better",IF(J178>=$H178,A_Scoring_Model!$C$14,IF(J178<$I178,0,A_Scoring_Model!$C$15+(A_Scoring_Model!$C$14-A_Scoring_Model!$C$15)*(J178-$I178)/($H178-$I178))),IF(J178<=$H178,A_Scoring_Model!$C$14,IF(J178>$I178,0,A_Scoring_Model!$C$15+(A_Scoring_Model!$C$14-A_Scoring_Model!$C$15)*($I178-J178)/($I178-$H178)))))) | O178: =IF(K178="","",IF($H178=$I178,IF(OR(AND($G178="Higher is better",K178>=$H178),AND($G178="Lower is better",K178<=$H178)),A_Scoring_Model!$C$14,0),IF($G178="Higher is better",IF(K178>=$H178,A_Scoring_Model!$C$14,IF(K178<$I178,0,A_Scoring_Model!$C$15+(A_Scoring_Model!$C$14-A_Scoring_Model!$C$15)*(K178-$I178)/($H178-$I178))),IF(K178<=$H178,A_Scoring_Model!$C$14,IF(K178>$I178,0,A_Scoring_Model!$C$15+(A_Scoring_Model!$C$14-A_Scoring_Model!$C$15)*($I178-K178)/($I178-$H178)))))) | P178: =IF(L178="","",IF($H178=$I178,IF(OR(AND($G178="Higher is better",L178>=$H178),AND($G178="Lower is better",L178<=$H178)),A_Scoring_Model!$C$14,0),IF($G178="Higher is better",IF(L178>=$H178,A_Scoring_Model!$C$14,IF(L178<$I178,0,A_Scoring_Model!$C$15+(A_Scoring_Model!$C$14-A_Scoring_Model!$C$15)*(L178-$I178)/($H178-$I178))),IF(L178<=$H178,A_Scoring_Model!$C$14,IF(L178>$I178,0,A_Scoring_Model!$C$15+(A_Scoring_Model!$C$14-A_Scoring_Model!$C$15)*($I178-L178)/($I178-$H178)))))) | Q178: =IF(M178="","",IF($H178=$I178,IF(OR(AND($G178="Higher is better",M178>=$H178),AND($G178="Lower is better",M178<=$H178)),A_Scoring_Model!$C$14,0),IF($G178="Higher is better",IF(M178>=$H178,A_Scoring_Model!$C$14,IF(M178<$I178,0,A_Scoring_Model!$C$15+(A_Scoring_Model!$C$14-A_Scoring_Model!$C$15)*(M178-$I178)/($H178-$I178))),IF(M178<=$H178,A_Scoring_Model!$C$14,IF(M178>$I178,0,A_Scoring_Model!$C$15+(A_Scoring_Model!$C$14-A_Scoring_Model!$C$15)*($I178-M178)/($I178-$H178)))))) -> 100
... A200: =C_KPI_Benchmark!A200 -> 3.d-D6-34 | B200: =C_KPI_Benchmark!D200 -> 3.d | C200: =C_KPI_Benchmark!E200 -> AI Code Review Agent (Review Shield) | D200: =C_KPI_Benchmark!F200 -> D6 | E200: =C_KPI_Benchmark!J200 -> Named owner and support SLA | F200: =C_KPI_Benchmark!K200 -> Yes/No | G200: =C_KPI_Benchmark!L200 -> Higher is better | H200: =C_KPI_Benchmark!N200 -> 1 | I200: =IF(C_KPI_Benchmark!O200<>"",C_KPI_Benchmark!O200,IF(G200="Higher is better",H200*(1-A_Scoring_Model!$C$16),H200*(1+A_Scoring_Model!$C$16))) -> 0.8 | M200: 1 | N200: =IF(J200="","",IF($H200=$I200,IF(OR(AND($G200="Higher is better",J200>=$H200),AND($G200="Lower is better",J200<=$H200)),A_Scoring_Model!$C$14,0),IF($G200="Higher is better",IF(J200>=$H200,A_Scoring_Model!$C$14,IF(J200<$I200,0,A_Scoring_Model!$C$15+(A_Scoring_Model!$C$14-A_Scoring_Model!$C$15)*(J200-$I200)/($H200-$I200))),IF(J200<=$H200,A_Scoring_Model!$C$14,IF(J200>$I200,0,A_Scoring_Model!$C$15+(A_Scoring_Model!$C$14-A_Scoring_Model!$C$15)*($I200-J200)/($I200-$H200)))))) | O200: =IF(K200="","",IF($H200=$I200,IF(OR(AND($G200="Higher is better",K200>=$H200),AND($G200="Lower is better",K200<=$H200)),A_Scoring_Model!$C$14,0),IF($G200="Higher is better",IF(K200>=$H200,A_Scoring_Model!$C$14,IF(K200<$I200,0,A_Scoring_Model!$C$15+(A_Scoring_Model!$C$14-A_Scoring_Model!$C$15)*(K200-$I200)/($H200-$I200))),IF(K200<=$H200,A_Scoring_Model!$C$14,IF(K200>$I200,0,A_Scoring_Model!$C$15+(A_Scoring_Model!$C$14-A_Scoring_Model!$C$15)*($I200-K200)/($I200-$H200)))))) | P200: =IF(L200="","",IF($H200=$I200,IF(OR(AND($G200="Higher is better",L200>=$H200),AND($G200="Lower is better",L200<=$H200)),A_Scoring_Model!$C$14,0),IF($G200="Higher is better",IF(L200>=$H200,A_Scoring_Model!$C$14,IF(L200<$I200,0,A_Scoring_Model!$C$15+(A_Scoring_Model!$C$14-A_Scoring_Model!$C$15)*(L200-$I200)/($H200-$I200))),IF(L200<=$H200,A_Scoring_Model!$C$14,IF(L200>$I200,0,A_Scoring_Model!$C$15+(A_Scoring_Model!$C$14-A_Scoring_Model!$C$15)*($I200-L200)/($I200-$H200)))))) | Q200: =IF(M200="","",IF($H200=$I200,IF(OR(AND($G200="Higher is better",M200>=$H200),AND($G200="Lower is better",M200<=$H200)),A_Scoring_Model!$C$14,0),IF($G200="Higher is better",IF(M200>=$H200,A_Scoring_Model!$C$14,IF(M200<$I200,0,A_Scoring_Model!$C$15+(A_Scoring_Model!$C$14-A_Scoring_Model!$C$15)*(M200-$I200)/($H200-$I200))),IF(M200<=$H200,A_Scoring_Model!$C$14,IF(M200>$I200,0,A_Scoring_Model!$C$15+(A_Scoring_Model!$C$14-A_Scoring_Model!$C$15)*($I200-M200)/($I200-$H200)))))) -> 100
A201: =C_KPI_Benchmark!A201 -> 4.a-D1-01 | B201: =C_KPI_Benchmark!D201 -> 4.a | C201: =C_KPI_Benchmark!E201 -> IaC Provisioner Agent | D201: =C_KPI_Benchmark!F201 -> D1 | E201: =C_KPI_Benchmark!J201 -> IaC validity (validate / lint) | F201: =C_KPI_Benchmark!K201 -> % | G201: =C_KPI_Benchmark!L201 -> Higher is better | H201: =C_KPI_Benchmark!N201 -> 1 | I201: =IF(C_KPI_Benchmark!O201<>"",C_KPI_Benchmark!O201,IF(G201="Higher is better",H201*(1-A_Scoring_Model!$C$16),H201*(1+A_Scoring_Model!$C$16))) -> 0.98 | N201: =IF(J201="","",IF($H201=$I201,IF(OR(AND($G201="Higher is better",J201>=$H201),AND($G201="Lower is better",J201<=$H201)),A_Scoring_Model!$C$14,0),IF($G201="Higher is better",IF(J201>=$H201,A_Scoring_Model!$C$14,IF(J201<$I201,0,A_Scoring_Model!$C$15+(A_Scoring_Model!$C$14-A_Scoring_Model!$C$15)*(J201-$I201)/($H201-$I201))),IF(J201<=$H201,A_Scoring_Model!$C$14,IF(J201>$I201,0,A_Scoring_Model!$C$15+(A_Scoring_Model!$C$14-A_Scoring_Model!$C$15)*($I201-J201)/($I201-$H201)))))) | O201: =IF(K201="","",IF($H201=$I201,IF(OR(AND($G201="Higher is better",K201>=$H201),AND($G201="Lower is better",K201<=$H201)),A_Scoring_Model!$C$14,0),IF($G201="Higher is better",IF(K201>=$H201,A_Scoring_Model!$C$14,IF(K201<$I201,0,A_Scoring_Model!$C$15+(A_Scoring_Model!$C$14-A_Scoring_Model!$C$15)*(K201-$I201)/($H201-$I201))),IF(K201<=$H201,A_Scoring_Model!$C$14,IF(K201>$I201,0,A_Scoring_Model!$C$15+(A_Scoring_Model!$C$14-A_Scoring_Model!$C$15)*($I201-K201)/($I201-$H201)))))) | P201: =IF(L201="","",IF($H201=$I201,IF(OR(AND($G201="Higher is better",L201>=$H201),AND($G201="Lower is better",L201<=$H201)),A_Scoring_Model!$C$14,0),IF($G201="Higher is better",IF(L201>=$H201,A_Scoring_Model!$C$14,IF(L201<$I201,0,A_Scoring_Model!$C$15+(A_Scoring_Model!$C$14-A_Scoring_Model!$C$15)*(L201-$I201)/($H201-$I201))),IF(L201<=$H201,A_Scoring_Model!$C$14,IF(L201>$I201,0,A_Scoring_Model!$C$15+(A_Scoring_Model!$C$14-A_Scoring_Model!$C$15)*($I201-L201)/($I201-$H201)))))) | Q201: =IF(M201="","",IF($H201=$I201,IF(OR(AND($G201="Higher is better",M201>=$H201),AND($G201="Lower is better",M201<=$H201)),A_Scoring_Model!$C$14,0),IF($G201="Higher is better",IF(M201>=$H201,A_Scoring_Model!$C$14,IF(M201<$I201,0,A_Scoring_Model!$C$15+(A_Scoring_Model!$C$14-A_Scoring_Model!$C$15)*(M201-$I201)/($H201-$I201))),IF(M201<=$H201,A_Scoring_Model!$C$14,IF(M201>$I201,0,A_Scoring_Model!$C$15+(A_Scoring_Model!$C$14-A_Scoring_Model!$C$15)*($I201-M201)/($I201-$H201))))))
A202: =C_KPI_Benchmark!A202 -> 4.a-D1-02 | B202: =C_KPI_Benchmark!D202 -> 4.a | C202: =C_KPI_Benchmark!E202 -> IaC Provisioner Agent | D202: =C_KPI_Benchmark!F202 -> D1 | E202: =C_KPI_Benchmark!J202 -> First-attempt provisioning success | F202: =C_KPI_Benchmark!K202 -> % | G202: =C_KPI_Benchmark!L202 -> Higher is better | H202: =C_KPI_Benchmark!N202 -> 0.95 | I202: =IF(C_KPI_Benchmark!O202<>"",C_KPI_Benchmark!O202,IF(G202="Higher is better",H202*(1-A_Scoring_Model!$C$16),H202*(1+A_Scoring_Model!$C$16))) -> 0.85 | N202: =IF(J202="","",IF($H202=$I202,IF(OR(AND($G202="Higher is better",J202>=$H202),AND($G202="Lower is better",J202<=$H202)),A_Scoring_Model!$C$14,0),IF($G202="Higher is better",IF(J202>=$H202,A_Scoring_Model!$C$14,IF(J202<$I202,0,A_Scoring_Model!$C$15+(A_Scoring_Model!$C$14-A_Scoring_Model!$C$15)*(J202-$I202)/($H202-$I202))),IF(J202<=$H202,A_Scoring_Model!$C$14,IF(J202>$I202,0,A_Scoring_Model!$C$15+(A_Scoring_Model!$C$14-A_Scoring_Model!$C$15)*($I202-J202)/($I202-$H202)))))) | O202: =IF(K202="","",IF($H202=$I202,IF(OR(AND($G202="Higher is better",K202>=$H202),AND($G202="Lower is better",K202<=$H202)),A_Scoring_Model!$C$14,0),IF($G202="Higher is better",IF(K202>=$H202,A_Scoring_Model!$C$14,IF(K202<$I202,0,A_Scoring_Model!$C$15+(A_Scoring_Model!$C$14-A_Scoring_Model!$C$15)*(K202-$I202)/($H202-$I202))),IF(K202<=$H202,A_Scoring_Model!$C$14,IF(K202>$I202,0,A_Scoring_Model!$C$15+(A_Scoring_Model!$C$14-A_Scoring_Model!$C$15)*($I202-K202)/($I202-$H202)))))) | P202: =IF(L202="","",IF($H202=$I202,IF(OR(AND($G202="Higher is better",L202>=$H202),AND($G202="Lower is better",L202<=$H202)),A_Scoring_Model!$C$14,0),IF($G202="Higher is better",IF(L202>=$H202,A_Scoring_Model!$C$14,IF(L202<$I202,0,A_Scoring_Model!$C$15+(A_Scoring_Model!$C$14-A_Scoring_Model!$C$15)*(L202-$I202)/($H202-$I202))),IF(L202<=$H202,A_Scoring_Model!$C$14,IF(L202>$I202,0,A_Scoring_Model!$C$15+(A_Scoring_Model!$C$14-A_Scoring_Model!$C$15)*($I202-L202)/($I202-$H202)))))) | Q202: =IF(M202="","",IF($H202=$I202,IF(OR(AND($G202="Higher is better",M202>=$H202),AND($G202="Lower is better",M202<=$H202)),A_Scoring_Model!$C$14,0),IF($G202="Higher is better",IF(M202>=$H202,A_Scoring_Model!$C$14,IF(M202<$I202,0,A_Scoring_Model!$C$15+(A_Scoring_Model!$C$14-A_Scoring_Model!$C$15)*(M202-$I202)/($H202-$I202))),IF(M202<=$H202,A_Scoring_Model!$C$14,IF(M202>$I202,0,A_Scoring_Model!$C$15+(A_Scoring_Model!$C$14-A_Scoring_Model!$C$15)*($I202-M202)/($I202-$H202))))))
A203: =C_KPI_Benchmark!A203 -> 4.a-D1-03 | B203: =C_KPI_Benchmark!D203 -> 4.a | C203: =C_KPI_Benchmark!E203 -> IaC Provisioner Agent | D203: =C_KPI_Benchmark!F203 -> D1 | E203: =C_KPI_Benchmark!J203 -> Policy-as-code compliance | F203: =C_KPI_Benchmark!K203 -> % | G203: =C_KPI_Benchmark!L203 -> Higher is better | H203: =C_KPI_Benchmark!N203 -> 1 | I203: =IF(C_KPI_Benchmark!O203<>"",C_KPI_Benchmark!O203,IF(G203="Higher is better",H203*(1-A_Scoring_Model!$C$16),H203*(1+A_Scoring_Model!$C$16))) -> 1 | N203: =IF(J203="","",IF($H203=$I203,IF(OR(AND($G203="Higher is better",J203>=$H203),AND($G203="Lower is better",J203<=$H203)),A_Scoring_Model!$C$14,0),IF($G203="Higher is better",IF(J203>=$H203,A_Scoring_Model!$C$14,IF(J203<$I203,0,A_Scoring_Model!$C$15+(A_Scoring_Model!$C$14-A_Scoring_Model!$C$15)*(J203-$I203)/($H203-$I203))),IF(J203<=$H203,A_Scoring_Model!$C$14,IF(J203>$I203,0,A_Scoring_Model!$C$15+(A_Scoring_Model!$C$14-A_Scoring_Model!$C$15)*($I203-J203)/($I203-$H203)))))) | O203: =IF(K203="","",IF($H203=$I203,IF(OR(AND($G203="Higher is better",K203>=$H203),AND($G203="Lower is better",K203<=$H203)),A_Scoring_Model!$C$14,0),IF($G203="Higher is better",IF(K203>=$H203,A_Scoring_Model!$C$14,IF(K203<$I203,0,A_Scoring_Model!$C$15+(A_Scoring_Model!$C$14-A_Scoring_Model!$C$15)*(K203-$I203)/($H203-$I203))),IF(K203<=$H203,A_Scoring_Model!$C$14,IF(K203>$I203,0,A_Scoring_Model!$C$15+(A_Scoring_Model!$C$14-A_Scoring_Model!$C$15)*($I203-K203)/($I203-$H203)))))) | P203: =IF(L203="","",IF($H203=$I203,IF(OR(AND($G203="Higher is better",L203>=$H203),AND($G203="Lower is better",L203<=$H203)),A_Scoring_Model!$C$14,0),IF($G203="Higher is better",IF(L203>=$H203,A_Scoring_Model!$C$14,IF(L203<$I203,0,A_Scoring_Model!$C$15+(A_Scoring_Model!$C$14-A_Scoring_Model!$C$15)*(L203-$I203)/($H203-$I203))),IF(L203<=$H203,A_Scoring_Model!$C$14,IF(L203>$I203,0,A_Scoring_Model!$C$15+(A_Scoring_Model!$C$14-A_Scoring_Model!$C$15)*($I203-L203)/($I203-$H203)))))) | Q203: =IF(M203="","",IF($H203=$I203,IF(OR(AND($G203="Higher is better",M203>=$H203),AND($G203="Lower is better",M203<=$H203)),A_Scoring_Model!$C$14,0),IF($G203="Higher is better",IF(M203>=$H203,A_Scoring_Model!$C$14,IF(M203<$I203,0,A_Scoring_Model!$C$15+(A_Scoring_Model!$C$14-A_Scoring_Model!$C$15)*(M203-$I203)/($H203-$I203))),IF(M203<=$H203,A_Scoring_Model!$C$14,IF(M203>$I203,0,A_Scoring_Model!$C$15+(A_Scoring_Model!$C$14-A_Scoring_Model!$C$15)*($I203-M203)/($I203-$H203))))))
A204: =C_KPI_Benchmark!A204 -> 4.a-D2-04 | B204: =C_KPI_Benchmark!D204 -> 4.a | C204: =C_KPI_Benchmark!E204 -> IaC Provisioner Agent | D204: =C_KPI_Benchmark!F204 -> D2 | E204: =C_KPI_Benchmark!J204 -> Module registry covers VM, K8s and bare-metal host + DUT rigs | F204: =C_KPI_Benchmark!K204 -> Yes/No | G204: =C_KPI_Benchmark!L204 -> Higher is better | H204: =C_KPI_Benchmark!N204 -> 1 | I204: =IF(C_KPI_Benchmark!O204<>"",C_KPI_Benchmark!O204,IF(G204="Higher is better",H204*(1-A_Scoring_Model!$C$16),H204*(1+A_Scoring_Model!$C$16))) -> 0.8 | N204: =IF(J204="","",IF($H204=$I204,IF(OR(AND($G204="Higher is better",J204>=$H204),AND($G204="Lower is better",J204<=$H204)),A_Scoring_Model!$C$14,0),IF($G204="Higher is better",IF(J204>=$H204,A_Scoring_Model!$C$14,IF(J204<$I204,0,A_Scoring_Model!$C$15+(A_Scoring_Model!$C$14-A_Scoring_Model!$C$15)*(J204-$I204)/($H204-$I204))),IF(J204<=$H204,A_Scoring_Model!$C$14,IF(J204>$I204,0,A_Scoring_Model!$C$15+(A_Scoring_Model!$C$14-A_Scoring_Model!$C$15)*($I204-J204)/($I204-$H204)))))) | O204: =IF(K204="","",IF($H204=$I204,IF(OR(AND($G204="Higher is better",K204>=$H204),AND($G204="Lower is better",K204<=$H204)),A_Scoring_Model!$C$14,0),IF($G204="Higher is better",IF(K204>=$H204,A_Scoring_Model!$C$14,IF(K204<$I204,0,A_Scoring_Model!$C$15+(A_Scoring_Model!$C$14-A_Scoring_Model!$C$15)*(K204-$I204)/($H204-$I204))),IF(K204<=$H204,A_Scoring_Model!$C$14,IF(K204>$I204,0,A_Scoring_Model!$C$15+(A_Scoring_Model!$C$14-A_Scoring_Model!$C$15)*($I204-K204)/($I204-$H204)))))) | P204: =IF(L204="","",IF($H204=$I204,IF(OR(AND($G204="Higher is better",L204>=$H204),AND($G204="Lower is better",L204<=$H204)),A_Scoring_Model!$C$14,0),IF($G204="Higher is better",IF(L204>=$H204,A_Scoring_Model!$C$14,IF(L204<$I204,0,A_Scoring_Model!$C$15+(A_Scoring_Model!$C$14-A_Scoring_Model!$C$15)*(L204-$I204)/($H204-$I204))),IF(L204<=$H204,A_Scoring_Model!$C$14,IF(L204>$I204,0,A_Scoring_Model!$C$15+(A_Scoring_Model!$C$14-A_Scoring_Model!$C$15)*($I204-L204)/($I204-$H204)))))) | Q204: =IF(M204="","",IF($H204=$I204,IF(OR(AND($G204="Higher is better",M204>=$H204),AND($G204="Lower is better",M204<=$H204)),A_Scoring_Model!$C$14,0),IF($G204="Higher is better",IF(M204>=$H204,A_Scoring_Model!$C$14,IF(M204<$I204,0,A_Scoring_Model!$C$15+(A_Scoring_Model!$C$14-A_Scoring_Model!$C$15)*(M204-$I204)/($H204-$I204))),IF(M204<=$H204,A_Scoring_Model!$C$14,IF(M204>$I204,0,A_Scoring_Model!$C$15+(A_Scoring_Model!$C$14-A_Scoring_Model!$C$15)*($I204-M204)/($I204-$H204))))))
A205: =C_KPI_Benchmark!A205 -> 4.a-D2-05 | B205: =C_KPI_Benchmark!D205 -> 4.a | C205: =C_KPI_Benchmark!E205 -> IaC Provisioner Agent | D205: =C_KPI_Benchmark!F205 -> D2 | E205: =C_KPI_Benchmark!J205 -> Product lines supported with ≤10% efficacy drop (NVMe SSD, UFS, eMMC/uSD, PSSD) | F205: =C_KPI_Benchmark!K205 -> count | G205: =C_KPI_Benchmark!L205 -> Higher is better | H205: =C_KPI_Benchmark!N205 -> 3 | I205: =IF(C_KPI_Benchmark!O205<>"",C_KPI_Benchmark!O205,IF(G205="Higher is better",H205*(1-A_Scoring_Model!$C$16),H205*(1+A_Scoring_Model!$C$16))) -> 2 | N205: =IF(J205="","",IF($H205=$I205,IF(OR(AND($G205="Higher is better",J205>=$H205),AND($G205="Lower is better",J205<=$H205)),A_Scoring_Model!$C$14,0),IF($G205="Higher is better",IF(J205>=$H205,A_Scoring_Model!$C$14,IF(J205<$I205,0,A_Scoring_Model!$C$15+(A_Scoring_Model!$C$14-A_Scoring_Model!$C$15)*(J205-$I205)/($H205-$I205))),IF(J205<=$H205,A_Scoring_Model!$C$14,IF(J205>$I205,0,A_Scoring_Model!$C$15+(A_Scoring_Model!$C$14-A_Scoring_Model!$C$15)*($I205-J205)/($I205-$H205)))))) | O205: =IF(K205="","",IF($H205=$I205,IF(OR(AND($G205="Higher is better",K205>=$H205),AND($G205="Lower is better",K205<=$H205)),A_Scoring_Model!$C$14,0),IF($G205="Higher is better",IF(K205>=$H205,A_Scoring_Model!$C$14,IF(K205<$I205,0,A_Scoring_Model!$C$15+(A_Scoring_Model!$C$14-A_Scoring_Model!$C$15)*(K205-$I205)/($H205-$I205))),IF(K205<=$H205,A_Scoring_Model!$C$14,IF(K205>$I205,0,A_Scoring_Model!$C$15+(A_Scoring_Model!$C$14-A_Scoring_Model!$C$15)*($I205-K205)/($I205-$H205)))))) | P205: =IF(L205="","",IF($H205=$I205,IF(OR(AND($G205="Higher is better",L205>=$H205),AND($G205="Lower is better",L205<=$H205)),A_Scoring_Model!$C$14,0),IF($G205="Higher is better",IF(L205>=$H205,A_Scoring_Model!$C$14,IF(L205<$I205,0,A_Scoring_Model!$C$15+(A_Scoring_Model!$C$14-A_Scoring_Model!$C$15)*(L205-$I205)/($H205-$I205))),IF(L205<=$H205,A_Scoring_Model!$C$14,IF(L205>$I205,0,A_Scoring_Model!$C$15+(A_Scoring_Model!$C$14-A_Scoring_Model!$C$15)*($I205-L205)/($I205-$H205)))))) | Q205: =IF(M205="","",IF($H205=$I205,IF(OR(AND($G205="Higher is better",M205>=$H205),AND($G205="Lower is better",M205<=$H205)),A_Scoring_Model!$C$14,0),IF($G205="Higher is better",IF(M205>=$H205,A_Scoring_Model!$C$14,IF(M205<$I205,0,A_Scoring_Model!$C$15+(A_Scoring_Model!$C$14-A_Scoring_Model!$C$15)*(M205-$I205)/($H205-$I205))),IF(M205<=$H205,A_Scoring_Model!$C$14,IF(M205>$I205,0,A_Scoring_Model!$C$15+(A_Scoring_Model!$C$14-A_Scoring_Model!$C$15)*($I205-M205)/($I205-$H205))))))
A206: =C_KPI_Benchmark!A206 -> 4.a-D2-06 | B206: =C_KPI_Benchmark!D206 -> 4.a | C206: =C_KPI_Benchmark!E206 -> IaC Provisioner Agent | D206: =C_KPI_Benchmark!F206 -> D2 | E206: =C_KPI_Benchmark!J206 -> Uses Zion shared services instead of re-implementing them | F206: =C_KPI_Benchmark!K206 -> Yes/No | G206: =C_KPI_Benchmark!L206 -> Higher is better | H206: =C_KPI_Benchmark!N206 -> 1 | I206: =IF(C_KPI_Benchmark!O206<>"",C_KPI_Benchmark!O206,IF(G206="Higher is better",H206*(1-A_Scoring_Model!$C$16),H206*(1+A_Scoring_Model!$C$16))) -> 0.8 | N206: =IF(J206="","",IF($H206=$I206,IF(OR(AND($G206="Higher is better",J206>=$H206),AND($G206="Lower is better",J206<=$H206)),A_Scoring_Model!$C$14,0),IF($G206="Higher is better",IF(J206>=$H206,A_Scoring_Model!$C$14,IF(J206<$I206,0,A_Scoring_Model!$C$15+(A_Scoring_Model!$C$14-A_Scoring_Model!$C$15)*(J206-$I206)/($H206-$I206))),IF(J206<=$H206,A_Scoring_Model!$C$14,IF(J206>$I206,0,A_Scoring_Model!$C$15+(A_Scoring_Model!$C$14-A_Scoring_Model!$C$15)*($I206-J206)/($I206-$H206)))))) | O206: =IF(K206="","",IF($H206=$I206,IF(OR(AND($G206="Higher is better",K206>=$H206),AND($G206="Lower is better",K206<=$H206)),A_Scoring_Model!$C$14,0),IF($G206="Higher is better",IF(K206>=$H206,A_Scoring_Model!$C$14,IF(K206<$I206,0,A_Scoring_Model!$C$15+(A_Scoring_Model!$C$14-A_Scoring_Model!$C$15)*(K206-$I206)/($H206-$I206))),IF(K206<=$H206,A_Scoring_Model!$C$14,IF(K206>$I206,0,A_Scoring_Model!$C$15+(A_Scoring_Model!$C$14-A_Scoring_Model!$C$15)*($I206-K206)/($I206-$H206)))))) | P206: =IF(L206="","",IF($H206=$I206,IF(OR(AND($G206="Higher is better",L206>=$H206),AND($G206="Lower is better",L206<=$H206)),A_Scoring_Model!$C$14,0),IF($G206="Higher is better",IF(L206>=$H206,A_Scoring_Model!$C$14,IF(L206<$I206,0,A_Scoring_Model!$C$15+(A_Scoring_Model!$C$14-A_Scoring_Model!$C$15)*(L206-$I206)/($H206-$I206))),IF(L206<=$H206,A_Scoring_Model!$C$14,IF(L206>$I206,0,A_Scoring_Model!$C$15+(A_Scoring_Model!$C$14-A_Scoring_Model!$C$15)*($I206-L206)/($I206-$H206)))))) | Q206: =IF(M206="","",IF($H206=$I206,IF(OR(AND($G206="Higher is better",M206>=$H206),AND($G206="Lower is better",M206<=$H206)),A_Scoring_Model!$C$14,0),IF($G206="Higher is better",IF(M206>=$H206,A_Scoring_Model!$C$14,IF(M206<$I206,0,A_Scoring_Model!$C$15+(A_Scoring_Model!$C$14-A_Scoring_Model!$C$15)*(M206-$I206)/($H206-$I206))),IF(M206<=$H206,A_Scoring_Model!$C$14,IF(M206>$I206,0,A_Scoring_Model!$C$15+(A_Scoring_Model!$C$14-A_Scoring_Model!$C$15)*($I206-M206)/($I206-$H206))))))
A207: =C_KPI_Benchmark!A207 -> 4.a-D3-07 | B207: =C_KPI_Benchmark!D207 -> 4.a | C207: =C_KPI_Benchmark!E207 -> IaC Provisioner Agent | D207: =C_KPI_Benchmark!F207 -> D3 | E207: =C_KPI_Benchmark!J207 -> Rigs provisioned in parallel | F207: =C_KPI_Benchmark!K207 -> count | G207: =C_KPI_Benchmark!L207 -> Higher is better | H207: =C_KPI_Benchmark!N207 -> 50 | I207: =IF(C_KPI_Benchmark!O207<>"",C_KPI_Benchmark!O207,IF(G207="Higher is better",H207*(1-A_Scoring_Model!$C$16),H207*(1+A_Scoring_Model!$C$16))) -> 40 | N207: =IF(J207="","",IF($H207=$I207,IF(OR(AND($G207="Higher is better",J207>=$H207),AND($G207="Lower is better",J207<=$H207)),A_Scoring_Model!$C$14,0),IF($G207="Higher is better",IF(J207>=$H207,A_Scoring_Model!$C$14,IF(J207<$I207,0,A_Scoring_Model!$C$15+(A_Scoring_Model!$C$14-A_Scoring_Model!$C$15)*(J207-$I207)/($H207-$I207))),IF(J207<=$H207,A_Scoring_Model!$C$14,IF(J207>$I207,0,A_Scoring_Model!$C$15+(A_Scoring_Model!$C$14-A_Scoring_Model!$C$15)*($I207-J207)/($I207-$H207)))))) | O207: =IF(K207="","",IF($H207=$I207,IF(OR(AND($G207="Higher is better",K207>=$H207),AND($G207="Lower is better",K207<=$H207)),A_Scoring_Model!$C$14,0),IF($G207="Higher is better",IF(K207>=$H207,A_Scoring_Model!$C$14,IF(K207<$I207,0,A_Scoring_Model!$C$15+(A_Scoring_Model!$C$14-A_Scoring_Model!$C$15)*(K207-$I207)/($H207-$I207))),IF(K207<=$H207,A_Scoring_Model!$C$14,IF(K207>$I207,0,A_Scoring_Model!$C$15+(A_Scoring_Model!$C$14-A_Scoring_Model!$C$15)*($I207-K207)/($I207-$H207)))))) | P207: =IF(L207="","",IF($H207=$I207,IF(OR(AND($G207="Higher is better",L207>=$H207),AND($G207="Lower is better",L207<=$H207)),A_Scoring_Model!$C$14,0),IF($G207="Higher is better",IF(L207>=$H207,A_Scoring_Model!$C$14,IF(L207<$I207,0,A_Scoring_Model!$C$15+(A_Scoring_Model!$C$14-A_Scoring_Model!$C$15)*(L207-$I207)/($H207-$I207))),IF(L207<=$H207,A_Scoring_Model!$C$14,IF(L207>$I207,0,A_Scoring_Model!$C$15+(A_Scoring_Model!$C$14-A_Scoring_Model!$C$15)*($I207-L207)/($I207-$H207)))))) | Q207: =IF(M207="","",IF($H207=$I207,IF(OR(AND($G207="Higher is better",M207>=$H207),AND($G207="Lower is better",M207<=$H207)),A_Scoring_Model!$C$14,0),IF($G207="Higher is better",IF(M207>=$H207,A_Scoring_Model!$C$14,IF(M207<$I207,0,A_Scoring_Model!$C$15+(A_Scoring_Model!$C$14-A_Scoring_Model!$C$15)*(M207-$I207)/($H207-$I207))),IF(M207<=$H207,A_Scoring_Model!$C$14,IF(M207>$I207,0,A_Scoring_Model!$C$15+(A_Scoring_Model!$C$14-A_Scoring_Model!$C$15)*($I207-M207)/($I207-$H207))))))
A208: =C_KPI_Benchmark!A208 -> 4.a-D3-08 | B208: =C_KPI_Benchmark!D208 -> 4.a | C208: =C_KPI_Benchmark!E208 -> IaC Provisioner Agent | D208: =C_KPI_Benchmark!F208 -> D3 | E208: =C_KPI_Benchmark!J208 -> Environment ready time | F208: =C_KPI_Benchmark!K208 -> min | G208: =C_KPI_Benchmark!L208 -> Lower is better | H208: =C_KPI_Benchmark!N208 -> 30 | I208: =IF(C_KPI_Benchmark!O208<>"",C_KPI_Benchmark!O208,IF(G208="Higher is better",H208*(1-A_Scoring_Model!$C$16),H208*(1+A_Scoring_Model!$C$16))) -> 36 | N208: =IF(J208="","",IF($H208=$I208,IF(OR(AND($G208="Higher is better",J208>=$H208),AND($G208="Lower is better",J208<=$H208)),A_Scoring_Model!$C$14,0),IF($G208="Higher is better",IF(J208>=$H208,A_Scoring_Model!$C$14,IF(J208<$I208,0,A_Scoring_Model!$C$15+(A_Scoring_Model!$C$14-A_Scoring_Model!$C$15)*(J208-$I208)/($H208-$I208))),IF(J208<=$H208,A_Scoring_Model!$C$14,IF(J208>$I208,0,A_Scoring_Model!$C$15+(A_Scoring_Model!$C$14-A_Scoring_Model!$C$15)*($I208-J208)/($I208-$H208)))))) | O208: =IF(K208="","",IF($H208=$I208,IF(OR(AND($G208="Higher is better",K208>=$H208),AND($G208="Lower is better",K208<=$H208)),A_Scoring_Model!$C$14,0),IF($G208="Higher is better",IF(K208>=$H208,A_Scoring_Model!$C$14,IF(K208<$I208,0,A_Scoring_Model!$C$15+(A_Scoring_Model!$C$14-A_Scoring_Model!$C$15)*(K208-$I208)/($H208-$I208))),IF(K208<=$H208,A_Scoring_Model!$C$14,IF(K208>$I208,0,A_Scoring_Model!$C$15+(A_Scoring_Model!$C$14-A_Scoring_Model!$C$15)*($I208-K208)/($I208-$H208)))))) | P208: =IF(L208="","",IF($H208=$I208,IF(OR(AND($G208="Higher is better",L208>=$H208),AND($G208="Lower is better",L208<=$H208)),A_Scoring_Model!$C$14,0),IF($G208="Higher is better",IF(L208>=$H208,A_Scoring_Model!$C$14,IF(L208<$I208,0,A_Scoring_Model!$C$15+(A_Scoring_Model!$C$14-A_Scoring_Model!$C$15)*(L208-$I208)/($H208-$I208))),IF(L208<=$H208,A_Scoring_Model!$C$14,IF(L208>$I208,0,A_Scoring_Model!$C$15+(A_Scoring_Model!$C$14-A_Scoring_Model!$C$15)*($I208-L208)/($I208-$H208)))))) | Q208: =IF(M208="","",IF($H208=$I208,IF(OR(AND($G208="Higher is better",M208>=$H208),AND($G208="Lower is better",M208<=$H208)),A_Scoring_Model!$C$14,0),IF($G208="Higher is better",IF(M208>=$H208,A_Scoring_Model!$C$14,IF(M208<$I208,0,A_Scoring_Model!$C$15+(A_Scoring_Model!$C$14-A_Scoring_Model!$C$15)*(M208-$I208)/($H208-$I208))),IF(M208<=$H208,A_Scoring_Model!$C$14,IF(M208>$I208,0,A_Scoring_Model!$C$15+(A_Scoring_Model!$C$14-A_Scoring_Model!$C$15)*($I208-M208)/($I208-$H208))))))
A209: =C_KPI_Benchmark!A209 -> 4.a-D3-09 | B209: =C_KPI_Benchmark!D209 -> 4.a | C209: =C_KPI_Benchmark!E209 -> IaC Provisioner Agent | D209: =C_KPI_Benchmark!F209 -> D3 | E209: =C_KPI_Benchmark!J209 -> Latency degradation at 10× load | F209: =C_KPI_Benchmark!K209 -> % | G209: =C_KPI_Benchmark!L209 -> Lower is better | H209: =C_KPI_Benchmark!N209 -> 0.2 | I209: =IF(C_KPI_Benchmark!O209<>"",C_KPI_Benchmark!O209,IF(G209="Higher is better",H209*(1-A_Scoring_Model!$C$16),H209*(1+A_Scoring_Model!$C$16))) -> 0.4 | N209: =IF(J209="","",IF($H209=$I209,IF(OR(AND($G209="Higher is better",J209>=$H209),AND($G209="Lower is better",J209<=$H209)),A_Scoring_Model!$C$14,0),IF($G209="Higher is better",IF(J209>=$H209,A_Scoring_Model!$C$14,IF(J209<$I209,0,A_Scoring_Model!$C$15+(A_Scoring_Model!$C$14-A_Scoring_Model!$C$15)*(J209-$I209)/($H209-$I209))),IF(J209<=$H209,A_Scoring_Model!$C$14,IF(J209>$I209,0,A_Scoring_Model!$C$15+(A_Scoring_Model!$C$14-A_Scoring_Model!$C$15)*($I209-J209)/($I209-$H209)))))) | O209: =IF(K209="","",IF($H209=$I209,IF(OR(AND($G209="Higher is better",K209>=$H209),AND($G209="Lower is better",K209<=$H209)),A_Scoring_Model!$C$14,0),IF($G209="Higher is better",IF(K209>=$H209,A_Scoring_Model!$C$14,IF(K209<$I209,0,A_Scoring_Model!$C$15+(A_Scoring_Model!$C$14-A_Scoring_Model!$C$15)*(K209-$I209)/($H209-$I209))),IF(K209<=$H209,A_Scoring_Model!$C$14,IF(K209>$I209,0,A_Scoring_Model!$C$15+(A_Scoring_Model!$C$14-A_Scoring_Model!$C$15)*($I209-K209)/($I209-$H209)))))) | P209: =IF(L209="","",IF($H209=$I209,IF(OR(AND($G209="Higher is better",L209>=$H209),AND($G209="Lower is better",L209<=$H209)),A_Scoring_Model!$C$14,0),IF($G209="Higher is better",IF(L209>=$H209,A_Scoring_Model!$C$14,IF(L209<$I209,0,A_Scoring_Model!$C$15+(A_Scoring_Model!$C$14-A_Scoring_Model!$C$15)*(L209-$I209)/($H209-$I209))),IF(L209<=$H209,A_Scoring_Model!$C$14,IF(L209>$I209,0,A_Scoring_Model!$C$15+(A_Scoring_Model!$C$14-A_Scoring_Model!$C$15)*($I209-L209)/($I209-$H209)))))) | Q209: =IF(M209="","",IF($H209=$I209,IF(OR(AND($G209="Higher is better",M209>=$H209),AND($G209="Lower is better",M209<=$H209)),A_Scoring_Model!$C$14,0),IF($G209="Higher is better",IF(M209>=$H209,A_Scoring_Model!$C$14,IF(M209<$I209,0,A_Scoring_Model!$C$15+(A_Scoring_Model!$C$14-A_Scoring_Model!$C$15)*(M209-$I209)/($H209-$I209))),IF(M209<=$H209,A_Scoring_Model!$C$14,IF(M209>$I209,0,A_Scoring_Model!$C$15+(A_Scoring_Model!$C$14-A_Scoring_Model!$C$15)*($I209-M209)/($I209-$H209))))))
A210: =C_KPI_Benchmark!A210 -> 4.a-D4-10 | B210: =C_KPI_Benchmark!D210 -> 4.a | C210: =C_KPI_Benchmark!E210 -> IaC Provisioner Agent | D210: =C_KPI_Benchmark!F210 -> D4 | E210: =C_KPI_Benchmark!J210 -> Idempotent re-apply (no diff) | F210: =C_KPI_Benchmark!K210 -> % | G210: =C_KPI_Benchmark!L210 -> Higher is better | H210: =C_KPI_Benchmark!N210 -> 1 | I210: =IF(C_KPI_Benchmark!O210<>"",C_KPI_Benchmark!O210,IF(G210="Higher is better",H210*(1-A_Scoring_Model!$C$16),H210*(1+A_Scoring_Model!$C$16))) -> 0.8 | N210: =IF(J210="","",IF($H210=$I210,IF(OR(AND($G210="Higher is better",J210>=$H210),AND($G210="Lower is better",J210<=$H210)),A_Scoring_Model!$C$14,0),IF($G210="Higher is better",IF(J210>=$H210,A_Scoring_Model!$C$14,IF(J210<$I210,0,A_Scoring_Model!$C$15+(A_Scoring_Model!$C$14-A_Scoring_Model!$C$15)*(J210-$I210)/($H210-$I210))),IF(J210<=$H210,A_Scoring_Model!$C$14,IF(J210>$I210,0,A_Scoring_Model!$C$15+(A_Scoring_Model!$C$14-A_Scoring_Model!$C$15)*($I210-J210)/($I210-$H210)))))) | O210: =IF(K210="","",IF($H210=$I210,IF(OR(AND($G210="Higher is better",K210>=$H210),AND($G210="Lower is better",K210<=$H210)),A_Scoring_Model!$C$14,0),IF($G210="Higher is better",IF(K210>=$H210,A_Scoring_Model!$C$14,IF(K210<$I210,0,A_Scoring_Model!$C$15+(A_Scoring_Model!$C$14-A_Scoring_Model!$C$15)*(K210-$I210)/($H210-$I210))),IF(K210<=$H210,A_Scoring_Model!$C$14,IF(K210>$I210,0,A_Scoring_Model!$C$15+(A_Scoring_Model!$C$14-A_Scoring_Model!$C$15)*($I210-K210)/($I210-$H210)))))) | P210: =IF(L210="","",IF($H210=$I210,IF(OR(AND($G210="Higher is better",L210>=$H210),AND($G210="Lower is better",L210<=$H210)),A_Scoring_Model!$C$14,0),IF($G210="Higher is better",IF(L210>=$H210,A_Scoring_Model!$C$14,IF(L210<$I210,0,A_Scoring_Model!$C$15+(A_Scoring_Model!$C$14-A_Scoring_Model!$C$15)*(L210-$I210)/($H210-$I210))),IF(L210<=$H210,A_Scoring_Model!$C$14,IF(L210>$I210,0,A_Scoring_Model!$C$15+(A_Scoring_Model!$C$14-A_Scoring_Model!$C$15)*($I210-L210)/($I210-$H210)))))) | Q210: =IF(M210="","",IF($H210=$I210,IF(OR(AND($G210="Higher is better",M210>=$H210),AND($G210="Lower is better",M210<=$H210)),A_Scoring_Model!$C$14,0),IF($G210="Higher is better",IF(M210>=$H210,A_Scoring_Model!$C$14,IF(M210<$I210,0,A_Scoring_Model!$C$15+(A_Scoring_Model!$C$14-A_Scoring_Model!$C$15)*(M210-$I210)/($H210-$I210))),IF(M210<=$H210,A_Scoring_Model!$C$14,IF(M210>$I210,0,A_Scoring_Model!$C$15+(A_Scoring_Model!$C$14-A_Scoring_Model!$C$15)*($I210-M210)/($I210-$H210))))))
A211: =C_KPI_Benchmark!A211 -> 4.a-D4-11 | B211: =C_KPI_Benchmark!D211 -> 4.a | C211: =C_KPI_Benchmark!E211 -> IaC Provisioner Agent | D211: =C_KPI_Benchmark!F211 -> D4 | E211: =C_KPI_Benchmark!J211 -> Destroy / rollback success | F211: =C_KPI_Benchmark!K211 -> % | G211: =C_KPI_Benchmark!L211 -> Higher is better | H211: =C_KPI_Benchmark!N211 -> 1 | I211: =IF(C_KPI_Benchmark!O211<>"",C_KPI_Benchmark!O211,IF(G211="Higher is better",H211*(1-A_Scoring_Model!$C$16),H211*(1+A_Scoring_Model!$C$16))) -> 0.8 | N211: =IF(J211="","",IF($H211=$I211,IF(OR(AND($G211="Higher is better",J211>=$H211),AND($G211="Lower is better",J211<=$H211)),A_Scoring_Model!$C$14,0),IF($G211="Higher is better",IF(J211>=$H211,A_Scoring_Model!$C$14,IF(J211<$I211,0,A_Scoring_Model!$C$15+(A_Scoring_Model!$C$14-A_Scoring_Model!$C$15)*(J211-$I211)/($H211-$I211))),IF(J211<=$H211,A_Scoring_Model!$C$14,IF(J211>$I211,0,A_Scoring_Model!$C$15+(A_Scoring_Model!$C$14-A_Scoring_Model!$C$15)*($I211-J211)/($I211-$H211)))))) | O211: =IF(K211="","",IF($H211=$I211,IF(OR(AND($G211="Higher is better",K211>=$H211),AND($G211="Lower is better",K211<=$H211)),A_Scoring_Model!$C$14,0),IF($G211="Higher is better",IF(K211>=$H211,A_Scoring_Model!$C$14,IF(K211<$I211,0,A_Scoring_Model!$C$15+(A_Scoring_Model!$C$14-A_Scoring_Model!$C$15)*(K211-$I211)/($H211-$I211))),IF(K211<=$H211,A_Scoring_Model!$C$14,IF(K211>$I211,0,A_Scoring_Model!$C$15+(A_Scoring_Model!$C$14-A_Scoring_Model!$C$15)*($I211-K211)/($I211-$H211)))))) | P211: =IF(L211="","",IF($H211=$I211,IF(OR(AND($G211="Higher is better",L211>=$H211),AND($G211="Lower is better",L211<=$H211)),A_Scoring_Model!$C$14,0),IF($G211="Higher is better",IF(L211>=$H211,A_Scoring_Model!$C$14,IF(L211<$I211,0,A_Scoring_Model!$C$15+(A_Scoring_Model!$C$14-A_Scoring_Model!$C$15)*(L211-$I211)/($H211-$I211))),IF(L211<=$H211,A_Scoring_Model!$C$14,IF(L211>$I211,0,A_Scoring_Model!$C$15+(A_Scoring_Model!$C$14-A_Scoring_Model!$C$15)*($I211-L211)/($I211-$H211)))))) | Q211: =IF(M211="","",IF($H211=$I211,IF(OR(AND($G211="Higher is better",M211>=$H211),AND($G211="Lower is better",M211<=$H211)),A_Scoring_Model!$C$14,0),IF($G211="Higher is better",IF(M211>=$H211,A_Scoring_Model!$C$14,IF(M211<$I211,0,A_Scoring_Model!$C$15+(A_Scoring_Model!$C$14-A_Scoring_Model!$C$15)*(M211-$I211)/($H211-$I211))),IF(M211<=$H211,A_Scoring_Model!$C$14,IF(M211>$I211,0,A_Scoring_Model!$C$15+(A_Scoring_Model!$C$14-A_Scoring_Model!$C$15)*($I211-M211)/($I211-$H211))))))
A212: =C_KPI_Benchmark!A212 -> 4.a-D4-12 | B212: =C_KPI_Benchmark!D212 -> 4.a | C212: =C_KPI_Benchmark!E212 -> IaC Provisioner Agent | D212: =C_KPI_Benchmark!F212 -> D4 | E212: =C_KPI_Benchmark!J212 -> Service availability | F212: =C_KPI_Benchmark!K212 -> % | G212: =C_KPI_Benchmark!L212 -> Higher is better | H212: =C_KPI_Benchmark!N212 -> 0.995 | I212: =IF(C_KPI_Benchmark!O212<>"",C_KPI_Benchmark!O212,IF(G212="Higher is better",H212*(1-A_Scoring_Model!$C$16),H212*(1+A_Scoring_Model!$C$16))) -> 0.99 | N212: =IF(J212="","",IF($H212=$I212,IF(OR(AND($G212="Higher is better",J212>=$H212),AND($G212="Lower is better",J212<=$H212)),A_Scoring_Model!$C$14,0),IF($G212="Higher is better",IF(J212>=$H212,A_Scoring_Model!$C$14,IF(J212<$I212,0,A_Scoring_Model!$C$15+(A_Scoring_Model!$C$14-A_Scoring_Model!$C$15)*(J212-$I212)/($H212-$I212))),IF(J212<=$H212,A_Scoring_Model!$C$14,IF(J212>$I212,0,A_Scoring_Model!$C$15+(A_Scoring_Model!$C$14-A_Scoring_Model!$C$15)*($I212-J212)/($I212-$H212)))))) | O212: =IF(K212="","",IF($H212=$I212,IF(OR(AND($G212="Higher is better",K212>=$H212),AND($G212="Lower is better",K212<=$H212)),A_Scoring_Model!$C$14,0),IF($G212="Higher is better",IF(K212>=$H212,A_Scoring_Model!$C$14,IF(K212<$I212,0,A_Scoring_Model!$C$15+(A_Scoring_Model!$C$14-A_Scoring_Model!$C$15)*(K212-$I212)/($H212-$I212))),IF(K212<=$H212,A_Scoring_Model!$C$14,IF(K212>$I212,0,A_Scoring_Model!$C$15+(A_Scoring_Model!$C$14-A_Scoring_Model!$C$15)*($I212-K212)/($I212-$H212)))))) | P212: =IF(L212="","",IF($H212=$I212,IF(OR(AND($G212="Higher is better",L212>=$H212),AND($G212="Lower is better",L212<=$H212)),A_Scoring_Model!$C$14,0),IF($G212="Higher is better",IF(L212>=$H212,A_Scoring_Model!$C$14,IF(L212<$I212,0,A_Scoring_Model!$C$15+(A_Scoring_Model!$C$14-A_Scoring_Model!$C$15)*(L212-$I212)/($H212-$I212))),IF(L212<=$H212,A_Scoring_Model!$C$14,IF(L212>$I212,0,A_Scoring_Model!$C$15+(A_Scoring_Model!$C$14-A_Scoring_Model!$C$15)*($I212-L212)/($I212-$H212)))))) | Q212: =IF(M212="","",IF($H212=$I212,IF(OR(AND($G212="Higher is better",M212>=$H212),AND($G212="Lower is better",M212<=$H212)),A_Scoring_Model!$C$14,0),IF($G212="Higher is better",IF(M212>=$H212,A_Scoring_Model!$C$14,IF(M212<$I212,0,A_Scoring_Model!$C$15+(A_Scoring_Model!$C$14-A_Scoring_Model!$C$15)*(M212-$I212)/($H212-$I212))),IF(M212<=$H212,A_Scoring_Model!$C$14,IF(M212>$I212,0,A_Scoring_Model!$C$15+(A_Scoring_Model!$C$14-A_Scoring_Model!$C$15)*($I212-M212)/($I212-$H212))))))
... A546: =C_KPI_Benchmark!A546 -> 10.c-D6-17 | B546: =C_KPI_Benchmark!D546 -> 10.c | C546: =C_KPI_Benchmark!E546 -> Hotfix Triage & MLOps Pipeline | D546: =C_KPI_Benchmark!F546 -> D6 | E546: =C_KPI_Benchmark!J546 -> Named owner and support SLA | F546: =C_KPI_Benchmark!K546 -> Yes/No | G546: =C_KPI_Benchmark!L546 -> Higher is better | H546: =C_KPI_Benchmark!N546 -> 1 | I546: =IF(C_KPI_Benchmark!O546<>"",C_KPI_Benchmark!O546,IF(G546="Higher is better",H546*(1-A_Scoring_Model!$C$16),H546*(1+A_Scoring_Model!$C$16))) -> 0.8 | N546: =IF(J546="","",IF($H546=$I546,IF(OR(AND($G546="Higher is better",J546>=$H546),AND($G546="Lower is better",J546<=$H546)),A_Scoring_Model!$C$14,0),IF($G546="Higher is better",IF(J546>=$H546,A_Scoring_Model!$C$14,IF(J546<$I546,0,A_Scoring_Model!$C$15+(A_Scoring_Model!$C$14-A_Scoring_Model!$C$15)*(J546-$I546)/($H546-$I546))),IF(J546<=$H546,A_Scoring_Model!$C$14,IF(J546>$I546,0,A_Scoring_Model!$C$15+(A_Scoring_Model!$C$14-A_Scoring_Model!$C$15)*($I546-J546)/($I546-$H546)))))) | O546: =IF(K546="","",IF($H546=$I546,IF(OR(AND($G546="Higher is better",K546>=$H546),AND($G546="Lower is better",K546<=$H546)),A_Scoring_Model!$C$14,0),IF($G546="Higher is better",IF(K546>=$H546,A_Scoring_Model!$C$14,IF(K546<$I546,0,A_Scoring_Model!$C$15+(A_Scoring_Model!$C$14-A_Scoring_Model!$C$15)*(K546-$I546)/($H546-$I546))),IF(K546<=$H546,A_Scoring_Model!$C$14,IF(K546>$I546,0,A_Scoring_Model!$C$15+(A_Scoring_Model!$C$14-A_Scoring_Model!$C$15)*($I546-K546)/($I546-$H546)))))) | P546: =IF(L546="","",IF($H546=$I546,IF(OR(AND($G546="Higher is better",L546>=$H546),AND($G546="Lower is better",L546<=$H546)),A_Scoring_Model!$C$14,0),IF($G546="Higher is better",IF(L546>=$H546,A_Scoring_Model!$C$14,IF(L546<$I546,0,A_Scoring_Model!$C$15+(A_Scoring_Model!$C$14-A_Scoring_Model!$C$15)*(L546-$I546)/($H546-$I546))),IF(L546<=$H546,A_Scoring_Model!$C$14,IF(L546>$I546,0,A_Scoring_Model!$C$15+(A_Scoring_Model!$C$14-A_Scoring_Model!$C$15)*($I546-L546)/($I546-$H546)))))) | Q546: =IF(M546="","",IF($H546=$I546,IF(OR(AND($G546="Higher is better",M546>=$H546),AND($G546="Lower is better",M546<=$H546)),A_Scoring_Model!$C$14,0),IF($G546="Higher is better",IF(M546>=$H546,A_Scoring_Model!$C$14,IF(M546<$I546,0,A_Scoring_Model!$C$15+(A_Scoring_Model!$C$14-A_Scoring_Model!$C$15)*(M546-$I546)/($H546-$I546))),IF(M546<=$H546,A_Scoring_Model!$C$14,IF(M546>$I546,0,A_Scoring_Model!$C$15+(A_Scoring_Model!$C$14-A_Scoring_Model!$C$15)*($I546-M546)/($I546-$H546))))))

Sheet E_Scorecard
A1: E · Ranking scorecard — grp1 vs grp2 vs grp3 per L3 component
A2: Dimension score = mean of measured KPI scores · Composite needs all six dimensions · Gates G1–G4, G6 are inputs (Y/N); G5 is computed
A4: L3 ID | B4: L3 component | C4: Group | D4: KPIs measured | E4: KPIs total | F4: D1 | G4: D2 | H4: D3 | I4: D4 | J4: D5 | K4: D6 | L4: Composite | M4: G1 | N4: G2 | O4: G3 | P4: G4 | Q4: G5 (auto) | R4: G6 | S4: All gates | T4: Tier | U4: Rank | V4: Key
A5: 1.a | B5: NL Req Parsing & Classification Agent | C5: grp1 | D5: =COUNTIFS(E_Measurements!$B$5:$B$546,A5,E_Measurements!$J$5:$J$546,"<>") -> 19 | E5: =COUNTIF(E_Measurements!$B$5:$B$546,A5) -> 19 | F5: =IFERROR(AVERAGEIFS(E_Measurements!$N$5:$N$546,E_Measurements!$B$5:$B$546,$A5,E_Measurements!$D$5:$D$546,"D1"),"") -> 80.952381 | G5: =IFERROR(AVERAGEIFS(E_Measurements!$N$5:$N$546,E_Measurements!$B$5:$B$546,$A5,E_Measurements!$D$5:$D$546,"D2"),"") -> 86.666667 | H5: =IFERROR(AVERAGEIFS(E_Measurements!$N$5:$N$546,E_Measurements!$B$5:$B$546,$A5,E_Measurements!$D$5:$D$546,"D3"),"") -> 79.666667 | I5: =IFERROR(AVERAGEIFS(E_Measurements!$N$5:$N$546,E_Measurements!$B$5:$B$546,$A5,E_Measurements!$D$5:$D$546,"D4"),"") -> 79.958763 | J5: =IFERROR(AVERAGEIFS(E_Measurements!$N$5:$N$546,E_Measurements!$B$5:$B$546,$A5,E_Measurements!$D$5:$D$546,"D5"),"") -> 80.784314 | K5: =IFERROR(AVERAGEIFS(E_Measurements!$N$5:$N$546,E_Measurements!$B$5:$B$546,$A5,E_Measurements!$D$5:$D$546,"D6"),"") -> 96 | L5: =IF(COUNT(F5:K5)<6,"",F5*A_Scoring_Model!$C$5+G5*A_Scoring_Model!$C$6+H5*A_Scoring_Model!$C$7+I5*A_Scoring_Model!$C$8+J5*A_Scoring_Model!$C$9+K5*A_Scoring_Model!$C$10) -> 83.282571 | M5: Y | N5: Y | O5: Y | P5: Y | Q5: =IF(F5="","",IF(COUNTIFS(E_Measurements!$B$5:$B$546,A5,E_Measurements!$D$5:$D$546,"D1",E_Measurements!$N$5:$N$546,0)>0,"N","Y")) -> Y | R5: Y | S5: =IF(COUNTIF(M5:R5,"Y")=6,"Y","N") -> Y | T5: =IF(L5="","",IF(OR(S5<>"Y",L5<A_Scoring_Model!$C$33),"Not eligible",IF(L5>=A_Scoring_Model!$C$30,"Tier 1 · Certified",IF(L5>=A_Scoring_Model!$C$31,"Tier 2 · Conditional",IF(L5>=A_Scoring_Model!$C$32,"Tier 3 · Group-local","Tier 4 · Rework"))))) -> Tier 2 · Conditional | U5: =IF(OR(L5="",S5<>"Y"),"",COUNTIFS($A$5:$A$95,A5,$S$5:$S$95,"Y",$L$5:$L$95,">"&L5)+1) -> 2 | V5: =A5&"|"&U5 -> 1.a|2
A6: 1.a | B6: NL Req Parsing & Classification Agent | C6: grp2 | D6: =COUNTIFS(E_Measurements!$B$5:$B$546,A6,E_Measurements!$K$5:$K$546,"<>") -> 19 | E6: =COUNTIF(E_Measurements!$B$5:$B$546,A6) -> 19 | F6: =IFERROR(AVERAGEIFS(E_Measurements!$O$5:$O$546,E_Measurements!$B$5:$B$546,$A6,E_Measurements!$D$5:$D$546,"D1"),"") -> 100 | G6: =IFERROR(AVERAGEIFS(E_Measurements!$O$5:$O$546,E_Measurements!$B$5:$B$546,$A6,E_Measurements!$D$5:$D$546,"D2"),"") -> 0 | H6: =IFERROR(AVERAGEIFS(E_Measurements!$O$5:$O$546,E_Measurements!$B$5:$B$546,$A6,E_Measurements!$D$5:$D$546,"D3"),"") -> 100 | I6: =IFERROR(AVERAGEIFS(E_Measurements!$O$5:$O$546,E_Measurements!$B$5:$B$546,$A6,E_Measurements!$D$5:$D$546,"D4"),"") -> 86.666667 | J6: =IFERROR(AVERAGEIFS(E_Measurements!$O$5:$O$546,E_Measurements!$B$5:$B$546,$A6,E_Measurements!$D$5:$D$546,"D5"),"") -> 100 | K6: =IFERROR(AVERAGEIFS(E_Measurements!$O$5:$O$546,E_Measurements!$B$5:$B$546,$A6,E_Measurements!$D$5:$D$546,"D6"),"") -> 54 | L6: =IF(COUNT(F6:K6)<6,"",F6*A_Scoring_Model!$C$5+G6*A_Scoring_Model!$C$6+H6*A_Scoring_Model!$C$7+I6*A_Scoring_Model!$C$8+J6*A_Scoring_Model!$C$9+K6*A_Scoring_Model!$C$10) -> 74.066667 | M6: Y | N6: Y | O6: Y | P6: Y | Q6: =IF(F6="","",IF(COUNTIFS(E_Measurements!$B$5:$B$546,A6,E_Measurements!$D$5:$D$546,"D1",E_Measurements!$O$5:$O$546,0)>0,"N","Y")) -> Y | R6: Y | S6: =IF(COUNTIF(M6:R6,"Y")=6,"Y","N") -> Y | T6: =IF(L6="","",IF(OR(S6<>"Y",L6<A_Scoring_Model!$C$33),"Not eligible",IF(L6>=A_Scoring_Model!$C$30,"Tier 1 · Certified",IF(L6>=A_Scoring_Model!$C$31,"Tier 2 · Conditional",IF(L6>=A_Scoring_Model!$C$32,"Tier 3 · Group-local","Tier 4 · Rework"))))) -> Tier 3 · Group-local | U6: =IF(OR(L6="",S6<>"Y"),"",COUNTIFS($A$5:$A$95,A6,$S$5:$S$95,"Y",$L$5:$L$95,">"&L6)+1) -> 3 | V6: =A6&"|"&U6 -> 1.a|3
A7: 1.a | B7: NL Req Parsing & Classification Agent | C7: grp3 | D7: =COUNTIFS(E_Measurements!$B$5:$B$546,A7,E_Measurements!$L$5:$L$546,"<>") -> 19 | E7: =COUNTIF(E_Measurements!$B$5:$B$546,A7) -> 19 | F7: =IFERROR(AVERAGEIFS(E_Measurements!$P$5:$P$546,E_Measurements!$B$5:$B$546,$A7,E_Measurements!$D$5:$D$546,"D1"),"") -> 92.857143 | G7: =IFERROR(AVERAGEIFS(E_Measurements!$P$5:$P$546,E_Measurements!$B$5:$B$546,$A7,E_Measurements!$D$5:$D$546,"D2"),"") -> 100 | H7: =IFERROR(AVERAGEIFS(E_Measurements!$P$5:$P$546,E_Measurements!$B$5:$B$546,$A7,E_Measurements!$D$5:$D$546,"D3"),"") -> 93.944444 | I7: =IFERROR(AVERAGEIFS(E_Measurements!$P$5:$P$546,E_Measurements!$B$5:$B$546,$A7,E_Measurements!$D$5:$D$546,"D4"),"") -> 93.333333 | J7: =IFERROR(AVERAGEIFS(E_Measurements!$P$5:$P$546,E_Measurements!$B$5:$B$546,$A7,E_Measurements!$D$5:$D$546,"D5"),"") -> 93.823529 | K7: =IFERROR(AVERAGEIFS(E_Measurements!$P$5:$P$546,E_Measurements!$B$5:$B$546,$A7,E_Measurements!$D$5:$D$546,"D6"),"") -> 99.2 | L7: =IF(COUNT(F7:K7)<6,"",F7*A_Scoring_Model!$C$5+G7*A_Scoring_Model!$C$6+H7*A_Scoring_Model!$C$7+I7*A_Scoring_Model!$C$8+J7*A_Scoring_Model!$C$9+K7*A_Scoring_Model!$C$10) -> 95.275672 | M7: Y | N7: Y | O7: Y | P7: Y | Q7: =IF(F7="","",IF(COUNTIFS(E_Measurements!$B$5:$B$546,A7,E_Measurements!$D$5:$D$546,"D1",E_Measurements!$P$5:$P$546,0)>0,"N","Y")) -> Y | R7: Y | S7: =IF(COUNTIF(M7:R7,"Y")=6,"Y","N") -> Y | T7: =IF(L7="","",IF(OR(S7<>"Y",L7<A_Scoring_Model!$C$33),"Not eligible",IF(L7>=A_Scoring_Model!$C$30,"Tier 1 · Certified",IF(L7>=A_Scoring_Model!$C$31,"Tier 2 · Conditional",IF(L7>=A_Scoring_Model!$C$32,"Tier 3 · Group-local","Tier 4 · Rework"))))) -> Tier 1 · Certified | U7: =IF(OR(L7="",S7<>"Y"),"",COUNTIFS($A$5:$A$95,A7,$S$5:$S$95,"Y",$L$5:$L$95,">"&L7)+1) -> 1 | V7: =A7&"|"&U7 -> 1.a|1
